Workbook
Name DATA_GESTAO: '02. PARÂMETROS'!$B$5
Name FERIADOS_342: '02. PARÂMETROS'!$F$18:$F$40
Name FERIADOS_343: '02. PARÂMETROS'!$G$18:$G$40
Name FERIADOS_281: '02. PARÂMETROS'!$I$18:$I$40
Name LISTA_FRENTES: '02. PARÂMETROS'!$A$45:$A$121
Name LISTA_CAUSAS: '02. PARÂMETROS'!$E$45:$E$52

Sheet 00. GUIA
A1: TAF — GESTÃO DA EMPRESA (obras 342, 343 e 281) | E1: ◀ MENU
A2: Mesma arquitetura da WCR - GESTÃO DA EMPRESA. Comece pelo 00A. MENU.
A4: O que é | B4: A gestão da TAF em um arquivo: o que foi contratado (03), o plano de cada obra (04: 342 do estudo REV13, 343 do MOTOR TAF, 281 do cronograma da SANEAGO), o que aconteceu (05 a 08) e a comparação (08A a 12), com o MASTER CHECK no painel.
A5: Cores | B5: Azul = digitar. Preto = fórmula. Verde = vem de outra aba. Amarelo = falta dado ou decisão. Aba verde = dia a dia; cinza = só leitura; âmbar = ajuste eventual.
A6: Rotina da segunda | B6: 02 (data de corte) → 05B (apontamento da semana conferido) → 05C (restrições com dono e prazo) → 05A (compromisso da próxima semana, confirmado pelo engenheiro na sexta) → 01A (10 perguntas e 3 luzes) → PAUTA (1 decisão por obra).
A7: Fechamento do mês | B7: 06 (BM) → 07 (NF) → 08 (custos pagos) → 08A/08C (desvio e resultado) → 10 (caixa).
A8: Plano | B8: 342: plano do estudo REV13 (interno, pasta panorama do projeto), cenário 1 eventograma Anexo VII, copiado em azul na 04 com fonte. 343: MOTOR TAF. Plano novo: copiar de novo na 04 e conferir a 13. CHECKS e a CHECKS DA OPERAÇÃO. 281: cronograma físico-financeiro da SANEAGO (Cronograma FF x Gráficos) na 04, linhas 40 a 50; BMs 1 a 7 na 06; NFs da Medição 02 na 07; custos do consórcio TAF TECNOBOMBAS até maio/2026 na 08D, somados por mês e conta na 08. Obra gerida a 100% do contrato; a parte da TAF fica na 03 (F22). Ainda sem orçamento de custo, por isso margem e caixa da 281 aparecem SEM BASE.
A9: Atenção 342 | B9: O plano da 342 é o estudo REV13 sobre o eventograma Anexo VII (UN só mede na conclusão). R$ 993 mil do custo ainda estão sem cotação da TAF (SEM BASE), por isso o resultado aparece como SEM BASE no painel. Resultado e caixa da 342 são números internos.
A10: ROTINA — todo dia (engenheiro residente / apontador) | B10: Lançar o dia na 05B até 9h do dia seguinte: data, obra, frente, pessoas, serviço, quantidade e paradas com motivo. Foto de avanço de cada frente. Comparar o dia com o ritmo-alvo (343: 80 m/dia de PEAD, 10 m/dia de FoFo); se cair 2 dias seguidos, escalar na hora.
A11: ROTINA — toda segunda (gerente de contrato, Tiago) | B11: Sexta: o engenheiro confirma o compromisso da próxima semana na 05A e marca o que cumpriu. Segunda: PPC, efetivo e restrições na 01A; 1 causa por desvio (MO → planejamento → material → equipamento → projeto → cliente); 1 decisão por obra com dono e prazo.
A12: ROTINA — todo mês (diretoria, Thadeu) | B12: 01. PAINEL → MASTER CHECK antes de qualquer número. Fechar medição (06/07/08). Medido × previsto do plano (04): desvio > 10% vira pauta. Nunca decidir com número pendente: buscar o dado.
A16: ABRIR O MENU

Sheet 00A. MENU
A1: TAF — MENU
A2: Clique no botão para ir. Em toda aba, '◀ MENU' (canto superior direito) volta para cá.
A4: VISÃO | B4: 01 PAINEL | D4: 01C PLACAR SEMANAL | F4: 13 CHECKS
A6: CONTRATO E PLANO | B6: 02 PARÂMETROS | D6: 03 CONTRATOS | F6: 04 PLANO DAS OBRAS
A8: DIA A DIA | B8: 05 SEMANAS | D8: 06 MEDIÇÃO (BM) | F8: 07 NF E RECEBIMENTO | H8: 08 CUSTOS
A10: RESULTADO | B10: 08A CUSTO POR OBRA | D10: 08B TODAS AS OBRAS | F10: 08C RESULTADO | H10: 10 CAIXA | J10: 12 EVM
A12: REFERÊNCIA | B12: 00 GUIA | D12: 14 FONTES | F12: 15 CHANGELOG
A14: ROTEIRO DE USO
A15: TODA SEGUNDA (reunião, 90 min) | B15: 02: mude a data de corte | C15: → | D15: 05B e 05C: apontamento e restrições | E15: → | F15: 05A: compromisso da semana | G15: → | H15: 01A: 10 perguntas e 3 luzes | I15: → | J15: PAUTA: 1 decisão por obra
A17: TODO MÊS (fechamento) | B17: 06: lance o BM | C17: → | D17: 07: lance a NF | E17: → | F17: 08: lance os custos pagos | G17: → | H17: 08A e 08C: desvio e resultado | I17: → | J17: 10: caixa previsto × real
A19: QUANDO O PLANO MUDA | B19: 342: estudo novo (pasta panorama) · 343: MOTOR TAF | C19: → | D19: 343: rodar_taf.py | E19: → | F19: copiar na 04 (azul, com fonte) | G19: → | H19: 13: estudo em uso confere | I19: → | J19: 04 e 12: plano novo e EVM
A21: COMO FUNCIONA — da medição ao dinheiro (quem faz)
A22: Encarregado: executa e aponta | B22: → | C22: Engenheiro: monta o BM do mês | D22: → | E22: ◆ BM aprovado pelo fiscal? | F22: SIM → | G22: Administrativo: emite a NF (342: até o último dia útil do mês; 343: protocola no 1º dia útil) | H22: → | I22: Diretoria: confere o crédito em 30 dias (07)
E23: NÃO ↓ corrigir a memória de cálculo e reapresentar (06: situação EM ELABORAÇÃO)
A25: COMO FUNCIONA — do custo ao pagamento
A26: Compra ou folha | B26: → | C26: ◆ Tem obra e conta? | D26: SIM → | E26: Administrativo: lança na 08 e paga | F26: → | G26: Diretoria: lê a 08A (desvio por conta)
C27: NÃO ↓ não paga sem obra e conta (13. CHECKS acusa)
A29: OPERAÇÃO (rev1) | B29: 00A CICLO | D29: CRONOGRAMA | F29: HISTOGRAMA | H29: FLUXO PROJETADO
A31: OPERAÇÃO (rev1) | B31: DASHBOARD BI | D31: PAUTA DE SEGUNDA | F31: LINHA DE BASE | H31: CHECKS DA OPERAÇÃO
A33: GESTÃO (rev2) | B33: 01A GESTÃO DA SEMANA | D33: 05A COMPROMISSO | F33: 05B APONTAMENTO | H33: 05C RESTRIÇÕES
A35: OBRA 281 (rev3) | B35: 08D LANÇAMENTOS 281 | D35: 03 CONTRATOS (281)

Sheet 00A. CICLO DA OBRA
A2: CICLO DA OBRA: do orçamento ao caixa, na ordem
A3: Siga a ordem. Cada etapa lê a anterior. As duas últimas colunas mostram a situação de cada obra agora (fórmulas).
A5: Etapa | B5: O que responde | C5: Quem | D5: Quando | E5: Onde (clique) | F5: 342 agora | G5: 343 agora
A6: 1. Viabilidade e orçamento | B6: A obra cabe no contrato? Qual o custo previsto? | C6: Diretoria | D6: Antes de assinar; revisar se o contrato mudar | E6: FLUXO PROJETADO TAF | F6: ="Contrato R$ "&FIXED('03. CONTRATOS'!$B$8,0)&" · saídas previstas R$ "&FIXED('FLUXO PROJETADO TAF'!$S$32,0)&" · o estudo interno estima resultado após tributos de R$ "&FIXED('FLUXO PROJETADO TAF'!$C$19,0) -> Contrato R$ 3,258,000 · saídas previstas R$ 3,212,459 · o estudo interno estima resultado após tributos de R$ -231,416 | G6: ="Contrato R$ "&FIXED('03. CONTRATOS'!$D$8,0)&" · custo previsto R$ "&FIXED('04. PLANO DAS OBRAS'!$D$30,0)&" · o estudo interno estima resultado após tributos de R$ "&FIXED('04. PLANO DAS OBRAS'!$D$31,0)&IF(AND(ABS(N('04. PLANO DAS OBRAS'!$D$30)-N('04. PLANO DAS OBRAS'!$S$24)-N('13. CHECKS'!$E$16))>1,ABS(N('04. PLANO DAS OBRAS'!$D$30)-N('04. PLANO DAS OBRAS'!$S$24))>1)," (custo sem conferência na 04)",IF(ABS(N('04. PLANO DAS OBRAS'!$D$30)-N('04. PLANO DAS OBRAS'!$S$24))>1," (o caixa ainda não tem R$ "&FIXED(N('04. PLANO DAS OBRAS'!$D$30)-N('04. PLANO DAS OBRAS'!$S$24),0)&" desse custo: 05C R101)","")) -> Contrato R$ 5,226,634 · custo previsto R$ 3,702,036 · o estudo interno estima resultado após tributos de R$ 1,080,334 (o caixa ainda não tem R$ 96,418 desse custo: 05C R101)
A7: 2. Cronograma | B7: Quais etapas, em que datas, em que ordem? O que é crítico? | C7: Planejador e engenheiro residente | D7: No início; revisar todo mês | E7: CRONOGRAMA PROJECT | F7: ="Etapas: "&COUNTIFS('CRONOGRAMA PROJECT'!$B$7:$B$27,"342",'CRONOGRAMA PROJECT'!$BV$7:$BV$27,"Contrato")&" · "&TEXT(DAY(_xlfn.MINIFS('CRONOGRAMA PROJECT'!$D$7:$D$27,'CRONOGRAMA PROJECT'!$BW$7:$BW$27,"342")),"00")&"/"&TEXT(MONTH(_xlfn.MINIFS('CRONOGRAMA PROJECT'!$D$7:$D$27,'CRONOGRAMA PROJECT'!$BW$7:$BW$27,"342")),"00")&"/"&RIGHT(YEAR(_xlfn.MINIFS('CRONOGRAMA PROJECT'!$D$7:$D$27,'CRONOGRAMA PROJECT'!$BW$7:$BW$27,"342")),2)&" a "&TEXT(DAY(_xlfn.MAXIFS('CRONOGRAMA PROJECT'!$E$7:$E$27,'CRONOGRAMA PROJECT'!$BW$7:$BW$27,"342")),"00")&"/"&TEXT(MONTH(_xlfn.MAXIFS('CRONOGRAMA PROJECT'!$E$7:$E$27,'CRONOGRAMA PROJECT'!$BW$7:$BW$27,"342")),"00")&"/"&RIGHT(YEAR(_xlfn.MAXIFS('CRONOGRAMA PROJECT'!$E$7:$E$27,'CRONOGRAMA PROJECT'!$BW$7:$BW$27,"342")),2)&" · sem predecessora: "&COUNTIFS('CRONOGRAMA PROJECT'!$B$7:$B$27,"342",'CRONOGRAMA PROJECT'!$BV$7:$BV$27,"Contrato",'CRONOGRAMA PROJECT'!$G$7:$G$27,"",'CRONOGRAMA PROJECT'!$H$7:$H$27,"",'CRONOGRAMA PROJECT'!$I$7:$I$27,"") -> Etapas: 11 · 03/09/26 a 27/08/27 · sem predecessora: 11 | G7: ="Etapas: "&COUNTIFS('CRONOGRAMA PROJECT'!$B$7:$B$27,"343",'CRONOGRAMA PROJECT'!$BV$7:$BV$27,"Contrato")&" · "&TEXT(DAY(_xlfn.MINIFS('CRONOGRAMA PROJECT'!$D$7:$D$27,'CRONOGRAMA PROJECT'!$BW$7:$BW$27,"343")),"00")&"/"&TEXT(MONTH(_xlfn.MINIFS('CRONOGRAMA PROJECT'!$D$7:$D$27,'CRONOGRAMA PROJECT'!$BW$7:$BW$27,"343")),"00")&"/"&RIGHT(YEAR(_xlfn.MINIFS('CRONOGRAMA PROJECT'!$D$7:$D$27,'CRONOGRAMA PROJECT'!$BW$7:$BW$27,"343")),2)&" a "&TEXT(DAY(_xlfn.MAXIFS('CRONOGRAMA PROJECT'!$E$7:$E$27,'CRONOGRAMA PROJECT'!$BW$7:$BW$27,"343")),"00")&"/"&TEXT(MONTH(_xlfn.MAXIFS('CRONOGRAMA PROJECT'!$E$7:$E$27,'CRONOGRAMA PROJECT'!$BW$7:$BW$27,"343")),"00")&"/"&RIGHT(YEAR(_xlfn.MAXIFS('CRONOGRAMA PROJECT'!$E$7:$E$27,'CRONOGRAMA PROJECT'!$BW$7:$BW$27,"343")),2)&" · sem predecessora: "&COUNTIFS('CRONOGRAMA PROJECT'!$B$7:$B$27,"343",'CRONOGRAMA PROJECT'!$BV$7:$BV$27,"Contrato",'CRONOGRAMA PROJECT'!$G$7:$G$27,"",'CRONOGRAMA PROJECT'!$H$7:$H$27,"",'CRONOGRAMA PROJECT'!$I$7:$I$27,"") -> Etapas: 5 · 01/09/26 a 31/05/27 · sem predecessora: 5
A8: 3. Restrições e lookahead | B8: O que falta para liberar as próximas 6 semanas? | C8: Engenheiro residente | D8: Sexta | E8: PAUTA DE SEGUNDA TAF | F8: ="Começam em 42 dias: "&COUNTIFS('CRONOGRAMA PROJECT'!$B$7:$B$27,"342",'CRONOGRAMA PROJECT'!$BV$7:$BV$27,"Contrato",'CRONOGRAMA PROJECT'!$D$7:$D$27,">"&DATA_GESTAO,'CRONOGRAMA PROJECT'!$D$7:$D$27,"<="&DATA_GESTAO+42)&" · críticas: "&IF(COUNTIFS('CRONOGRAMA PROJECT'!$B$7:$B$27,"342",'CRONOGRAMA PROJECT'!$N$7:$N$27,"sem rede")=COUNTIFS('CRONOGRAMA PROJECT'!$B$7:$B$27,"342"),"sem rede",COUNTIFS('CRONOGRAMA PROJECT'!$B$7:$B$27,"342",'CRONOGRAMA PROJECT'!$N$7:$N$27,"CRÍTICA")&IF(COUNTIFS('CRONOGRAMA PROJECT'!$B$7:$B$27,"342",'CRONOGRAMA PROJECT'!$N$7:$N$27,"sem rede")>0," ("&COUNTIFS('CRONOGRAMA PROJECT'!$B$7:$B$27,"342",'CRONOGRAMA PROJECT'!$N$7:$N$27,"sem rede")&" sem rede)",""))&" · ocorrências e pendências do cliente: "&IF(COUNTIFS('05. SEMANAS'!$A$5:$A$64,'02. PARÂMETROS'!$B$5,'05. SEMANAS'!$B$5:$B$64,"342")=0,"sem lançamento",'01C. PLACAR SEMANAL'!C11) -> Começam em 42 dias: 5 · críticas: sem rede · ocorrências e pendências do cliente: 56 | G8: ="Começam em 42 dias: "&COUNTIFS('CRONOGRAMA PROJECT'!$B$7:$B$27,"343",'CRONOGRAMA PROJECT'!$BV$7:$BV$27,"Contrato",'CRONOGRAMA PROJECT'!$D$7:$D$27,">"&DATA_GESTAO,'CRONOGRAMA PROJECT'!$D$7:$D$27,"<="&DATA_GESTAO+42)&" · críticas: "&IF(COUNTIFS('CRONOGRAMA PROJECT'!$B$7:$B$27,"343",'CRONOGRAMA PROJECT'!$N$7:$N$27,"sem rede")=COUNTIFS('CRONOGRAMA PROJECT'!$B$7:$B$27,"343"),"sem rede",COUNTIFS('CRONOGRAMA PROJECT'!$B$7:$B$27,"343",'CRONOGRAMA PROJECT'!$N$7:$N$27,"CRÍTICA")&IF(COUNTIFS('CRONOGRAMA PROJECT'!$B$7:$B$27,"343",'CRONOGRAMA PROJECT'!$N$7:$N$27,"sem rede")>0," ("&COUNTIFS('CRONOGRAMA PROJECT'!$B$7:$B$27,"343",'CRONOGRAMA PROJECT'!$N$7:$N$27,"sem rede")&" sem rede)",""))&" · ocorrências e pendências do cliente: "&IF(COUNTIFS('05. SEMANAS'!$A$5:$A$64,'02. PARÂMETROS'!$B$5,'05. SEMANAS'!$B$5:$B$64,"343")=0,"sem lançamento",'01C. PLACAR SEMANAL'!D11) -> Começam em 42 dias: 0 · críticas: sem rede · ocorrências e pendências do cliente: 11
A9: 4. Plano semanal | B9: Quanto cada equipe promete entregar na semana? | C9: Engenheiro com encarregados | D9: Sexta | E9: 05A. COMPROMISSO DA SEMANA | F9: ="PPC da semana: "&IF(COUNTIFS('05. SEMANAS'!$A$5:$A$64,'02. PARÂMETROS'!$B$5,'05. SEMANAS'!$B$5:$B$64,"342")=0,"sem lançamento",TEXT('01C. PLACAR SEMANAL'!C9,"0%")) -> PPC da semana: sem compromisso | G9: ="PPC da semana: "&IF(COUNTIFS('05. SEMANAS'!$A$5:$A$64,'02. PARÂMETROS'!$B$5,'05. SEMANAS'!$B$5:$B$64,"343")=0,"sem lançamento",TEXT('01C. PLACAR SEMANAL'!D9,"0%")) -> PPC da semana: sem compromisso
A10: 5. Controle diário | B10: O que foi feito hoje, com que gente? | C10: Encarregado e apontador | D10: Todo dia | E10: 05B. APONTAMENTO DIÁRIO | F10: ="Apontamentos ÷ dias úteis: "&IF(COUNTIFS('05. SEMANAS'!$A$5:$A$64,'02. PARÂMETROS'!$B$5,'05. SEMANAS'!$B$5:$B$64,"342")=0,"sem lançamento",TEXT('01C. PLACAR SEMANAL'!C10,"0%"))&" · efetivo ÷ previsto: "&IF(COUNTIFS('05. SEMANAS'!$A$5:$A$64,'02. PARÂMETROS'!$B$5,'05. SEMANAS'!$B$5:$B$64,"342")=0,"sem lançamento",TEXT('01C. PLACAR SEMANAL'!C8,"0%")) -> Apontamentos ÷ dias úteis: 0% · efetivo ÷ previsto: sem apontamento | G10: ="Apontamentos ÷ dias úteis: "&IF(COUNTIFS('05. SEMANAS'!$A$5:$A$64,'02. PARÂMETROS'!$B$5,'05. SEMANAS'!$B$5:$B$64,"343")=0,"sem lançamento",TEXT('01C. PLACAR SEMANAL'!D10,"0%"))&" · efetivo ÷ previsto: "&IF(COUNTIFS('05. SEMANAS'!$A$5:$A$64,'02. PARÂMETROS'!$B$5,'05. SEMANAS'!$B$5:$B$64,"343")=0,"sem lançamento",TEXT('01C. PLACAR SEMANAL'!D8,"0%")) -> Apontamentos ÷ dias úteis: 0% · efetivo ÷ previsto: sem apontamento
A11: 6. Histograma | B11: Quanta gente por mês e por semana, previsto x real? | C11: Engenheiro residente | D11: Semanal (olhar) | E11: HISTOGRAMA PLANEJADO | F11: ="Previsto no mês do corte: pico "&FIXED(INDEX('HISTOGRAMA PLANEJADO'!$B$8:$B$23,MATCH(DATE(YEAR(DATA_GESTAO),MONTH(DATA_GESTAO),1),'HISTOGRAMA PLANEJADO'!$A$8:$A$23,0)),0)&" pessoas · realizado: "&IF(ISNUMBER(INDEX('HISTOGRAMA PLANEJADO'!$I$8:$I$23,MATCH(DATE(YEAR(DATA_GESTAO),MONTH(DATA_GESTAO),1),'HISTOGRAMA PLANEJADO'!$A$8:$A$23,0))),"lançado","sem lançamento") -> Previsto no mês do corte: pico 23 pessoas · realizado: sem lançamento | G11: ="Previsto no mês do corte: pico "&FIXED(INDEX('HISTOGRAMA PLANEJADO'!$B$29:$B$44,MATCH(DATE(YEAR(DATA_GESTAO),MONTH(DATA_GESTAO),1),'HISTOGRAMA PLANEJADO'!$A$29:$A$44,0)),0)&" pessoas · realizado: "&IF(ISNUMBER(INDEX('HISTOGRAMA PLANEJADO'!$I$29:$I$44,MATCH(DATE(YEAR(DATA_GESTAO),MONTH(DATA_GESTAO),1),'HISTOGRAMA PLANEJADO'!$A$29:$A$44,0))),"lançado","sem lançamento") -> Previsto no mês do corte: pico 11 pessoas · realizado: sem lançamento
A12: 7. Medição | B12: O que foi feito já virou BM e dinheiro? | C12: Engenheiro e administrativo | D12: Fechamento do mês | E12: 06. MEDIÇÃO (BM) | F12: ="Medido até o corte: "&IF(COUNTIFS('06. MEDIÇÃO (BM)'!$B$5:$B$44,"342",'06. MEDIÇÃO (BM)'!$G$5:$G$44,"<>")=0,"sem lançamento","R$ "&FIXED('08B. TODAS AS OBRAS'!C5,0)&" ("&TEXT('08B. TODAS AS OBRAS'!D5,"0%")&" do contrato)")&" · previsto até o último BM fechado R$ "&FIXED('08B. TODAS AS OBRAS'!E5,0) -> Medido até o corte: sem lançamento · previsto até o último BM fechado R$ 0 | G12: ="Medido até o corte: "&IF(COUNTIFS('06. MEDIÇÃO (BM)'!$B$5:$B$44,"343",'06. MEDIÇÃO (BM)'!$G$5:$G$44,"<>")=0,"sem lançamento","R$ "&FIXED('08B. TODAS AS OBRAS'!C6,0)&" ("&TEXT('08B. TODAS AS OBRAS'!D6,"0%")&" do contrato)")&" · previsto até o último BM fechado R$ "&FIXED('08B. TODAS AS OBRAS'!E6,0) -> Medido até o corte: sem lançamento · previsto até o último BM fechado R$ 0
A13: 8. Custo | B13: Quanto custou, por obra e mês, contra o previsto? | C13: Administrativo | D13: Todo pagamento; fechamento do mês | E13: 08. CUSTOS | F13: ="Custo lançado até o corte: "&IF(COUNTIFS('08. CUSTOS'!$C$5:$C$404,"342",'08. CUSTOS'!$F$5:$F$404,"<>")=0,"sem lançamento","R$ "&FIXED('08B. TODAS AS OBRAS'!G5,0))&" · previsto até o corte R$ "&FIXED('08B. TODAS AS OBRAS'!H5,0) -> Custo lançado até o corte: sem lançamento · previsto até o corte R$ 29,526 | G13: ="Custo lançado até o corte: "&IF(COUNTIFS('08. CUSTOS'!$C$5:$C$404,"343",'08. CUSTOS'!$F$5:$F$404,"<>")=0,"sem lançamento","R$ "&FIXED('08B. TODAS AS OBRAS'!G6,0))&" · previsto até o corte R$ "&FIXED('08B. TODAS AS OBRAS'!H6,0) -> Custo lançado até o corte: sem lançamento · previsto até o corte R$ 820,643
A14: 9. Caixa | B14: Quanto entra e sai; qual o pior saldo e quando? | C14: Diretoria e administrativo | D14: Segunda | E14: FLUXO PROJETADO TAF | F14: ="Pior saldo previsto R$ "&FIXED('FLUXO PROJETADO TAF'!$C$14,0)&" em "&CHOOSE(MONTH('FLUXO PROJETADO TAF'!$C$15),"jan","fev","mar","abr","mai","jun","jul","ago","set","out","nov","dez")&"/"&RIGHT(YEAR('FLUXO PROJETADO TAF'!$C$15),2)&" · capital R$ "&FIXED('FLUXO PROJETADO TAF'!$C$16,0) -> Pior saldo previsto R$ -1,151,142 em fev/27 · capital R$ 1,323,813 | G14: ="Pior saldo previsto R$ "&FIXED('FLUXO PROJETADO TAF'!$D$14,0)&" em "&CHOOSE(MONTH('FLUXO PROJETADO TAF'!$D$15),"jan","fev","mar","abr","mai","jun","jul","ago","set","out","nov","dez")&"/"&RIGHT(YEAR('FLUXO PROJETADO TAF'!$D$15),2)&" · capital R$ "&FIXED('FLUXO PROJETADO TAF'!$D$16,0) -> Pior saldo previsto R$ -1,401,326 em nov/26 · capital R$ 1,611,524
A15: 10. Placar | B15: Cumprimos? IDP, custo, PPC, adoção do apontamento. | C15: Diretoria | D15: Segunda | E15: 01C. PLACAR SEMANAL | F15: ="IDP: "&IF(COUNTIFS('06. MEDIÇÃO (BM)'!$B$5:$B$44,"342",'06. MEDIÇÃO (BM)'!$G$5:$G$44,"<>")=0,"sem lançamento",IF('08B. TODAS AS OBRAS'!E5=0,"previsto zero",TEXT('08B. TODAS AS OBRAS'!C5/'08B. TODAS AS OBRAS'!E5,"0,00")))&" · custo ÷ previsto: "&IF(COUNTIFS('08. CUSTOS'!$C$5:$C$404,"342",'08. CUSTOS'!$F$5:$F$404,"<>")=0,"sem lançamento",TEXT(IFERROR('08B. TODAS AS OBRAS'!G5/'08B. TODAS AS OBRAS'!H5,0),"0,00")) -> IDP: sem lançamento · custo ÷ previsto: sem lançamento | G15: ="IDP: "&IF(COUNTIFS('06. MEDIÇÃO (BM)'!$B$5:$B$44,"343",'06. MEDIÇÃO (BM)'!$G$5:$G$44,"<>")=0,"sem lançamento",IF('08B. TODAS AS OBRAS'!E6=0,"previsto zero",TEXT('08B. TODAS AS OBRAS'!C6/'08B. TODAS AS OBRAS'!E6,"0,00")))&" · custo ÷ previsto: "&IF(COUNTIFS('08. CUSTOS'!$C$5:$C$404,"343",'08. CUSTOS'!$F$5:$F$404,"<>")=0,"sem lançamento",TEXT(IFERROR('08B. TODAS AS OBRAS'!G6/'08B. TODAS AS OBRAS'!H6,0),"0,00")) -> IDP: sem lançamento · custo ÷ previsto: sem lançamento
A16: 11. Decisão | B16: Qual a decisão, com dono e prazo? | C16: Diretoria e engenheiro | D16: Segunda, 90 minutos | E16: PAUTA DE SEGUNDA TAF | F16: ="Decisões abertas na pauta (proposta, aberta ou aprovada): "&(COUNTIF('PAUTA DE SEGUNDA TAF'!$D$64:$D$77,"PROPOSTA")+COUNTIF('PAUTA DE SEGUNDA TAF'!$D$64:$D$77,"ABERTA")+COUNTIF('PAUTA DE SEGUNDA TAF'!$D$64:$D$77,"APROVADA"))&" (342, 343 e 281)" -> Decisões abertas na pauta (proposta, aberta ou aprovada): 14 (342, 343 e 281) | G16: ="Decisões abertas na pauta (proposta, aberta ou aprovada): "&(COUNTIF('PAUTA DE SEGUNDA TAF'!$D$64:$D$77,"PROPOSTA")+COUNTIF('PAUTA DE SEGUNDA TAF'!$D$64:$D$77,"ABERTA")+COUNTIF('PAUTA DE SEGUNDA TAF'!$D$64:$D$77,"APROVADA"))&" (342, 343 e 281)" -> Decisões abertas na pauta (proposta, aberta ou aprovada): 14 (342, 343 e 281)
A19: ROTINA
A20: Todo dia | B20: Encarregado manda o apontamento e a foto; o apontador confere. Escalar se o ritmo cair 2 dias seguidos (roteiros diários por obra).
A21: Sexta | B21: Engenheiro residente: restrições das próximas 6 semanas na 05C e compromisso da próxima semana confirmado na 05A (o PPC sai sozinho na 05. SEMANAS).
A22: Segunda | B22: Mudar a data de corte (02), conferir o apontamento da semana (05B), ler as luzes (01A), o placar (01C), a PAUTA DE SEGUNDA TAF e o MASTER CHECK (13). Uma decisão por obra, com dono e prazo.
A23: Fim do mês | B23: Lançar o BM (06), a NF (07) e os custos pagos (08); lançar o % físico das etapas na coluna J do CRONOGRAMA PROJECT (a 12. EVM calcula o valor agregado a custo); conferir a LINHA DE BASE TAF.

Sheet CRONOGRAMA PROJECT
A2: CRONOGRAMA PROJECT: as duas obras, etapa por etapa, com caminho crítico
A3: Datas: primeiro e último mês com valor no cronograma (dia 1 do primeiro mês até o último dia do último mês). Predecessoras entre etapas: nenhuma fonte traz; as colunas amarelas G a I ficam para você digitar. Sem elas o caminho crítico não vale (a coluna Situação mostra 'sem rede'). Na tabela de eventos (linha 72), o antecessor da aba 37 do estudo REV13 liga eventos da mesma etapa; os marcos do fim da obra estão na linha 107.
A4: Fonte: 342 = eventograma Anexo VII (Eventograma 49/2024): valor de cada evento e datas de execução do plano do estudo REV13 (aba 05), na tabela de eventos da linha 72 em diante. 343 = mesmo arquivo, aba 343 - CRONOGRAMA (cronograma CAESB, Mês 1 = set/26, OS em 01/09/2026). Linhas 343-M = plano do motor, MOTOR TAF\ESTUDOS\TAF 343 CAESB SOBRADINHO - PLANEJAMENTO.xlsx, aba 13 PLANO (27/09/2026 17:51): referência de data, valor e custo; não somam com o contrato. | Q4: =IF(AND(TODAY()>=Q$6,TODAY()<=Q$6+6),"▲","") | R4: =IF(AND(TODAY()>=R$6,TODAY()<=R$6+6),"▲","") | S4: =IF(AND(TODAY()>=S$6,TODAY()<=S$6+6),"▲","") | T4: =IF(AND(TODAY()>=T$6,TODAY()<=T$6+6),"▲","") | U4: =IF(AND(TODAY()>=U$6,TODAY()<=U$6+6),"▲","") | V4: =IF(AND(TODAY()>=V$6,TODAY()<=V$6+6),"▲","") | W4: =IF(AND(TODAY()>=W$6,TODAY()<=W$6+6),"▲","") -> ▲ | X4: =IF(AND(TODAY()>=X$6,TODAY()<=X$6+6),"▲","") | ... BR4: =IF(AND(TODAY()>=BR$6,TODAY()<=BR$6+6),"▲","")
A5: ="Rede: "&SUMPRODUCT(--($G$7:$I$27<>""))&" predecessoras digitadas · etapas críticas: "&IF(COUNTIF($N$7:$N$27,"sem rede")=ROWS($N$7:$N$27),"sem rede",COUNTIF($N$7:$N$27,"CRÍTICA"))&" · problemas de checagem: "&COUNTIFS($P$7:$P$27,"<>ok")&" · data de gestão (02. PARÂMETROS): "&TEXT(DATA_GESTAO,"dd/mm")&"/"&YEAR(DATA_GESTAO) -> Rede: 0 predecessoras digitadas · etapas críticas: sem rede · problemas de checagem: 0 · data de gestão (02. PARÂMETROS): 16/10/2026 | Q5: =IF(AND(DATA_GESTAO>=Q$6,DATA_GESTAO<=Q$6+6),"▼","") | R5: =IF(AND(DATA_GESTAO>=R$6,DATA_GESTAO<=R$6+6),"▼","") | S5: =IF(AND(DATA_GESTAO>=S$6,DATA_GESTAO<=S$6+6),"▼","") | T5: =IF(AND(DATA_GESTAO>=T$6,DATA_GESTAO<=T$6+6),"▼","") | U5: =IF(AND(DATA_GESTAO>=U$6,DATA_GESTAO<=U$6+6),"▼","") | V5: =IF(AND(DATA_GESTAO>=V$6,DATA_GESTAO<=V$6+6),"▼","") | W5: =IF(AND(DATA_GESTAO>=W$6,DATA_GESTAO<=W$6+6),"▼","") -> ▼ | X5: =IF(AND(DATA_GESTAO>=X$6,DATA_GESTAO<=X$6+6),"▼","") | ... BR5: =IF(AND(DATA_GESTAO>=BR$6,DATA_GESTAO<=BR$6+6),"▼","")
A6: ID | B6: Obra | C6: Etapa | D6: Início | E6: Fim | F6: Duração (dias) | G6: Predecessora 1 | H6: Predecessora 2 | I6: Predecessora 3 | J6: % físico (lançar do BM) | K6: Valor da etapa (R$) | L6: Custo planejado (R$) | M6: Folga (dias) | N6: Situação | O6: Valor medido (R$) | P6: Checagem | Q6: =MIN('03. CONTRATOS'!$B$10,'03. CONTRATOS'!$D$10)-WEEKDAY(MIN('03. CONTRATOS'!$B$10,'03. CONTRATOS'!$D$10),2)+1 -> 46265 | R6: =Q6+7 -> 46272 | S6: =R6+7 -> 46279 | T6: =S6+7 -> 46286 | U6: =T6+7 -> 46293 | V6: =U6+7 -> 46300 | W6: =V6+7 -> 46307 | X6: =W6+7 -> 46314 | Y6: =X6+7 -> 46321 | ... BR6: =BQ6+7 -> 46636 | BT6: Início fixado (fonte) | BU6: Fim fixado (fonte) | BV6: Camada | BW6: Rede | BX6: Fim tarde | BY6: Início tarde | BZ6: Chave (auxiliar) | CA6: Predecessoras na rede (auxiliar)
A7: 342-01 | B7: 342 | C7: CANTEIRO DE OBRAS | D7: =IF(BT7="","",MAX(BT7,IF($G7="",0,_xlfn.MAXIFS($E$6:$E6,$A$6:$A6,$G7)+1),IF($H7="",0,_xlfn.MAXIFS($E$6:$E6,$A$6:$A6,$H7)+1),IF($I7="",0,_xlfn.MAXIFS($E$6:$E6,$A$6:$A6,$I7)+1))) -> 46314 | E7: =IF(D7="","",D7+F7-1) -> 46604 | F7: =IF(OR(BT7="",BU7=""),"",BU7-BT7+1) -> 291 | K7: =$P33 -> 122394 | L7: pendente | M7: =IF(OR(BX7="",E7=""),"",BX7-E7) -> 22 | N7: =IF(M7="","",IF(CA7=0,"sem rede",IF(M7<=0,"CRÍTICA",""))) -> sem rede | O7: =IF(OR(J7="",K7=""),"",J7*K7) | P7: =IF(OR(BT7="",BU7=""),"sem data",IF(OR(AND(G7<>"",COUNTIF($A$7:$A$27,G7)=0),AND(H7<>"",COUNTIF($A$7:$A$27,H7)=0),AND(I7<>"",COUNTIF($A$7:$A$27,I7)=0)),"predecessora inexistente",IF(OR(AND(G7<>"",COUNTIF($A$6:$A6,G7)=0),AND(H7<>"",COUNTIF($A$6:$A6,H7)=0),AND(I7<>"",COUNTIF($A$6:$A6,I7)=0)),"predecessora abaixo da tarefa","ok"))) -> ok | Q7: =IF(OR($D7="",$E7=""),"",IF(AND($D7<=Q$6+6,$E7>=Q$6),IF($N7="CRÍTICA","C","P"),"")) | R7: =IF(OR($D7="",$E7=""),"",IF(AND($D7<=R$6+6,$E7>=R$6),IF($N7="CRÍTICA","C","P"),"")) | S7: =IF(OR($D7="",$E7=""),"",IF(AND($D7<=S$6+6,$E7>=S$6),IF($N7="CRÍTICA","C","P"),"")) | T7: =IF(OR($D7="",$E7=""),"",IF(AND($D7<=T$6+6,$E7>=T$6),IF($N7="CRÍTICA","C","P"),"")) | U7: =IF(OR($D7="",$E7=""),"",IF(AND($D7<=U$6+6,$E7>=U$6),IF($N7="CRÍTICA","C","P"),"")) | V7: =IF(OR($D7="",$E7=""),"",IF(AND($D7<=V$6+6,$E7>=V$6),IF($N7="CRÍTICA","C","P"),"")) | W7: =IF(OR($D7="",$E7=""),"",IF(AND($D7<=W$6+6,$E7>=W$6),IF($N7="CRÍTICA","C","P"),"")) | X7: =IF(OR($D7="",$E7=""),"",IF(AND($D7<=X$6+6,$E7>=X$6),IF($N7="CRÍTICA","C","P"),"")) -> P | ... BR7: =IF(OR($D7="",$E7=""),"",IF(AND($D7<=BR$6+6,$E7>=BR$6),IF($N7="CRÍTICA","C","P"),"")) | BT7: =_xlfn.MINIFS($G$74:$G$103,$D$74:$D$103,$A7) -> 46314 | BU7: =_xlfn.MAXIFS($H$74:$H$103,$D$74:$D$103,$A7) -> 46604 | BV7: Contrato | BW7: 342 | BX7: =IF(E7="","",IF(COUNTIF($G8:$G$28,$A7)+COUNTIF($H8:$H$28,$A7)+COUNTIF($I8:$I$28,$A7)=0,_xlfn.MAXIFS($E$7:$E$27,$BW$7:$BW$27,$BW7),MIN(IF(COUNTIF($G8:$G$28,$A7)>0,_xlfn.MINIFS($BY8:$BY$28,$G8:$G$28,$A7),99999999),IF(COUNTIF($H8:$H$28,$A7)>0,_xlfn.MINIFS($BY8:$BY$28,$H8:$H$28,$A7),99999999),IF(COUNTIF($I8:$I$28,$A7)>0,_xlfn.MINIFS($BY8:$BY$28,$I8:$I$28,$A7),99999999))-1)) -> 46626 | BY7: =IF(BX7="","",BX7-F7+1) -> 46336 | BZ7: =IF(AND(D7<>"",D7>DATA_GESTAO),D7+ROW()/1000000,"") -> 46314 | CA7: =SUMPRODUCT(($BW$7:$BW$27=$BW7)*($G$7:$I$27<>"")) -> 0
A8: 342-02 | B8: 342 | C8: ADMINISTRAÇÃO LOCAL | D8: =IF(BT8="","",MAX(BT8,IF($G8="",0,_xlfn.MAXIFS($E$6:$E7,$A$6:$A7,$G8)+1),IF($H8="",0,_xlfn.MAXIFS($E$6:$E7,$A$6:$A7,$H8)+1),IF($I8="",0,_xlfn.MAXIFS($E$6:$E7,$A$6:$A7,$I8)+1))) -> 46314 | E8: =IF(D8="","",D8+F8-1) -> 46604 | F8: =IF(OR(BT8="",BU8=""),"",BU8-BT8+1) -> 291 | K8: =$P34 -> 479911 | L8: pendente | M8: =IF(OR(BX8="",E8=""),"",BX8-E8) -> 22 | N8: =IF(M8="","",IF(CA8=0,"sem rede",IF(M8<=0,"CRÍTICA",""))) -> sem rede | O8: =IF(OR(J8="",K8=""),"",J8*K8) | P8: =IF(OR(BT8="",BU8=""),"sem data",IF(OR(AND(G8<>"",COUNTIF($A$7:$A$27,G8)=0),AND(H8<>"",COUNTIF($A$7:$A$27,H8)=0),AND(I8<>"",COUNTIF($A$7:$A$27,I8)=0)),"predecessora inexistente",IF(OR(AND(G8<>"",COUNTIF($A$6:$A7,G8)=0),AND(H8<>"",COUNTIF($A$6:$A7,H8)=0),AND(I8<>"",COUNTIF($A$6:$A7,I8)=0)),"predecessora abaixo da tarefa","ok"))) -> ok | Q8: =IF(OR($D8="",$E8=""),"",IF(AND($D8<=Q$6+6,$E8>=Q$6),IF($N8="CRÍTICA","C","P"),"")) | R8: =IF(OR($D8="",$E8=""),"",IF(AND($D8<=R$6+6,$E8>=R$6),IF($N8="CRÍTICA","C","P"),"")) | S8: =IF(OR($D8="",$E8=""),"",IF(AND($D8<=S$6+6,$E8>=S$6),IF($N8="CRÍTICA","C","P"),"")) | T8: =IF(OR($D8="",$E8=""),"",IF(AND($D8<=T$6+6,$E8>=T$6),IF($N8="CRÍTICA","C","P"),"")) | U8: =IF(OR($D8="",$E8=""),"",IF(AND($D8<=U$6+6,$E8>=U$6),IF($N8="CRÍTICA","C","P"),"")) | V8: =IF(OR($D8="",$E8=""),"",IF(AND($D8<=V$6+6,$E8>=V$6),IF($N8="CRÍTICA","C","P"),"")) | W8: =IF(OR($D8="",$E8=""),"",IF(AND($D8<=W$6+6,$E8>=W$6),IF($N8="CRÍTICA","C","P"),"")) | X8: =IF(OR($D8="",$E8=""),"",IF(AND($D8<=X$6+6,$E8>=X$6),IF($N8="CRÍTICA","C","P"),"")) -> P | ... BR8: =IF(OR($D8="",$E8=""),"",IF(AND($D8<=BR$6+6,$E8>=BR$6),IF($N8="CRÍTICA","C","P"),"")) | BT8: =_xlfn.MINIFS($G$74:$G$103,$D$74:$D$103,$A8) -> 46314 | BU8: =_xlfn.MAXIFS($H$74:$H$103,$D$74:$D$103,$A8) -> 46604 | BV8: Contrato | BW8: 342 | BX8: =IF(E8="","",IF(COUNTIF($G9:$G$28,$A8)+COUNTIF($H9:$H$28,$A8)+COUNTIF($I9:$I$28,$A8)=0,_xlfn.MAXIFS($E$7:$E$27,$BW$7:$BW$27,$BW8),MIN(IF(COUNTIF($G9:$G$28,$A8)>0,_xlfn.MINIFS($BY9:$BY$28,$G9:$G$28,$A8),99999999),IF(COUNTIF($H9:$H$28,$A8)>0,_xlfn.MINIFS($BY9:$BY$28,$H9:$H$28,$A8),99999999),IF(COUNTIF($I9:$I$28,$A8)>0,_xlfn.MINIFS($BY9:$BY$28,$I9:$I$28,$A8),99999999))-1)) -> 46626 | BY8: =IF(BX8="","",BX8-F8+1) -> 46336 | BZ8: =IF(AND(D8<>"",D8>DATA_GESTAO),D8+ROW()/1000000,"") -> 46314 | CA8: =SUMPRODUCT(($BW$7:$BW$27=$BW8)*($G$7:$I$27<>"")) -> 0
A9: 342-03 | B9: 342 | C9: TERRAPLANAGEM E DESVIO DE TUBULAÇÃO | D9: =IF(BT9="","",MAX(BT9,IF($G9="",0,_xlfn.MAXIFS($E$6:$E8,$A$6:$A8,$G9)+1),IF($H9="",0,_xlfn.MAXIFS($E$6:$E8,$A$6:$A8,$H9)+1),IF($I9="",0,_xlfn.MAXIFS($E$6:$E8,$A$6:$A8,$I9)+1))) -> 46314 | E9: =IF(D9="","",D9+F9-1) -> 46325 | F9: =IF(OR(BT9="",BU9=""),"",BU9-BT9+1) -> 12 | K9: =$P35 -> 131545.55 | L9: pendente | M9: =IF(OR(BX9="",E9=""),"",BX9-E9) -> 301 | N9: =IF(M9="","",IF(CA9=0,"sem rede",IF(M9<=0,"CRÍTICA",""))) -> sem rede | O9: =IF(OR(J9="",K9=""),"",J9*K9) | P9: =IF(OR(BT9="",BU9=""),"sem data",IF(OR(AND(G9<>"",COUNTIF($A$7:$A$27,G9)=0),AND(H9<>"",COUNTIF($A$7:$A$27,H9)=0),AND(I9<>"",COUNTIF($A$7:$A$27,I9)=0)),"predecessora inexistente",IF(OR(AND(G9<>"",COUNTIF($A$6:$A8,G9)=0),AND(H9<>"",COUNTIF($A$6:$A8,H9)=0),AND(I9<>"",COUNTIF($A$6:$A8,I9)=0)),"predecessora abaixo da tarefa","ok"))) -> ok | Q9: =IF(OR($D9="",$E9=""),"",IF(AND($D9<=Q$6+6,$E9>=Q$6),IF($N9="CRÍTICA","C","P"),"")) | R9: =IF(OR($D9="",$E9=""),"",IF(AND($D9<=R$6+6,$E9>=R$6),IF($N9="CRÍTICA","C","P"),"")) | S9: =IF(OR($D9="",$E9=""),"",IF(AND($D9<=S$6+6,$E9>=S$6),IF($N9="CRÍTICA","C","P"),"")) | T9: =IF(OR($D9="",$E9=""),"",IF(AND($D9<=T$6+6,$E9>=T$6),IF($N9="CRÍTICA","C","P"),"")) | U9: =IF(OR($D9="",$E9=""),"",IF(AND($D9<=U$6+6,$E9>=U$6),IF($N9="CRÍTICA","C","P"),"")) | V9: =IF(OR($D9="",$E9=""),"",IF(AND($D9<=V$6+6,$E9>=V$6),IF($N9="CRÍTICA","C","P"),"")) | W9: =IF(OR($D9="",$E9=""),"",IF(AND($D9<=W$6+6,$E9>=W$6),IF($N9="CRÍTICA","C","P"),"")) | X9: =IF(OR($D9="",$E9=""),"",IF(AND($D9<=X$6+6,$E9>=X$6),IF($N9="CRÍTICA","C","P"),"")) -> P | ... BR9: =IF(OR($D9="",$E9=""),"",IF(AND($D9<=BR$6+6,$E9>=BR$6),IF($N9="CRÍTICA","C","P"),"")) | BT9: =_xlfn.MINIFS($G$74:$G$103,$D$74:$D$103,$A9) -> 46314 | BU9: =_xlfn.MAXIFS($H$74:$H$103,$D$74:$D$103,$A9) -> 46325 | BV9: Contrato | BW9: 342 | BX9: =IF(E9="","",IF(COUNTIF($G10:$G$28,$A9)+COUNTIF($H10:$H$28,$A9)+COUNTIF($I10:$I$28,$A9)=0,_xlfn.MAXIFS($E$7:$E$27,$BW$7:$BW$27,$BW9),MIN(IF(COUNTIF($G10:$G$28,$A9)>0,_xlfn.MINIFS($BY10:$BY$28,$G10:$G$28,$A9),99999999),IF(COUNTIF($H10:$H$28,$A9)>0,_xlfn.MINIFS($BY10:$BY$28,$H10:$H$28,$A9),99999999),IF(COUNTIF($I10:$I$28,$A9)>0,_xlfn.MINIFS($BY10:$BY$28,$I10:$I$28,$A9),99999999))-1)) -> 46626 | BY9: =IF(BX9="","",BX9-F9+1) -> 46615 | BZ9: =IF(AND(D9<>"",D9>DATA_GESTAO),D9+ROW()/1000000,"") -> 46314 | CA9: =SUMPRODUCT(($BW$7:$BW$27=$BW9)*($G$7:$I$27<>"")) -> 0
A10: 342-04 | B10: 342 | C10: INTERLIGAÇÕES ETA × UTR | D10: =IF(BT10="","",MAX(BT10,IF($G10="",0,_xlfn.MAXIFS($E$6:$E9,$A$6:$A9,$G10)+1),IF($H10="",0,_xlfn.MAXIFS($E$6:$E9,$A$6:$A9,$H10)+1),IF($I10="",0,_xlfn.MAXIFS($E$6:$E9,$A$6:$A9,$I10)+1))) -> 46358 | E10: =IF(D10="","",D10+F10-1) -> 46380 | F10: =IF(OR(BT10="",BU10=""),"",BU10-BT10+1) -> 23 | K10: =$P36 -> 334559.95 | L10: pendente | M10: =IF(OR(BX10="",E10=""),"",BX10-E10) -> 246 | N10: =IF(M10="","",IF(CA10=0,"sem rede",IF(M10<=0,"CRÍTICA",""))) -> sem rede | O10: =IF(OR(J10="",K10=""),"",J10*K10) | P10: =IF(OR(BT10="",BU10=""),"sem data",IF(OR(AND(G10<>"",COUNTIF($A$7:$A$27,G10)=0),AND(H10<>"",COUNTIF($A$7:$A$27,H10)=0),AND(I10<>"",COUNTIF($A$7:$A$27,I10)=0)),"predecessora inexistente",IF(OR(AND(G10<>"",COUNTIF($A$6:$A9,G10)=0),AND(H10<>"",COUNTIF($A$6:$A9,H10)=0),AND(I10<>"",COUNTIF($A$6:$A9,I10)=0)),"predecessora abaixo da tarefa","ok"))) -> ok | Q10: =IF(OR($D10="",$E10=""),"",IF(AND($D10<=Q$6+6,$E10>=Q$6),IF($N10="CRÍTICA","C","P"),"")) | R10: =IF(OR($D10="",$E10=""),"",IF(AND($D10<=R$6+6,$E10>=R$6),IF($N10="CRÍTICA","C","P"),"")) | S10: =IF(OR($D10="",$E10=""),"",IF(AND($D10<=S$6+6,$E10>=S$6),IF($N10="CRÍTICA","C","P"),"")) | T10: =IF(OR($D10="",$E10=""),"",IF(AND($D10<=T$6+6,$E10>=T$6),IF($N10="CRÍTICA","C","P"),"")) | U10: =IF(OR($D10="",$E10=""),"",IF(AND($D10<=U$6+6,$E10>=U$6),IF($N10="CRÍTICA","C","P"),"")) | V10: =IF(OR($D10="",$E10=""),"",IF(AND($D10<=V$6+6,$E10>=V$6),IF($N10="CRÍTICA","C","P"),"")) | W10: =IF(OR($D10="",$E10=""),"",IF(AND($D10<=W$6+6,$E10>=W$6),IF($N10="CRÍTICA","C","P"),"")) | X10: =IF(OR($D10="",$E10=""),"",IF(AND($D10<=X$6+6,$E10>=X$6),IF($N10="CRÍTICA","C","P"),"")) | ... BR10: =IF(OR($D10="",$E10=""),"",IF(AND($D10<=BR$6+6,$E10>=BR$6),IF($N10="CRÍTICA","C","P"),"")) | BT10: =_xlfn.MINIFS($G$74:$G$103,$D$74:$D$103,$A10) -> 46358 | BU10: =_xlfn.MAXIFS($H$74:$H$103,$D$74:$D$103,$A10) -> 46380 | BV10: Contrato | BW10: 342 | BX10: =IF(E10="","",IF(COUNTIF($G11:$G$28,$A10)+COUNTIF($H11:$H$28,$A10)+COUNTIF($I11:$I$28,$A10)=0,_xlfn.MAXIFS($E$7:$E$27,$BW$7:$BW$27,$BW10),MIN(IF(COUNTIF($G11:$G$28,$A10)>0,_xlfn.MINIFS($BY11:$BY$28,$G11:$G$28,$A10),99999999),IF(COUNTIF($H11:$H$28,$A10)>0,_xlfn.MINIFS($BY11:$BY$28,$H11:$H$28,$A10),99999999),IF(COUNTIF($I11:$I$28,$A10)>0,_xlfn.MINIFS($BY11:$BY$28,$I11:$I$28,$A10),99999999))-1)) -> 46626 | BY10: =IF(BX10="","",BX10-F10+1) -> 46604 | BZ10: =IF(AND(D10<>"",D10>DATA_GESTAO),D10+ROW()/1000000,"") -> 46358 | CA10: =SUMPRODUCT(($BW$7:$BW$27=$BW10)*($G$7:$I$27<>"")) -> 0
A11: 342-05 | B11: 342 | C11: INTERLIGAÇÕES LINHA DE RECALQUE UTR × ETA | D11: =IF(BT11="","",MAX(BT11,IF($G11="",0,_xlfn.MAXIFS($E$6:$E10,$A$6:$A10,$G11)+1),IF($H11="",0,_xlfn.MAXIFS($E$6:$E10,$A$6:$A10,$H11)+1),IF($I11="",0,_xlfn.MAXIFS($E$6:$E10,$A$6:$A10,$I11)+1))) -> 46370 | E11: =IF(D11="","",D11+F11-1) -> 46387 | F11: =IF(OR(BT11="",BU11=""),"",BU11-BT11+1) -> 18 | K11: =$P37 -> 54857.68 | L11: pendente | M11: =IF(OR(BX11="",E11=""),"",BX11-E11) -> 239 | N11: =IF(M11="","",IF(CA11=0,"sem rede",IF(M11<=0,"CRÍTICA",""))) -> sem rede | O11: =IF(OR(J11="",K11=""),"",J11*K11) | P11: =IF(OR(BT11="",BU11=""),"sem data",IF(OR(AND(G11<>"",COUNTIF($A$7:$A$27,G11)=0),AND(H11<>"",COUNTIF($A$7:$A$27,H11)=0),AND(I11<>"",COUNTIF($A$7:$A$27,I11)=0)),"predecessora inexistente",IF(OR(AND(G11<>"",COUNTIF($A$6:$A10,G11)=0),AND(H11<>"",COUNTIF($A$6:$A10,H11)=0),AND(I11<>"",COUNTIF($A$6:$A10,I11)=0)),"predecessora abaixo da tarefa","ok"))) -> ok | Q11: =IF(OR($D11="",$E11=""),"",IF(AND($D11<=Q$6+6,$E11>=Q$6),IF($N11="CRÍTICA","C","P"),"")) | R11: =IF(OR($D11="",$E11=""),"",IF(AND($D11<=R$6+6,$E11>=R$6),IF($N11="CRÍTICA","C","P"),"")) | S11: =IF(OR($D11="",$E11=""),"",IF(AND($D11<=S$6+6,$E11>=S$6),IF($N11="CRÍTICA","C","P"),"")) | T11: =IF(OR($D11="",$E11=""),"",IF(AND($D11<=T$6+6,$E11>=T$6),IF($N11="CRÍTICA","C","P"),"")) | U11: =IF(OR($D11="",$E11=""),"",IF(AND($D11<=U$6+6,$E11>=U$6),IF($N11="CRÍTICA","C","P"),"")) | V11: =IF(OR($D11="",$E11=""),"",IF(AND($D11<=V$6+6,$E11>=V$6),IF($N11="CRÍTICA","C","P"),"")) | W11: =IF(OR($D11="",$E11=""),"",IF(AND($D11<=W$6+6,$E11>=W$6),IF($N11="CRÍTICA","C","P"),"")) | X11: =IF(OR($D11="",$E11=""),"",IF(AND($D11<=X$6+6,$E11>=X$6),IF($N11="CRÍTICA","C","P"),"")) | ... BR11: =IF(OR($D11="",$E11=""),"",IF(AND($D11<=BR$6+6,$E11>=BR$6),IF($N11="CRÍTICA","C","P"),"")) | BT11: =_xlfn.MINIFS($G$74:$G$103,$D$74:$D$103,$A11) -> 46370 | BU11: =_xlfn.MAXIFS($H$74:$H$103,$D$74:$D$103,$A11) -> 46387 | BV11: Contrato | BW11: 342 | BX11: =IF(E11="","",IF(COUNTIF($G12:$G$28,$A11)+COUNTIF($H12:$H$28,$A11)+COUNTIF($I12:$I$28,$A11)=0,_xlfn.MAXIFS($E$7:$E$27,$BW$7:$BW$27,$BW11),MIN(IF(COUNTIF($G12:$G$28,$A11)>0,_xlfn.MINIFS($BY12:$BY$28,$G12:$G$28,$A11),99999999),IF(COUNTIF($H12:$H$28,$A11)>0,_xlfn.MINIFS($BY12:$BY$28,$H12:$H$28,$A11),99999999),IF(COUNTIF($I12:$I$28,$A11)>0,_xlfn.MINIFS($BY12:$BY$28,$I12:$I$28,$A11),99999999))-1)) -> 46626 | BY11: =IF(BX11="","",BX11-F11+1) -> 46609 | BZ11: =IF(AND(D11<>"",D11>DATA_GESTAO),D11+ROW()/1000000,"") -> 46370 | CA11: =SUMPRODUCT(($BW$7:$BW$27=$BW11)*($G$7:$I$27<>"")) -> 0
A12: 342-06 | B12: 342 | C12: DRENAGENS, ESGOTAMENTO E CAIXA DE CHEGADA | D12: =IF(BT12="","",MAX(BT12,IF($G12="",0,_xlfn.MAXIFS($E$6:$E11,$A$6:$A11,$G12)+1),IF($H12="",0,_xlfn.MAXIFS($E$6:$E11,$A$6:$A11,$H12)+1),IF($I12="",0,_xlfn.MAXIFS($E$6:$E11,$A$6:$A11,$I12)+1))) -> 46349 | E12: =IF(D12="","",D12+F12-1) -> 46366 | F12: =IF(OR(BT12="",BU12=""),"",BU12-BT12+1) -> 18 | K12: =$P38 -> 72003.88 | L12: pendente | M12: =IF(OR(BX12="",E12=""),"",BX12-E12) -> 260 | N12: =IF(M12="","",IF(CA12=0,"sem rede",IF(M12<=0,"CRÍTICA",""))) -> sem rede | O12: =IF(OR(J12="",K12=""),"",J12*K12) | P12: =IF(OR(BT12="",BU12=""),"sem data",IF(OR(AND(G12<>"",COUNTIF($A$7:$A$27,G12)=0),AND(H12<>"",COUNTIF($A$7:$A$27,H12)=0),AND(I12<>"",COUNTIF($A$7:$A$27,I12)=0)),"predecessora inexistente",IF(OR(AND(G12<>"",COUNTIF($A$6:$A11,G12)=0),AND(H12<>"",COUNTIF($A$6:$A11,H12)=0),AND(I12<>"",COUNTIF($A$6:$A11,I12)=0)),"predecessora abaixo da tarefa","ok"))) -> ok | Q12: =IF(OR($D12="",$E12=""),"",IF(AND($D12<=Q$6+6,$E12>=Q$6),IF($N12="CRÍTICA","C","P"),"")) | R12: =IF(OR($D12="",$E12=""),"",IF(AND($D12<=R$6+6,$E12>=R$6),IF($N12="CRÍTICA","C","P"),"")) | S12: =IF(OR($D12="",$E12=""),"",IF(AND($D12<=S$6+6,$E12>=S$6),IF($N12="CRÍTICA","C","P"),"")) | T12: =IF(OR($D12="",$E12=""),"",IF(AND($D12<=T$6+6,$E12>=T$6),IF($N12="CRÍTICA","C","P"),"")) | U12: =IF(OR($D12="",$E12=""),"",IF(AND($D12<=U$6+6,$E12>=U$6),IF($N12="CRÍTICA","C","P"),"")) | V12: =IF(OR($D12="",$E12=""),"",IF(AND($D12<=V$6+6,$E12>=V$6),IF($N12="CRÍTICA","C","P"),"")) | W12: =IF(OR($D12="",$E12=""),"",IF(AND($D12<=W$6+6,$E12>=W$6),IF($N12="CRÍTICA","C","P"),"")) | X12: =IF(OR($D12="",$E12=""),"",IF(AND($D12<=X$6+6,$E12>=X$6),IF($N12="CRÍTICA","C","P"),"")) | ... BR12: =IF(OR($D12="",$E12=""),"",IF(AND($D12<=BR$6+6,$E12>=BR$6),IF($N12="CRÍTICA","C","P"),"")) | BT12: =_xlfn.MINIFS($G$74:$G$103,$D$74:$D$103,$A12) -> 46349 | BU12: =_xlfn.MAXIFS($H$74:$H$103,$D$74:$D$103,$A12) -> 46366 | BV12: Contrato | BW12: 342 | BX12: =IF(E12="","",IF(COUNTIF($G13:$G$28,$A12)+COUNTIF($H13:$H$28,$A12)+COUNTIF($I13:$I$28,$A12)=0,_xlfn.MAXIFS($E$7:$E$27,$BW$7:$BW$27,$BW12),MIN(IF(COUNTIF($G13:$G$28,$A12)>0,_xlfn.MINIFS($BY13:$BY$28,$G13:$G$28,$A12),99999999),IF(COUNTIF($H13:$H$28,$A12)>0,_xlfn.MINIFS($BY13:$BY$28,$H13:$H$28,$A12),99999999),IF(COUNTIF($I13:$I$28,$A12)>0,_xlfn.MINIFS($BY13:$BY$28,$I13:$I$28,$A12),99999999))-1)) -> 46626 | BY12: =IF(BX12="","",BX12-F12+1) -> 46609 | BZ12: =IF(AND(D12<>"",D12>DATA_GESTAO),D12+ROW()/1000000,"") -> 46349 | CA12: =SUMPRODUCT(($BW$7:$BW$27=$BW12)*($G$7:$I$27<>"")) -> 0
A13: 342-07 | B13: 342 | C13: TANQUE DE LODO | D13: =IF(BT13="","",MAX(BT13,IF($G13="",0,_xlfn.MAXIFS($E$6:$E12,$A$6:$A12,$G13)+1),IF($H13="",0,_xlfn.MAXIFS($E$6:$E12,$A$6:$A12,$H13)+1),IF($I13="",0,_xlfn.MAXIFS($E$6:$E12,$A$6:$A12,$I13)+1))) -> 46329 | E13: =IF(D13="","",D13+F13-1) -> 46518 | F13: =IF(OR(BT13="",BU13=""),"",BU13-BT13+1) -> 190 | K13: =$P39 -> 1180517.8 | L13: pendente | M13: =IF(OR(BX13="",E13=""),"",BX13-E13) -> 108 | N13: =IF(M13="","",IF(CA13=0,"sem rede",IF(M13<=0,"CRÍTICA",""))) -> sem rede | O13: =IF(OR(J13="",K13=""),"",J13*K13) | P13: =IF(OR(BT13="",BU13=""),"sem data",IF(OR(AND(G13<>"",COUNTIF($A$7:$A$27,G13)=0),AND(H13<>"",COUNTIF($A$7:$A$27,H13)=0),AND(I13<>"",COUNTIF($A$7:$A$27,I13)=0)),"predecessora inexistente",IF(OR(AND(G13<>"",COUNTIF($A$6:$A12,G13)=0),AND(H13<>"",COUNTIF($A$6:$A12,H13)=0),AND(I13<>"",COUNTIF($A$6:$A12,I13)=0)),"predecessora abaixo da tarefa","ok"))) -> ok | Q13: =IF(OR($D13="",$E13=""),"",IF(AND($D13<=Q$6+6,$E13>=Q$6),IF($N13="CRÍTICA","C","P"),"")) | R13: =IF(OR($D13="",$E13=""),"",IF(AND($D13<=R$6+6,$E13>=R$6),IF($N13="CRÍTICA","C","P"),"")) | S13: =IF(OR($D13="",$E13=""),"",IF(AND($D13<=S$6+6,$E13>=S$6),IF($N13="CRÍTICA","C","P"),"")) | T13: =IF(OR($D13="",$E13=""),"",IF(AND($D13<=T$6+6,$E13>=T$6),IF($N13="CRÍTICA","C","P"),"")) | U13: =IF(OR($D13="",$E13=""),"",IF(AND($D13<=U$6+6,$E13>=U$6),IF($N13="CRÍTICA","C","P"),"")) | V13: =IF(OR($D13="",$E13=""),"",IF(AND($D13<=V$6+6,$E13>=V$6),IF($N13="CRÍTICA","C","P"),"")) | W13: =IF(OR($D13="",$E13=""),"",IF(AND($D13<=W$6+6,$E13>=W$6),IF($N13="CRÍTICA","C","P"),"")) | X13: =IF(OR($D13="",$E13=""),"",IF(AND($D13<=X$6+6,$E13>=X$6),IF($N13="CRÍTICA","C","P"),"")) | ... BR13: =IF(OR($D13="",$E13=""),"",IF(AND($D13<=BR$6+6,$E13>=BR$6),IF($N13="CRÍTICA","C","P"),"")) | BT13: =_xlfn.MINIFS($G$74:$G$103,$D$74:$D$103,$A13) -> 46329 | BU13: =_xlfn.MAXIFS($H$74:$H$103,$D$74:$D$103,$A13) -> 46518 | BV13: Contrato | BW13: 342 | BX13: =IF(E13="","",IF(COUNTIF($G14:$G$28,$A13)+COUNTIF($H14:$H$28,$A13)+COUNTIF($I14:$I$28,$A13)=0,_xlfn.MAXIFS($E$7:$E$27,$BW$7:$BW$27,$BW13),MIN(IF(COUNTIF($G14:$G$28,$A13)>0,_xlfn.MINIFS($BY14:$BY$28,$G14:$G$28,$A13),99999999),IF(COUNTIF($H14:$H$28,$A13)>0,_xlfn.MINIFS($BY14:$BY$28,$H14:$H$28,$A13),99999999),IF(COUNTIF($I14:$I$28,$A13)>0,_xlfn.MINIFS($BY14:$BY$28,$I14:$I$28,$A13),99999999))-1)) -> 46626 | BY13: =IF(BX13="","",BX13-F13+1) -> 46437 | BZ13: =IF(AND(D13<>"",D13>DATA_GESTAO),D13+ROW()/1000000,"") -> 46329 | CA13: =SUMPRODUCT(($BW$7:$BW$27=$BW13)*($G$7:$I$27<>"")) -> 0
A14: 342-08 | B14: 342 | C14: ESTAÇÃO ELEVATÓRIA DE RECIRCULAÇÃO DE LODO | D14: =IF(BT14="","",MAX(BT14,IF($G14="",0,_xlfn.MAXIFS($E$6:$E13,$A$6:$A13,$G14)+1),IF($H14="",0,_xlfn.MAXIFS($E$6:$E13,$A$6:$A13,$H14)+1),IF($I14="",0,_xlfn.MAXIFS($E$6:$E13,$A$6:$A13,$I14)+1))) -> 46408 | E14: =IF(D14="","",D14+F14-1) -> 46549 | F14: =IF(OR(BT14="",BU14=""),"",BU14-BT14+1) -> 142 | K14: =$P40 -> 530787.26 | L14: pendente | M14: =IF(OR(BX14="",E14=""),"",BX14-E14) -> 77 | N14: =IF(M14="","",IF(CA14=0,"sem rede",IF(M14<=0,"CRÍTICA",""))) -> sem rede | O14: =IF(OR(J14="",K14=""),"",J14*K14) | P14: =IF(OR(BT14="",BU14=""),"sem data",IF(OR(AND(G14<>"",COUNTIF($A$7:$A$27,G14)=0),AND(H14<>"",COUNTIF($A$7:$A$27,H14)=0),AND(I14<>"",COUNTIF($A$7:$A$27,I14)=0)),"predecessora inexistente",IF(OR(AND(G14<>"",COUNTIF($A$6:$A13,G14)=0),AND(H14<>"",COUNTIF($A$6:$A13,H14)=0),AND(I14<>"",COUNTIF($A$6:$A13,I14)=0)),"predecessora abaixo da tarefa","ok"))) -> ok | Q14: =IF(OR($D14="",$E14=""),"",IF(AND($D14<=Q$6+6,$E14>=Q$6),IF($N14="CRÍTICA","C","P"),"")) | R14: =IF(OR($D14="",$E14=""),"",IF(AND($D14<=R$6+6,$E14>=R$6),IF($N14="CRÍTICA","C","P"),"")) | S14: =IF(OR($D14="",$E14=""),"",IF(AND($D14<=S$6+6,$E14>=S$6),IF($N14="CRÍTICA","C","P"),"")) | T14: =IF(OR($D14="",$E14=""),"",IF(AND($D14<=T$6+6,$E14>=T$6),IF($N14="CRÍTICA","C","P"),"")) | U14: =IF(OR($D14="",$E14=""),"",IF(AND($D14<=U$6+6,$E14>=U$6),IF($N14="CRÍTICA","C","P"),"")) | V14: =IF(OR($D14="",$E14=""),"",IF(AND($D14<=V$6+6,$E14>=V$6),IF($N14="CRÍTICA","C","P"),"")) | W14: =IF(OR($D14="",$E14=""),"",IF(AND($D14<=W$6+6,$E14>=W$6),IF($N14="CRÍTICA","C","P"),"")) | X14: =IF(OR($D14="",$E14=""),"",IF(AND($D14<=X$6+6,$E14>=X$6),IF($N14="CRÍTICA","C","P"),"")) | ... BR14: =IF(OR($D14="",$E14=""),"",IF(AND($D14<=BR$6+6,$E14>=BR$6),IF($N14="CRÍTICA","C","P"),"")) | BT14: =_xlfn.MINIFS($G$74:$G$103,$D$74:$D$103,$A14) -> 46408 | BU14: =_xlfn.MAXIFS($H$74:$H$103,$D$74:$D$103,$A14) -> 46549 | BV14: Contrato | BW14: 342 | BX14: =IF(E14="","",IF(COUNTIF($G15:$G$28,$A14)+COUNTIF($H15:$H$28,$A14)+COUNTIF($I15:$I$28,$A14)=0,_xlfn.MAXIFS($E$7:$E$27,$BW$7:$BW$27,$BW14),MIN(IF(COUNTIF($G15:$G$28,$A14)>0,_xlfn.MINIFS($BY15:$BY$28,$G15:$G$28,$A14),99999999),IF(COUNTIF($H15:$H$28,$A14)>0,_xlfn.MINIFS($BY15:$BY$28,$H15:$H$28,$A14),99999999),IF(COUNTIF($I15:$I$28,$A14)>0,_xlfn.MINIFS($BY15:$BY$28,$I15:$I$28,$A14),99999999))-1)) -> 46626 | BY14: =IF(BX14="","",BX14-F14+1) -> 46485 | BZ14: =IF(AND(D14<>"",D14>DATA_GESTAO),D14+ROW()/1000000,"") -> 46408 | CA14: =SUMPRODUCT(($BW$7:$BW$27=$BW14)*($G$7:$I$27<>"")) -> 0
A15: 342-09 | B15: 342 | C15: URBANIZAÇÃO, CANALETAS, CAIXAS E SERVIÇOS COMPLEMENTARES | D15: =IF(BT15="","",MAX(BT15,IF($G15="",0,_xlfn.MAXIFS($E$6:$E14,$A$6:$A14,$G15)+1),IF($H15="",0,_xlfn.MAXIFS($E$6:$E14,$A$6:$A14,$H15)+1),IF($I15="",0,_xlfn.MAXIFS($E$6:$E14,$A$6:$A14,$I15)+1))) -> 46526 | E15: =IF(D15="","",D15+F15-1) -> 46589 | F15: =IF(OR(BT15="",BU15=""),"",BU15-BT15+1) -> 64 | K15: =$P41 -> 218637.74 | L15: pendente | M15: =IF(OR(BX15="",E15=""),"",BX15-E15) -> 37 | N15: =IF(M15="","",IF(CA15=0,"sem rede",IF(M15<=0,"CRÍTICA",""))) -> sem rede | O15: =IF(OR(J15="",K15=""),"",J15*K15) | P15: =IF(OR(BT15="",BU15=""),"sem data",IF(OR(AND(G15<>"",COUNTIF($A$7:$A$27,G15)=0),AND(H15<>"",COUNTIF($A$7:$A$27,H15)=0),AND(I15<>"",COUNTIF($A$7:$A$27,I15)=0)),"predecessora inexistente",IF(OR(AND(G15<>"",COUNTIF($A$6:$A14,G15)=0),AND(H15<>"",COUNTIF($A$6:$A14,H15)=0),AND(I15<>"",COUNTIF($A$6:$A14,I15)=0)),"predecessora abaixo da tarefa","ok"))) -> ok | Q15: =IF(OR($D15="",$E15=""),"",IF(AND($D15<=Q$6+6,$E15>=Q$6),IF($N15="CRÍTICA","C","P"),"")) | R15: =IF(OR($D15="",$E15=""),"",IF(AND($D15<=R$6+6,$E15>=R$6),IF($N15="CRÍTICA","C","P"),"")) | S15: =IF(OR($D15="",$E15=""),"",IF(AND($D15<=S$6+6,$E15>=S$6),IF($N15="CRÍTICA","C","P"),"")) | T15: =IF(OR($D15="",$E15=""),"",IF(AND($D15<=T$6+6,$E15>=T$6),IF($N15="CRÍTICA","C","P"),"")) | U15: =IF(OR($D15="",$E15=""),"",IF(AND($D15<=U$6+6,$E15>=U$6),IF($N15="CRÍTICA","C","P"),"")) | V15: =IF(OR($D15="",$E15=""),"",IF(AND($D15<=V$6+6,$E15>=V$6),IF($N15="CRÍTICA","C","P"),"")) | W15: =IF(OR($D15="",$E15=""),"",IF(AND($D15<=W$6+6,$E15>=W$6),IF($N15="CRÍTICA","C","P"),"")) | X15: =IF(OR($D15="",$E15=""),"",IF(AND($D15<=X$6+6,$E15>=X$6),IF($N15="CRÍTICA","C","P"),"")) | ... BR15: =IF(OR($D15="",$E15=""),"",IF(AND($D15<=BR$6+6,$E15>=BR$6),IF($N15="CRÍTICA","C","P"),"")) | BT15: =_xlfn.MINIFS($G$74:$G$103,$D$74:$D$103,$A15) -> 46526 | BU15: =_xlfn.MAXIFS($H$74:$H$103,$D$74:$D$103,$A15) -> 46589 | BV15: Contrato | BW15: 342 | BX15: =IF(E15="","",IF(COUNTIF($G16:$G$28,$A15)+COUNTIF($H16:$H$28,$A15)+COUNTIF($I16:$I$28,$A15)=0,_xlfn.MAXIFS($E$7:$E$27,$BW$7:$BW$27,$BW15),MIN(IF(COUNTIF($G16:$G$28,$A15)>0,_xlfn.MINIFS($BY16:$BY$28,$G16:$G$28,$A15),99999999),IF(COUNTIF($H16:$H$28,$A15)>0,_xlfn.MINIFS($BY16:$BY$28,$H16:$H$28,$A15),99999999),IF(COUNTIF($I16:$I$28,$A15)>0,_xlfn.MINIFS($BY16:$BY$28,$I16:$I$28,$A15),99999999))-1)) -> 46626 | BY15: =IF(BX15="","",BX15-F15+1) -> 46563 | BZ15: =IF(AND(D15<>"",D15>DATA_GESTAO),D15+ROW()/1000000,"") -> 46526 | CA15: =SUMPRODUCT(($BW$7:$BW$27=$BW15)*($G$7:$I$27<>"")) -> 0
A16: 342-10 | B16: 342 | C16: REDE DE DISTRIBUIÇÃO DE ENERGIA | D16: =IF(BT16="","",MAX(BT16,IF($G16="",0,_xlfn.MAXIFS($E$6:$E15,$A$6:$A15,$G16)+1),IF($H16="",0,_xlfn.MAXIFS($E$6:$E15,$A$6:$A15,$H16)+1),IF($I16="",0,_xlfn.MAXIFS($E$6:$E15,$A$6:$A15,$I16)+1))) -> 46433 | E16: =IF(D16="","",D16+F16-1) -> 46449 | F16: =IF(OR(BT16="",BU16=""),"",BU16-BT16+1) -> 17 | K16: =$P42 -> 104799.22 | L16: pendente | M16: =IF(OR(BX16="",E16=""),"",BX16-E16) -> 177 | N16: =IF(M16="","",IF(CA16=0,"sem rede",IF(M16<=0,"CRÍTICA",""))) -> sem rede | O16: =IF(OR(J16="",K16=""),"",J16*K16) | P16: =IF(OR(BT16="",BU16=""),"sem data",IF(OR(AND(G16<>"",COUNTIF($A$7:$A$27,G16)=0),AND(H16<>"",COUNTIF($A$7:$A$27,H16)=0),AND(I16<>"",COUNTIF($A$7:$A$27,I16)=0)),"predecessora inexistente",IF(OR(AND(G16<>"",COUNTIF($A$6:$A15,G16)=0),AND(H16<>"",COUNTIF($A$6:$A15,H16)=0),AND(I16<>"",COUNTIF($A$6:$A15,I16)=0)),"predecessora abaixo da tarefa","ok"))) -> ok | Q16: =IF(OR($D16="",$E16=""),"",IF(AND($D16<=Q$6+6,$E16>=Q$6),IF($N16="CRÍTICA","C","P"),"")) | R16: =IF(OR($D16="",$E16=""),"",IF(AND($D16<=R$6+6,$E16>=R$6),IF($N16="CRÍTICA","C","P"),"")) | S16: =IF(OR($D16="",$E16=""),"",IF(AND($D16<=S$6+6,$E16>=S$6),IF($N16="CRÍTICA","C","P"),"")) | T16: =IF(OR($D16="",$E16=""),"",IF(AND($D16<=T$6+6,$E16>=T$6),IF($N16="CRÍTICA","C","P"),"")) | U16: =IF(OR($D16="",$E16=""),"",IF(AND($D16<=U$6+6,$E16>=U$6),IF($N16="CRÍTICA","C","P"),"")) | V16: =IF(OR($D16="",$E16=""),"",IF(AND($D16<=V$6+6,$E16>=V$6),IF($N16="CRÍTICA","C","P"),"")) | W16: =IF(OR($D16="",$E16=""),"",IF(AND($D16<=W$6+6,$E16>=W$6),IF($N16="CRÍTICA","C","P"),"")) | X16: =IF(OR($D16="",$E16=""),"",IF(AND($D16<=X$6+6,$E16>=X$6),IF($N16="CRÍTICA","C","P"),"")) | ... BR16: =IF(OR($D16="",$E16=""),"",IF(AND($D16<=BR$6+6,$E16>=BR$6),IF($N16="CRÍTICA","C","P"),"")) | BT16: =_xlfn.MINIFS($G$74:$G$103,$D$74:$D$103,$A16) -> 46433 | BU16: =_xlfn.MAXIFS($H$74:$H$103,$D$74:$D$103,$A16) -> 46449 | BV16: Contrato | BW16: 342 | BX16: =IF(E16="","",IF(COUNTIF($G17:$G$28,$A16)+COUNTIF($H17:$H$28,$A16)+COUNTIF($I17:$I$28,$A16)=0,_xlfn.MAXIFS($E$7:$E$27,$BW$7:$BW$27,$BW16),MIN(IF(COUNTIF($G17:$G$28,$A16)>0,_xlfn.MINIFS($BY17:$BY$28,$G17:$G$28,$A16),99999999),IF(COUNTIF($H17:$H$28,$A16)>0,_xlfn.MINIFS($BY17:$BY$28,$H17:$H$28,$A16),99999999),IF(COUNTIF($I17:$I$28,$A16)>0,_xlfn.MINIFS($BY17:$BY$28,$I17:$I$28,$A16),99999999))-1)) -> 46626 | BY16: =IF(BX16="","",BX16-F16+1) -> 46610 | BZ16: =IF(AND(D16<>"",D16>DATA_GESTAO),D16+ROW()/1000000,"") -> 46433 | CA16: =SUMPRODUCT(($BW$7:$BW$27=$BW16)*($G$7:$I$27<>"")) -> 0
A17: 342-11 | B17: 342 | C17: PROJETOS EXECUTIVOS / AS BUILT | D17: =IF(BT17="","",MAX(BT17,IF($G17="",0,_xlfn.MAXIFS($E$6:$E16,$A$6:$A16,$G17)+1),IF($H17="",0,_xlfn.MAXIFS($E$6:$E16,$A$6:$A16,$H17)+1),IF($I17="",0,_xlfn.MAXIFS($E$6:$E16,$A$6:$A16,$I17)+1))) -> 46268 | E17: =IF(D17="","",D17+F17-1) -> 46626 | F17: =IF(OR(BT17="",BU17=""),"",BU17-BT17+1) -> 359 | K17: =$P43 -> 27956.66 | L17: pendente | M17: =IF(OR(BX17="",E17=""),"",BX17-E17) -> 0 | N17: =IF(M17="","",IF(CA17=0,"sem rede",IF(M17<=0,"CRÍTICA",""))) -> sem rede | O17: =IF(OR(J17="",K17=""),"",J17*K17) | P17: =IF(OR(BT17="",BU17=""),"sem data",IF(OR(AND(G17<>"",COUNTIF($A$7:$A$27,G17)=0),AND(H17<>"",COUNTIF($A$7:$A$27,H17)=0),AND(I17<>"",COUNTIF($A$7:$A$27,I17)=0)),"predecessora inexistente",IF(OR(AND(G17<>"",COUNTIF($A$6:$A16,G17)=0),AND(H17<>"",COUNTIF($A$6:$A16,H17)=0),AND(I17<>"",COUNTIF($A$6:$A16,I17)=0)),"predecessora abaixo da tarefa","ok"))) -> ok | Q17: =IF(OR($D17="",$E17=""),"",IF(AND($D17<=Q$6+6,$E17>=Q$6),IF($N17="CRÍTICA","C","P"),"")) -> P | R17: =IF(OR($D17="",$E17=""),"",IF(AND($D17<=R$6+6,$E17>=R$6),IF($N17="CRÍTICA","C","P"),"")) -> P | S17: =IF(OR($D17="",$E17=""),"",IF(AND($D17<=S$6+6,$E17>=S$6),IF($N17="CRÍTICA","C","P"),"")) -> P | T17: =IF(OR($D17="",$E17=""),"",IF(AND($D17<=T$6+6,$E17>=T$6),IF($N17="CRÍTICA","C","P"),"")) -> P | U17: =IF(OR($D17="",$E17=""),"",IF(AND($D17<=U$6+6,$E17>=U$6),IF($N17="CRÍTICA","C","P"),"")) -> P | V17: =IF(OR($D17="",$E17=""),"",IF(AND($D17<=V$6+6,$E17>=V$6),IF($N17="CRÍTICA","C","P"),"")) -> P | W17: =IF(OR($D17="",$E17=""),"",IF(AND($D17<=W$6+6,$E17>=W$6),IF($N17="CRÍTICA","C","P"),"")) -> P | X17: =IF(OR($D17="",$E17=""),"",IF(AND($D17<=X$6+6,$E17>=X$6),IF($N17="CRÍTICA","C","P"),"")) -> P | ... BR17: =IF(OR($D17="",$E17=""),"",IF(AND($D17<=BR$6+6,$E17>=BR$6),IF($N17="CRÍTICA","C","P"),"")) | BT17: =_xlfn.MINIFS($G$74:$G$103,$D$74:$D$103,$A17) -> 46268 | BU17: =_xlfn.MAXIFS($H$74:$H$103,$D$74:$D$103,$A17) -> 46626 | BV17: Contrato | BW17: 342 | BX17: =IF(E17="","",IF(COUNTIF($G18:$G$28,$A17)+COUNTIF($H18:$H$28,$A17)+COUNTIF($I18:$I$28,$A17)=0,_xlfn.MAXIFS($E$7:$E$27,$BW$7:$BW$27,$BW17),MIN(IF(COUNTIF($G18:$G$28,$A17)>0,_xlfn.MINIFS($BY18:$BY$28,$G18:$G$28,$A17),99999999),IF(COUNTIF($H18:$H$28,$A17)>0,_xlfn.MINIFS($BY18:$BY$28,$H18:$H$28,$A17),99999999),IF(COUNTIF($I18:$I$28,$A17)>0,_xlfn.MINIFS($BY18:$BY$28,$I18:$I$28,$A17),99999999))-1)) -> 46626 | BY17: =IF(BX17="","",BX17-F17+1) -> 46268 | BZ17: =IF(AND(D17<>"",D17>DATA_GESTAO),D17+ROW()/1000000,"") | CA17: =SUMPRODUCT(($BW$7:$BW$27=$BW17)*($G$7:$I$27<>"")) -> 0
A18: 343-01 | B18: 343 | C18: Canteiro de Obras | D18: =IF(BT18="","",MAX(BT18,IF($G18="",0,_xlfn.MAXIFS($E$6:$E17,$A$6:$A17,$G18)+1),IF($H18="",0,_xlfn.MAXIFS($E$6:$E17,$A$6:$A17,$H18)+1),IF($I18="",0,_xlfn.MAXIFS($E$6:$E17,$A$6:$A17,$I18)+1))) -> 46266 | E18: =IF(D18="","",D18+F18-1) -> 46538 | F18: =IF(OR(BT18="",BU18=""),"",BU18-BT18+1) -> 273 | K18: =$P44 -> 940360.23 | L18: pendente | M18: =IF(OR(BX18="",E18=""),"",BX18-E18) -> 0 | N18: =IF(M18="","",IF(CA18=0,"sem rede",IF(M18<=0,"CRÍTICA",""))) -> sem rede | O18: =IF(OR(J18="",K18=""),"",J18*K18) | P18: =IF(OR(BT18="",BU18=""),"sem data",IF(OR(AND(G18<>"",COUNTIF($A$7:$A$27,G18)=0),AND(H18<>"",COUNTIF($A$7:$A$27,H18)=0),AND(I18<>"",COUNTIF($A$7:$A$27,I18)=0)),"predecessora inexistente",IF(OR(AND(G18<>"",COUNTIF($A$6:$A17,G18)=0),AND(H18<>"",COUNTIF($A$6:$A17,H18)=0),AND(I18<>"",COUNTIF($A$6:$A17,I18)=0)),"predecessora abaixo da tarefa","ok"))) -> ok | Q18: =IF(OR($D18="",$E18=""),"",IF(AND($D18<=Q$6+6,$E18>=Q$6),IF($N18="CRÍTICA","C","P"),"")) -> P | R18: =IF(OR($D18="",$E18=""),"",IF(AND($D18<=R$6+6,$E18>=R$6),IF($N18="CRÍTICA","C","P"),"")) -> P | S18: =IF(OR($D18="",$E18=""),"",IF(AND($D18<=S$6+6,$E18>=S$6),IF($N18="CRÍTICA","C","P"),"")) -> P | T18: =IF(OR($D18="",$E18=""),"",IF(AND($D18<=T$6+6,$E18>=T$6),IF($N18="CRÍTICA","C","P"),"")) -> P | U18: =IF(OR($D18="",$E18=""),"",IF(AND($D18<=U$6+6,$E18>=U$6),IF($N18="CRÍTICA","C","P"),"")) -> P | V18: =IF(OR($D18="",$E18=""),"",IF(AND($D18<=V$6+6,$E18>=V$6),IF($N18="CRÍTICA","C","P"),"")) -> P | W18: =IF(OR($D18="",$E18=""),"",IF(AND($D18<=W$6+6,$E18>=W$6),IF($N18="CRÍTICA","C","P"),"")) -> P | X18: =IF(OR($D18="",$E18=""),"",IF(AND($D18<=X$6+6,$E18>=X$6),IF($N18="CRÍTICA","C","P"),"")) -> P | ... BR18: =IF(OR($D18="",$E18=""),"",IF(AND($D18<=BR$6+6,$E18>=BR$6),IF($N18="CRÍTICA","C","P"),"")) | BT18: =IF(SUM($D44:$O44)=0,"",_xlfn.MINIFS($D$32:$O$32,$D44:$O44,">0")) -> 46266 | BU18: =IF(BT18="","",EOMONTH(_xlfn.MAXIFS($D$32:$O$32,$D44:$O44,">0"),0)) -> 46538 | BV18: Contrato | BW18: 343 | BX18: =IF(E18="","",IF(COUNTIF($G19:$G$28,$A18)+COUNTIF($H19:$H$28,$A18)+COUNTIF($I19:$I$28,$A18)=0,_xlfn.MAXIFS($E$7:$E$27,$BW$7:$BW$27,$BW18),MIN(IF(COUNTIF($G19:$G$28,$A18)>0,_xlfn.MINIFS($BY19:$BY$28,$G19:$G$28,$A18),99999999),IF(COUNTIF($H19:$H$28,$A18)>0,_xlfn.MINIFS($BY19:$BY$28,$H19:$H$28,$A18),99999999),IF(COUNTIF($I19:$I$28,$A18)>0,_xlfn.MINIFS($BY19:$BY$28,$I19:$I$28,$A18),99999999))-1)) -> 46538 | BY18: =IF(BX18="","",BX18-F18+1) -> 46266 | BZ18: =IF(AND(D18<>"",D18>DATA_GESTAO),D18+ROW()/1000000,"") | CA18: =SUMPRODUCT(($BW$7:$BW$27=$BW18)*($G$7:$I$27<>"")) -> 0
A19: 343-02 | B19: 343 | C19: Subadutora | D19: =IF(BT19="","",MAX(BT19,IF($G19="",0,_xlfn.MAXIFS($E$6:$E18,$A$6:$A18,$G19)+1),IF($H19="",0,_xlfn.MAXIFS($E$6:$E18,$A$6:$A18,$H19)+1),IF($I19="",0,_xlfn.MAXIFS($E$6:$E18,$A$6:$A18,$I19)+1))) -> 46296 | E19: =IF(D19="","",D19+F19-1) -> 46507 | F19: =IF(OR(BT19="",BU19=""),"",BU19-BT19+1) -> 212 | K19: =$P45 -> 1674250.7 | L19: pendente | M19: =IF(OR(BX19="",E19=""),"",BX19-E19) -> 31 | N19: =IF(M19="","",IF(CA19=0,"sem rede",IF(M19<=0,"CRÍTICA",""))) -> sem rede | O19: =IF(OR(J19="",K19=""),"",J19*K19) | P19: =IF(OR(BT19="",BU19=""),"sem data",IF(OR(AND(G19<>"",COUNTIF($A$7:$A$27,G19)=0),AND(H19<>"",COUNTIF($A$7:$A$27,H19)=0),AND(I19<>"",COUNTIF($A$7:$A$27,I19)=0)),"predecessora inexistente",IF(OR(AND(G19<>"",COUNTIF($A$6:$A18,G19)=0),AND(H19<>"",COUNTIF($A$6:$A18,H19)=0),AND(I19<>"",COUNTIF($A$6:$A18,I19)=0)),"predecessora abaixo da tarefa","ok"))) -> ok | Q19: =IF(OR($D19="",$E19=""),"",IF(AND($D19<=Q$6+6,$E19>=Q$6),IF($N19="CRÍTICA","C","P"),"")) | R19: =IF(OR($D19="",$E19=""),"",IF(AND($D19<=R$6+6,$E19>=R$6),IF($N19="CRÍTICA","C","P"),"")) | S19: =IF(OR($D19="",$E19=""),"",IF(AND($D19<=S$6+6,$E19>=S$6),IF($N19="CRÍTICA","C","P"),"")) | T19: =IF(OR($D19="",$E19=""),"",IF(AND($D19<=T$6+6,$E19>=T$6),IF($N19="CRÍTICA","C","P"),"")) | U19: =IF(OR($D19="",$E19=""),"",IF(AND($D19<=U$6+6,$E19>=U$6),IF($N19="CRÍTICA","C","P"),"")) -> P | V19: =IF(OR($D19="",$E19=""),"",IF(AND($D19<=V$6+6,$E19>=V$6),IF($N19="CRÍTICA","C","P"),"")) -> P | W19: =IF(OR($D19="",$E19=""),"",IF(AND($D19<=W$6+6,$E19>=W$6),IF($N19="CRÍTICA","C","P"),"")) -> P | X19: =IF(OR($D19="",$E19=""),"",IF(AND($D19<=X$6+6,$E19>=X$6),IF($N19="CRÍTICA","C","P"),"")) -> P | ... BR19: =IF(OR($D19="",$E19=""),"",IF(AND($D19<=BR$6+6,$E19>=BR$6),IF($N19="CRÍTICA","C","P"),"")) | BT19: =IF(SUM($D45:$O45)=0,"",_xlfn.MINIFS($D$32:$O$32,$D45:$O45,">0")) -> 46296 | BU19: =IF(BT19="","",EOMONTH(_xlfn.MAXIFS($D$32:$O$32,$D45:$O45,">0"),0)) -> 46507 | BV19: Contrato | BW19: 343 | BX19: =IF(E19="","",IF(COUNTIF($G20:$G$28,$A19)+COUNTIF($H20:$H$28,$A19)+COUNTIF($I20:$I$28,$A19)=0,_xlfn.MAXIFS($E$7:$E$27,$BW$7:$BW$27,$BW19),MIN(IF(COUNTIF($G20:$G$28,$A19)>0,_xlfn.MINIFS($BY20:$BY$28,$G20:$G$28,$A19),99999999),IF(COUNTIF($H20:$H$28,$A19)>0,_xlfn.MINIFS($BY20:$BY$28,$H20:$H$28,$A19),99999999),IF(COUNTIF($I20:$I$28,$A19)>0,_xlfn.MINIFS($BY20:$BY$28,$I20:$I$28,$A19),99999999))-1)) -> 46538 | BY19: =IF(BX19="","",BX19-F19+1) -> 46327 | BZ19: =IF(AND(D19<>"",D19>DATA_GESTAO),D19+ROW()/1000000,"") | CA19: =SUMPRODUCT(($BW$7:$BW$27=$BW19)*($G$7:$I$27<>"")) -> 0
A20: 343-03 | B20: 343 | C20: Caixas e Interligações | D20: =IF(BT20="","",MAX(BT20,IF($G20="",0,_xlfn.MAXIFS($E$6:$E19,$A$6:$A19,$G20)+1),IF($H20="",0,_xlfn.MAXIFS($E$6:$E19,$A$6:$A19,$H20)+1),IF($I20="",0,_xlfn.MAXIFS($E$6:$E19,$A$6:$A19,$I20)+1))) -> 46296 | E20: =IF(D20="","",D20+F20-1) -> 46507 | F20: =IF(OR(BT20="",BU20=""),"",BU20-BT20+1) -> 212 | K20: =$P46 -> 290959.41 | L20: pendente | M20: =IF(OR(BX20="",E20=""),"",BX20-E20) -> 31 | N20: =IF(M20="","",IF(CA20=0,"sem rede",IF(M20<=0,"CRÍTICA",""))) -> sem rede | O20: =IF(OR(J20="",K20=""),"",J20*K20) | P20: =IF(OR(BT20="",BU20=""),"sem data",IF(OR(AND(G20<>"",COUNTIF($A$7:$A$27,G20)=0),AND(H20<>"",COUNTIF($A$7:$A$27,H20)=0),AND(I20<>"",COUNTIF($A$7:$A$27,I20)=0)),"predecessora inexistente",IF(OR(AND(G20<>"",COUNTIF($A$6:$A19,G20)=0),AND(H20<>"",COUNTIF($A$6:$A19,H20)=0),AND(I20<>"",COUNTIF($A$6:$A19,I20)=0)),"predecessora abaixo da tarefa","ok"))) -> ok | Q20: =IF(OR($D20="",$E20=""),"",IF(AND($D20<=Q$6+6,$E20>=Q$6),IF($N20="CRÍTICA","C","P"),"")) | R20: =IF(OR($D20="",$E20=""),"",IF(AND($D20<=R$6+6,$E20>=R$6),IF($N20="CRÍTICA","C","P"),"")) | S20: =IF(OR($D20="",$E20=""),"",IF(AND($D20<=S$6+6,$E20>=S$6),IF($N20="CRÍTICA","C","P"),"")) | T20: =IF(OR($D20="",$E20=""),"",IF(AND($D20<=T$6+6,$E20>=T$6),IF($N20="CRÍTICA","C","P"),"")) | U20: =IF(OR($D20="",$E20=""),"",IF(AND($D20<=U$6+6,$E20>=U$6),IF($N20="CRÍTICA","C","P"),"")) -> P | V20: =IF(OR($D20="",$E20=""),"",IF(AND($D20<=V$6+6,$E20>=V$6),IF($N20="CRÍTICA","C","P"),"")) -> P | W20: =IF(OR($D20="",$E20=""),"",IF(AND($D20<=W$6+6,$E20>=W$6),IF($N20="CRÍTICA","C","P"),"")) -> P | X20: =IF(OR($D20="",$E20=""),"",IF(AND($D20<=X$6+6,$E20>=X$6),IF($N20="CRÍTICA","C","P"),"")) -> P | ... BR20: =IF(OR($D20="",$E20=""),"",IF(AND($D20<=BR$6+6,$E20>=BR$6),IF($N20="CRÍTICA","C","P"),"")) | BT20: =IF(SUM($D46:$O46)=0,"",_xlfn.MINIFS($D$32:$O$32,$D46:$O46,">0")) -> 46296 | BU20: =IF(BT20="","",EOMONTH(_xlfn.MAXIFS($D$32:$O$32,$D46:$O46,">0"),0)) -> 46507 | BV20: Contrato | BW20: 343 | BX20: =IF(E20="","",IF(COUNTIF($G21:$G$28,$A20)+COUNTIF($H21:$H$28,$A20)+COUNTIF($I21:$I$28,$A20)=0,_xlfn.MAXIFS($E$7:$E$27,$BW$7:$BW$27,$BW20),MIN(IF(COUNTIF($G21:$G$28,$A20)>0,_xlfn.MINIFS($BY21:$BY$28,$G21:$G$28,$A20),99999999),IF(COUNTIF($H21:$H$28,$A20)>0,_xlfn.MINIFS($BY21:$BY$28,$H21:$H$28,$A20),99999999),IF(COUNTIF($I21:$I$28,$A20)>0,_xlfn.MINIFS($BY21:$BY$28,$I21:$I$28,$A20),99999999))-1)) -> 46538 | BY20: =IF(BX20="","",BX20-F20+1) -> 46327 | BZ20: =IF(AND(D20<>"",D20>DATA_GESTAO),D20+ROW()/1000000,"") | CA20: =SUMPRODUCT(($BW$7:$BW$27=$BW20)*($G$7:$I$27<>"")) -> 0
A21: 343-04 | B21: 343 | C21: Hidromecânico | D21: =IF(BT21="","",MAX(BT21,IF($G21="",0,_xlfn.MAXIFS($E$6:$E20,$A$6:$A20,$G21)+1),IF($H21="",0,_xlfn.MAXIFS($E$6:$E20,$A$6:$A20,$H21)+1),IF($I21="",0,_xlfn.MAXIFS($E$6:$E20,$A$6:$A20,$I21)+1))) -> 46296 | E21: =IF(D21="","",D21+F21-1) -> 46507 | F21: =IF(OR(BT21="",BU21=""),"",BU21-BT21+1) -> 212 | K21: =$P47 -> 1684030.6 | L21: pendente | M21: =IF(OR(BX21="",E21=""),"",BX21-E21) -> 31 | N21: =IF(M21="","",IF(CA21=0,"sem rede",IF(M21<=0,"CRÍTICA",""))) -> sem rede | O21: =IF(OR(J21="",K21=""),"",J21*K21) | P21: =IF(OR(BT21="",BU21=""),"sem data",IF(OR(AND(G21<>"",COUNTIF($A$7:$A$27,G21)=0),AND(H21<>"",COUNTIF($A$7:$A$27,H21)=0),AND(I21<>"",COUNTIF($A$7:$A$27,I21)=0)),"predecessora inexistente",IF(OR(AND(G21<>"",COUNTIF($A$6:$A20,G21)=0),AND(H21<>"",COUNTIF($A$6:$A20,H21)=0),AND(I21<>"",COUNTIF($A$6:$A20,I21)=0)),"predecessora abaixo da tarefa","ok"))) -> ok | Q21: =IF(OR($D21="",$E21=""),"",IF(AND($D21<=Q$6+6,$E21>=Q$6),IF($N21="CRÍTICA","C","P"),"")) | R21: =IF(OR($D21="",$E21=""),"",IF(AND($D21<=R$6+6,$E21>=R$6),IF($N21="CRÍTICA","C","P"),"")) | S21: =IF(OR($D21="",$E21=""),"",IF(AND($D21<=S$6+6,$E21>=S$6),IF($N21="CRÍTICA","C","P"),"")) | T21: =IF(OR($D21="",$E21=""),"",IF(AND($D21<=T$6+6,$E21>=T$6),IF($N21="CRÍTICA","C","P"),"")) | U21: =IF(OR($D21="",$E21=""),"",IF(AND($D21<=U$6+6,$E21>=U$6),IF($N21="CRÍTICA","C","P"),"")) -> P | V21: =IF(OR($D21="",$E21=""),"",IF(AND($D21<=V$6+6,$E21>=V$6),IF($N21="CRÍTICA","C","P"),"")) -> P | W21: =IF(OR($D21="",$E21=""),"",IF(AND($D21<=W$6+6,$E21>=W$6),IF($N21="CRÍTICA","C","P"),"")) -> P | X21: =IF(OR($D21="",$E21=""),"",IF(AND($D21<=X$6+6,$E21>=X$6),IF($N21="CRÍTICA","C","P"),"")) -> P | ... BR21: =IF(OR($D21="",$E21=""),"",IF(AND($D21<=BR$6+6,$E21>=BR$6),IF($N21="CRÍTICA","C","P"),"")) | BT21: =IF(SUM($D47:$O47)=0,"",_xlfn.MINIFS($D$32:$O$32,$D47:$O47,">0")) -> 46296 | BU21: =IF(BT21="","",EOMONTH(_xlfn.MAXIFS($D$32:$O$32,$D47:$O47,">0"),0)) -> 46507 | BV21: Contrato | BW21: 343 | BX21: =IF(E21="","",IF(COUNTIF($G22:$G$28,$A21)+COUNTIF($H22:$H$28,$A21)+COUNTIF($I22:$I$28,$A21)=0,_xlfn.MAXIFS($E$7:$E$27,$BW$7:$BW$27,$BW21),MIN(IF(COUNTIF($G22:$G$28,$A21)>0,_xlfn.MINIFS($BY22:$BY$28,$G22:$G$28,$A21),99999999),IF(COUNTIF($H22:$H$28,$A21)>0,_xlfn.MINIFS($BY22:$BY$28,$H22:$H$28,$A21),99999999),IF(COUNTIF($I22:$I$28,$A21)>0,_xlfn.MINIFS($BY22:$BY$28,$I22:$I$28,$A21),99999999))-1)) -> 46538 | BY21: =IF(BX21="","",BX21-F21+1) -> 46327 | BZ21: =IF(AND(D21<>"",D21>DATA_GESTAO),D21+ROW()/1000000,"") | CA21: =SUMPRODUCT(($BW$7:$BW$27=$BW21)*($G$7:$I$27<>"")) -> 0
A22: 343-06 | B22: 343 | C22: Adm. Local | D22: =IF(BT22="","",MAX(BT22,IF($G22="",0,_xlfn.MAXIFS($E$6:$E21,$A$6:$A21,$G22)+1),IF($H22="",0,_xlfn.MAXIFS($E$6:$E21,$A$6:$A21,$H22)+1),IF($I22="",0,_xlfn.MAXIFS($E$6:$E21,$A$6:$A21,$I22)+1))) -> 46266 | E22: =IF(D22="","",D22+F22-1) -> 46538 | F22: =IF(OR(BT22="",BU22=""),"",BU22-BT22+1) -> 273 | K22: =$P48 -> 689827.41 | L22: pendente | M22: =IF(OR(BX22="",E22=""),"",BX22-E22) -> 0 | N22: =IF(M22="","",IF(CA22=0,"sem rede",IF(M22<=0,"CRÍTICA",""))) -> sem rede | O22: =IF(OR(J22="",K22=""),"",J22*K22) | P22: =IF(OR(BT22="",BU22=""),"sem data",IF(OR(AND(G22<>"",COUNTIF($A$7:$A$27,G22)=0),AND(H22<>"",COUNTIF($A$7:$A$27,H22)=0),AND(I22<>"",COUNTIF($A$7:$A$27,I22)=0)),"predecessora inexistente",IF(OR(AND(G22<>"",COUNTIF($A$6:$A21,G22)=0),AND(H22<>"",COUNTIF($A$6:$A21,H22)=0),AND(I22<>"",COUNTIF($A$6:$A21,I22)=0)),"predecessora abaixo da tarefa","ok"))) -> ok | Q22: =IF(OR($D22="",$E22=""),"",IF(AND($D22<=Q$6+6,$E22>=Q$6),IF($N22="CRÍTICA","C","P"),"")) -> P | R22: =IF(OR($D22="",$E22=""),"",IF(AND($D22<=R$6+6,$E22>=R$6),IF($N22="CRÍTICA","C","P"),"")) -> P | S22: =IF(OR($D22="",$E22=""),"",IF(AND($D22<=S$6+6,$E22>=S$6),IF($N22="CRÍTICA","C","P"),"")) -> P | T22: =IF(OR($D22="",$E22=""),"",IF(AND($D22<=T$6+6,$E22>=T$6),IF($N22="CRÍTICA","C","P"),"")) -> P | U22: =IF(OR($D22="",$E22=""),"",IF(AND($D22<=U$6+6,$E22>=U$6),IF($N22="CRÍTICA","C","P"),"")) -> P | V22: =IF(OR($D22="",$E22=""),"",IF(AND($D22<=V$6+6,$E22>=V$6),IF($N22="CRÍTICA","C","P"),"")) -> P | W22: =IF(OR($D22="",$E22=""),"",IF(AND($D22<=W$6+6,$E22>=W$6),IF($N22="CRÍTICA","C","P"),"")) -> P | X22: =IF(OR($D22="",$E22=""),"",IF(AND($D22<=X$6+6,$E22>=X$6),IF($N22="CRÍTICA","C","P"),"")) -> P | ... BR22: =IF(OR($D22="",$E22=""),"",IF(AND($D22<=BR$6+6,$E22>=BR$6),IF($N22="CRÍTICA","C","P"),"")) | BT22: =IF(SUM($D48:$O48)=0,"",_xlfn.MINIFS($D$32:$O$32,$D48:$O48,">0")) -> 46266 | BU22: =IF(BT22="","",EOMONTH(_xlfn.MAXIFS($D$32:$O$32,$D48:$O48,">0"),0)) -> 46538 | BV22: Contrato | BW22: 343 | BX22: =IF(E22="","",IF(COUNTIF($G23:$G$28,$A22)+COUNTIF($H23:$H$28,$A22)+COUNTIF($I23:$I$28,$A22)=0,_xlfn.MAXIFS($E$7:$E$27,$BW$7:$BW$27,$BW22),MIN(IF(COUNTIF($G23:$G$28,$A22)>0,_xlfn.MINIFS($BY23:$BY$28,$G23:$G$28,$A22),99999999),IF(COUNTIF($H23:$H$28,$A22)>0,_xlfn.MINIFS($BY23:$BY$28,$H23:$H$28,$A22),99999999),IF(COUNTIF($I23:$I$28,$A22)>0,_xlfn.MINIFS($BY23:$BY$28,$I23:$I$28,$A22),99999999))-1)) -> 46538 | BY22: =IF(BX22="","",BX22-F22+1) -> 46266 | BZ22: =IF(AND(D22<>"",D22>DATA_GESTAO),D22+ROW()/1000000,"") | CA22: =SUMPRODUCT(($BW$7:$BW$27=$BW22)*($G$7:$I$27<>"")) -> 0
A23: 343-M1 | B23: 343 | C23: Plano do motor: F01 Subadutora SAT.SB1.192 · ADUT_PEAD | D23: =IF(BT23="","",MAX(BT23,IF($G23="",0,_xlfn.MAXIFS($E$6:$E22,$A$6:$A22,$G23)+1),IF($H23="",0,_xlfn.MAXIFS($E$6:$E22,$A$6:$A22,$H23)+1),IF($I23="",0,_xlfn.MAXIFS($E$6:$E22,$A$6:$A22,$I23)+1))) -> 46296 | E23: =IF(D23="","",D23+F23-1) -> 46343 | F23: =IF(OR(BT23="",BU23=""),"",BU23-BT23+1) -> 48 | K23: 906096.59 | L23: 543880.94 | M23: =IF(OR(BX23="",E23=""),"",BX23-E23) -> 182 | N23: =IF(M23="","",IF(CA23=0,"sem rede",IF(M23<=0,"CRÍTICA",""))) -> sem rede | O23: =IF(OR(J23="",K23=""),"",J23*K23) | P23: =IF(OR(BT23="",BU23=""),"sem data",IF(OR(AND(G23<>"",COUNTIF($A$7:$A$27,G23)=0),AND(H23<>"",COUNTIF($A$7:$A$27,H23)=0),AND(I23<>"",COUNTIF($A$7:$A$27,I23)=0)),"predecessora inexistente",IF(OR(AND(G23<>"",COUNTIF($A$6:$A22,G23)=0),AND(H23<>"",COUNTIF($A$6:$A22,H23)=0),AND(I23<>"",COUNTIF($A$6:$A22,I23)=0)),"predecessora abaixo da tarefa","ok"))) -> ok | Q23: =IF(OR($D23="",$E23=""),"",IF(AND($D23<=Q$6+6,$E23>=Q$6),IF($N23="CRÍTICA","C","P"),"")) | R23: =IF(OR($D23="",$E23=""),"",IF(AND($D23<=R$6+6,$E23>=R$6),IF($N23="CRÍTICA","C","P"),"")) | S23: =IF(OR($D23="",$E23=""),"",IF(AND($D23<=S$6+6,$E23>=S$6),IF($N23="CRÍTICA","C","P"),"")) | T23: =IF(OR($D23="",$E23=""),"",IF(AND($D23<=T$6+6,$E23>=T$6),IF($N23="CRÍTICA","C","P"),"")) | U23: =IF(OR($D23="",$E23=""),"",IF(AND($D23<=U$6+6,$E23>=U$6),IF($N23="CRÍTICA","C","P"),"")) -> P | V23: =IF(OR($D23="",$E23=""),"",IF(AND($D23<=V$6+6,$E23>=V$6),IF($N23="CRÍTICA","C","P"),"")) -> P | W23: =IF(OR($D23="",$E23=""),"",IF(AND($D23<=W$6+6,$E23>=W$6),IF($N23="CRÍTICA","C","P"),"")) -> P | X23: =IF(OR($D23="",$E23=""),"",IF(AND($D23<=X$6+6,$E23>=X$6),IF($N23="CRÍTICA","C","P"),"")) -> P | ... BR23: =IF(OR($D23="",$E23=""),"",IF(AND($D23<=BR$6+6,$E23>=BR$6),IF($N23="CRÍTICA","C","P"),"")) | BT23: 46296 | BU23: 46343 | BV23: Motor | BW23: 343M | BX23: =IF(E23="","",IF(COUNTIF($G24:$G$28,$A23)+COUNTIF($H24:$H$28,$A23)+COUNTIF($I24:$I$28,$A23)=0,_xlfn.MAXIFS($E$7:$E$27,$BW$7:$BW$27,$BW23),MIN(IF(COUNTIF($G24:$G$28,$A23)>0,_xlfn.MINIFS($BY24:$BY$28,$G24:$G$28,$A23),99999999),IF(COUNTIF($H24:$H$28,$A23)>0,_xlfn.MINIFS($BY24:$BY$28,$H24:$H$28,$A23),99999999),IF(COUNTIF($I24:$I$28,$A23)>0,_xlfn.MINIFS($BY24:$BY$28,$I24:$I$28,$A23),99999999))-1)) -> 46525 | BY23: =IF(BX23="","",BX23-F23+1) -> 46478 | BZ23: =IF(AND(D23<>"",D23>DATA_GESTAO),D23+ROW()/1000000,"") | CA23: =SUMPRODUCT(($BW$7:$BW$27=$BW23)*($G$7:$I$27<>"")) -> 0
A24: 343-M2 | B24: 343 | C24: Plano do motor: F01 Subadutora SAT.SB1.192 · ADUT_FOFO | D24: =IF(BT24="","",MAX(BT24,IF($G24="",0,_xlfn.MAXIFS($E$6:$E23,$A$6:$A23,$G24)+1),IF($H24="",0,_xlfn.MAXIFS($E$6:$E23,$A$6:$A23,$H24)+1),IF($I24="",0,_xlfn.MAXIFS($E$6:$E23,$A$6:$A23,$I24)+1))) -> 46344 | E24: =IF(D24="","",D24+F24-1) -> 46358 | F24: =IF(OR(BT24="",BU24=""),"",BU24-BT24+1) -> 15 | K24: 94175.285 | L24: 56528.347 | M24: =IF(OR(BX24="",E24=""),"",BX24-E24) -> 167 | N24: =IF(M24="","",IF(CA24=0,"sem rede",IF(M24<=0,"CRÍTICA",""))) -> sem rede | O24: =IF(OR(J24="",K24=""),"",J24*K24) | P24: =IF(OR(BT24="",BU24=""),"sem data",IF(OR(AND(G24<>"",COUNTIF($A$7:$A$27,G24)=0),AND(H24<>"",COUNTIF($A$7:$A$27,H24)=0),AND(I24<>"",COUNTIF($A$7:$A$27,I24)=0)),"predecessora inexistente",IF(OR(AND(G24<>"",COUNTIF($A$6:$A23,G24)=0),AND(H24<>"",COUNTIF($A$6:$A23,H24)=0),AND(I24<>"",COUNTIF($A$6:$A23,I24)=0)),"predecessora abaixo da tarefa","ok"))) -> ok | Q24: =IF(OR($D24="",$E24=""),"",IF(AND($D24<=Q$6+6,$E24>=Q$6),IF($N24="CRÍTICA","C","P"),"")) | R24: =IF(OR($D24="",$E24=""),"",IF(AND($D24<=R$6+6,$E24>=R$6),IF($N24="CRÍTICA","C","P"),"")) | S24: =IF(OR($D24="",$E24=""),"",IF(AND($D24<=S$6+6,$E24>=S$6),IF($N24="CRÍTICA","C","P"),"")) | T24: =IF(OR($D24="",$E24=""),"",IF(AND($D24<=T$6+6,$E24>=T$6),IF($N24="CRÍTICA","C","P"),"")) | U24: =IF(OR($D24="",$E24=""),"",IF(AND($D24<=U$6+6,$E24>=U$6),IF($N24="CRÍTICA","C","P"),"")) | V24: =IF(OR($D24="",$E24=""),"",IF(AND($D24<=V$6+6,$E24>=V$6),IF($N24="CRÍTICA","C","P"),"")) | W24: =IF(OR($D24="",$E24=""),"",IF(AND($D24<=W$6+6,$E24>=W$6),IF($N24="CRÍTICA","C","P"),"")) | X24: =IF(OR($D24="",$E24=""),"",IF(AND($D24<=X$6+6,$E24>=X$6),IF($N24="CRÍTICA","C","P"),"")) | ... BR24: =IF(OR($D24="",$E24=""),"",IF(AND($D24<=BR$6+6,$E24>=BR$6),IF($N24="CRÍTICA","C","P"),"")) | BT24: 46344 | BU24: 46358 | BV24: Motor | BW24: 343M | BX24: =IF(E24="","",IF(COUNTIF($G25:$G$28,$A24)+COUNTIF($H25:$H$28,$A24)+COUNTIF($I25:$I$28,$A24)=0,_xlfn.MAXIFS($E$7:$E$27,$BW$7:$BW$27,$BW24),MIN(IF(COUNTIF($G25:$G$28,$A24)>0,_xlfn.MINIFS($BY25:$BY$28,$G25:$G$28,$A24),99999999),IF(COUNTIF($H25:$H$28,$A24)>0,_xlfn.MINIFS($BY25:$BY$28,$H25:$H$28,$A24),99999999),IF(COUNTIF($I25:$I$28,$A24)>0,_xlfn.MINIFS($BY25:$BY$28,$I25:$I$28,$A24),99999999))-1)) -> 46525 | BY24: =IF(BX24="","",BX24-F24+1) -> 46511 | BZ24: =IF(AND(D24<>"",D24>DATA_GESTAO),D24+ROW()/1000000,"") -> 46344 | CA24: =SUMPRODUCT(($BW$7:$BW$27=$BW24)*($G$7:$I$27<>"")) -> 0
A25: 343-M3 | B25: 343 | C25: Plano do motor: F02 Civil: canteiro, caixas e interligações · CIVIL EQUIPE CIVIL TAF | D25: =IF(BT25="","",MAX(BT25,IF($G25="",0,_xlfn.MAXIFS($E$6:$E24,$A$6:$A24,$G25)+1),IF($H25="",0,_xlfn.MAXIFS($E$6:$E24,$A$6:$A24,$H25)+1),IF($I25="",0,_xlfn.MAXIFS($E$6:$E24,$A$6:$A24,$I25)+1))) -> 46296 | E25: =IF(D25="","",D25+F25-1) -> 46482 | F25: =IF(OR(BT25="",BU25=""),"",BU25-BT25+1) -> 187 | K25: 294931.07 | L25: 177031.22 | M25: =IF(OR(BX25="",E25=""),"",BX25-E25) -> 43 | N25: =IF(M25="","",IF(CA25=0,"sem rede",IF(M25<=0,"CRÍTICA",""))) -> sem rede | O25: =IF(OR(J25="",K25=""),"",J25*K25) | P25: =IF(OR(BT25="",BU25=""),"sem data",IF(OR(AND(G25<>"",COUNTIF($A$7:$A$27,G25)=0),AND(H25<>"",COUNTIF($A$7:$A$27,H25)=0),AND(I25<>"",COUNTIF($A$7:$A$27,I25)=0)),"predecessora inexistente",IF(OR(AND(G25<>"",COUNTIF($A$6:$A24,G25)=0),AND(H25<>"",COUNTIF($A$6:$A24,H25)=0),AND(I25<>"",COUNTIF($A$6:$A24,I25)=0)),"predecessora abaixo da tarefa","ok"))) -> ok | Q25: =IF(OR($D25="",$E25=""),"",IF(AND($D25<=Q$6+6,$E25>=Q$6),IF($N25="CRÍTICA","C","P"),"")) | R25: =IF(OR($D25="",$E25=""),"",IF(AND($D25<=R$6+6,$E25>=R$6),IF($N25="CRÍTICA","C","P"),"")) | S25: =IF(OR($D25="",$E25=""),"",IF(AND($D25<=S$6+6,$E25>=S$6),IF($N25="CRÍTICA","C","P"),"")) | T25: =IF(OR($D25="",$E25=""),"",IF(AND($D25<=T$6+6,$E25>=T$6),IF($N25="CRÍTICA","C","P"),"")) | U25: =IF(OR($D25="",$E25=""),"",IF(AND($D25<=U$6+6,$E25>=U$6),IF($N25="CRÍTICA","C","P"),"")) -> P | V25: =IF(OR($D25="",$E25=""),"",IF(AND($D25<=V$6+6,$E25>=V$6),IF($N25="CRÍTICA","C","P"),"")) -> P | W25: =IF(OR($D25="",$E25=""),"",IF(AND($D25<=W$6+6,$E25>=W$6),IF($N25="CRÍTICA","C","P"),"")) -> P | X25: =IF(OR($D25="",$E25=""),"",IF(AND($D25<=X$6+6,$E25>=X$6),IF($N25="CRÍTICA","C","P"),"")) -> P | ... BR25: =IF(OR($D25="",$E25=""),"",IF(AND($D25<=BR$6+6,$E25>=BR$6),IF($N25="CRÍTICA","C","P"),"")) | BT25: 46296 | BU25: 46482 | BV25: Motor | BW25: 343M | BX25: =IF(E25="","",IF(COUNTIF($G26:$G$28,$A25)+COUNTIF($H26:$H$28,$A25)+COUNTIF($I26:$I$28,$A25)=0,_xlfn.MAXIFS($E$7:$E$27,$BW$7:$BW$27,$BW25),MIN(IF(COUNTIF($G26:$G$28,$A25)>0,_xlfn.MINIFS($BY26:$BY$28,$G26:$G$28,$A25),99999999),IF(COUNTIF($H26:$H$28,$A25)>0,_xlfn.MINIFS($BY26:$BY$28,$H26:$H$28,$A25),99999999),IF(COUNTIF($I26:$I$28,$A25)>0,_xlfn.MINIFS($BY26:$BY$28,$I26:$I$28,$A25),99999999))-1)) -> 46525 | BY25: =IF(BX25="","",BX25-F25+1) -> 46339 | BZ25: =IF(AND(D25<>"",D25>DATA_GESTAO),D25+ROW()/1000000,"") | CA25: =SUMPRODUCT(($BW$7:$BW$27=$BW25)*($G$7:$I$27<>"")) -> 0
A26: 343-M4 | B26: 343 | C26: Plano do motor: F03 Material da obra · MATERIAL VIABILIDADE TAF | D26: =IF(BT26="","",MAX(BT26,IF($G26="",0,_xlfn.MAXIFS($E$6:$E25,$A$6:$A25,$G26)+1),IF($H26="",0,_xlfn.MAXIFS($E$6:$E25,$A$6:$A25,$H26)+1),IF($I26="",0,_xlfn.MAXIFS($E$6:$E25,$A$6:$A25,$I26)+1))) -> 46296 | E26: =IF(D26="","",D26+F26-1) -> 46525 | F26: =IF(OR(BT26="",BU26=""),"",BU26-BT26+1) -> 230 | K26: 3938808.2 | L26: 2364254.2 | M26: =IF(OR(BX26="",E26=""),"",BX26-E26) -> 0 | N26: =IF(M26="","",IF(CA26=0,"sem rede",IF(M26<=0,"CRÍTICA",""))) -> sem rede | O26: =IF(OR(J26="",K26=""),"",J26*K26) | P26: =IF(OR(BT26="",BU26=""),"sem data",IF(OR(AND(G26<>"",COUNTIF($A$7:$A$27,G26)=0),AND(H26<>"",COUNTIF($A$7:$A$27,H26)=0),AND(I26<>"",COUNTIF($A$7:$A$27,I26)=0)),"predecessora inexistente",IF(OR(AND(G26<>"",COUNTIF($A$6:$A25,G26)=0),AND(H26<>"",COUNTIF($A$6:$A25,H26)=0),AND(I26<>"",COUNTIF($A$6:$A25,I26)=0)),"predecessora abaixo da tarefa","ok"))) -> ok | Q26: =IF(OR($D26="",$E26=""),"",IF(AND($D26<=Q$6+6,$E26>=Q$6),IF($N26="CRÍTICA","C","P"),"")) | R26: =IF(OR($D26="",$E26=""),"",IF(AND($D26<=R$6+6,$E26>=R$6),IF($N26="CRÍTICA","C","P"),"")) | S26: =IF(OR($D26="",$E26=""),"",IF(AND($D26<=S$6+6,$E26>=S$6),IF($N26="CRÍTICA","C","P"),"")) | T26: =IF(OR($D26="",$E26=""),"",IF(AND($D26<=T$6+6,$E26>=T$6),IF($N26="CRÍTICA","C","P"),"")) | U26: =IF(OR($D26="",$E26=""),"",IF(AND($D26<=U$6+6,$E26>=U$6),IF($N26="CRÍTICA","C","P"),"")) -> P | V26: =IF(OR($D26="",$E26=""),"",IF(AND($D26<=V$6+6,$E26>=V$6),IF($N26="CRÍTICA","C","P"),"")) -> P | W26: =IF(OR($D26="",$E26=""),"",IF(AND($D26<=W$6+6,$E26>=W$6),IF($N26="CRÍTICA","C","P"),"")) -> P | X26: =IF(OR($D26="",$E26=""),"",IF(AND($D26<=X$6+6,$E26>=X$6),IF($N26="CRÍTICA","C","P"),"")) -> P | ... BR26: =IF(OR($D26="",$E26=""),"",IF(AND($D26<=BR$6+6,$E26>=BR$6),IF($N26="CRÍTICA","C","P"),"")) | BT26: 46296 | BU26: 46525 | BV26: Motor | BW26: 343M | BX26: =IF(E26="","",IF(COUNTIF($G27:$G$28,$A26)+COUNTIF($H27:$H$28,$A26)+COUNTIF($I27:$I$28,$A26)=0,_xlfn.MAXIFS($E$7:$E$27,$BW$7:$BW$27,$BW26),MIN(IF(COUNTIF($G27:$G$28,$A26)>0,_xlfn.MINIFS($BY27:$BY$28,$G27:$G$28,$A26),99999999),IF(COUNTIF($H27:$H$28,$A26)>0,_xlfn.MINIFS($BY27:$BY$28,$H27:$H$28,$A26),99999999),IF(COUNTIF($I27:$I$28,$A26)>0,_xlfn.MINIFS($BY27:$BY$28,$I27:$I$28,$A26),99999999))-1)) -> 46525 | BY26: =IF(BX26="","",BX26-F26+1) -> 46296 | BZ26: =IF(AND(D26<>"",D26>DATA_GESTAO),D26+ROW()/1000000,"") | CA26: =SUMPRODUCT(($BW$7:$BW$27=$BW26)*($G$7:$I$27<>"")) -> 0
A27: 343-M5 | B27: 343 | C27: Plano do motor: Administração do contrato (ADM) | D27: =IF(BT27="","",MAX(BT27,IF($G27="",0,_xlfn.MAXIFS($E$6:$E26,$A$6:$A26,$G27)+1),IF($H27="",0,_xlfn.MAXIFS($E$6:$E26,$A$6:$A26,$H27)+1),IF($I27="",0,_xlfn.MAXIFS($E$6:$E26,$A$6:$A26,$I27)+1))) -> 46266 | E27: =IF(D27="","",D27+F27-1) -> 46525 | F27: =IF(OR(BT27="",BU27=""),"",BU27-BT27+1) -> 260 | L27: 463923.01 | M27: =IF(OR(BX27="",E27=""),"",BX27-E27) -> 0 | N27: =IF(M27="","",IF(CA27=0,"sem rede",IF(M27<=0,"CRÍTICA",""))) -> sem rede | O27: =IF(OR(J27="",K27=""),"",J27*K27) | P27: =IF(OR(BT27="",BU27=""),"sem data",IF(OR(AND(G27<>"",COUNTIF($A$7:$A$27,G27)=0),AND(H27<>"",COUNTIF($A$7:$A$27,H27)=0),AND(I27<>"",COUNTIF($A$7:$A$27,I27)=0)),"predecessora inexistente",IF(OR(AND(G27<>"",COUNTIF($A$6:$A26,G27)=0),AND(H27<>"",COUNTIF($A$6:$A26,H27)=0),AND(I27<>"",COUNTIF($A$6:$A26,I27)=0)),"predecessora abaixo da tarefa","ok"))) -> ok | Q27: =IF(OR($D27="",$E27=""),"",IF(AND($D27<=Q$6+6,$E27>=Q$6),IF($N27="CRÍTICA","C","P"),"")) -> P | R27: =IF(OR($D27="",$E27=""),"",IF(AND($D27<=R$6+6,$E27>=R$6),IF($N27="CRÍTICA","C","P"),"")) -> P | S27: =IF(OR($D27="",$E27=""),"",IF(AND($D27<=S$6+6,$E27>=S$6),IF($N27="CRÍTICA","C","P"),"")) -> P | T27: =IF(OR($D27="",$E27=""),"",IF(AND($D27<=T$6+6,$E27>=T$6),IF($N27="CRÍTICA","C","P"),"")) -> P | U27: =IF(OR($D27="",$E27=""),"",IF(AND($D27<=U$6+6,$E27>=U$6),IF($N27="CRÍTICA","C","P"),"")) -> P | V27: =IF(OR($D27="",$E27=""),"",IF(AND($D27<=V$6+6,$E27>=V$6),IF($N27="CRÍTICA","C","P"),"")) -> P | W27: =IF(OR($D27="",$E27=""),"",IF(AND($D27<=W$6+6,$E27>=W$6),IF($N27="CRÍTICA","C","P"),"")) -> P | X27: =IF(OR($D27="",$E27=""),"",IF(AND($D27<=X$6+6,$E27>=X$6),IF($N27="CRÍTICA","C","P"),"")) -> P | ... BR27: =IF(OR($D27="",$E27=""),"",IF(AND($D27<=BR$6+6,$E27>=BR$6),IF($N27="CRÍTICA","C","P"),"")) | BT27: 46266 | BU27: 46525 | BV27: Motor | BW27: 343M | BX27: =IF(E27="","",IF(COUNTIF($G28:$G$28,$A27)+COUNTIF($H28:$H$28,$A27)+COUNTIF($I28:$I$28,$A27)=0,_xlfn.MAXIFS($E$7:$E$27,$BW$7:$BW$27,$BW27),MIN(IF(COUNTIF($G28:$G$28,$A27)>0,_xlfn.MINIFS($BY28:$BY$28,$G28:$G$28,$A27),99999999),IF(COUNTIF($H28:$H$28,$A27)>0,_xlfn.MINIFS($BY28:$BY$28,$H28:$H$28,$A27),99999999),IF(COUNTIF($I28:$I$28,$A27)>0,_xlfn.MINIFS($BY28:$BY$28,$I28:$I$28,$A27),99999999))-1)) -> 46525 | BY27: =IF(BX27="","",BX27-F27+1) -> 46266 | BZ27: =IF(AND(D27<>"",D27>DATA_GESTAO),D27+ROW()/1000000,"") | CA27: =SUMPRODUCT(($BW$7:$BW$27=$BW27)*($G$7:$I$27<>"")) -> 0
A29: Barras: azul = planejado; vermelho = etapa crítica (folga 0 e rede com predecessoras); ▼ vermelho = data de gestão (corte da 02. PARÂMETROS); ▲ azul = hoje. Digitou predecessora? Início = o maior entre a data da fonte e o fim da predecessora + 1.
A30: Valor da 342 = eventograma Anexo VII distribuído pelos dias de execução de cada evento no plano REV13; a medição de cada BM (UN só na conclusão) está na 04, linha 6. Valor da 343 = cronograma CAESB; o plano do motor (linhas 343-M) segue a execução, porque a 343 é medida por preço unitário. Custo planejado por etapa: a fonte não traz (só por mês, na grade abaixo), então fica 'pendente'.
A31: VALOR PLANEJADO POR ETAPA E POR MÊS (R$, cronograma de cada obra). É daqui que saem as datas de início e fim.
A32: ID | B32: Obra | C32: Etapa | D32: 46266 | E32: =EDATE(D32,1) -> 46296 | F32: =EDATE(E32,1) -> 46327 | G32: =EDATE(F32,1) -> 46357 | H32: =EDATE(G32,1) -> 46388 | I32: =EDATE(H32,1) -> 46419 | J32: =EDATE(I32,1) -> 46447 | K32: =EDATE(J32,1) -> 46478 | L32: =EDATE(K32,1) -> 46508 | ... O32: =EDATE(N32,1) -> 46600 | P32: Total
A33: 342-01 | B33: 342 | C33: CANTEIRO DE OBRAS | D33: =SUMPRODUCT(($D$74:$D$103=$A33)*$F$74:$F$103*(((($H$74:$H$103<EOMONTH(D$32,0))*$H$74:$H$103+($H$74:$H$103>=EOMONTH(D$32,0))*EOMONTH(D$32,0))-(($G$74:$G$103>D$32)*$G$74:$G$103+($G$74:$G$103<=D$32)*D$32)+1)>0)*((($H$74:$H$103<EOMONTH(D$32,0))*$H$74:$H$103+($H$74:$H$103>=EOMONTH(D$32,0))*EOMONTH(D$32,0))-(($G$74:$G$103>D$32)*$G$74:$G$103+($G$74:$G$103<=D$32)*D$32)+1)/($H$74:$H$103-$G$74:$G$103+1)) -> 0 | E33: =SUMPRODUCT(($D$74:$D$103=$A33)*$F$74:$F$103*(((($H$74:$H$103<EOMONTH(E$32,0))*$H$74:$H$103+($H$74:$H$103>=EOMONTH(E$32,0))*EOMONTH(E$32,0))-(($G$74:$G$103>E$32)*$G$74:$G$103+($G$74:$G$103<=E$32)*E$32)+1)>0)*((($H$74:$H$103<EOMONTH(E$32,0))*$H$74:$H$103+($H$74:$H$103>=EOMONTH(E$32,0))*EOMONTH(E$32,0))-(($G$74:$G$103>E$32)*$G$74:$G$103+($G$74:$G$103<=E$32)*E$32)+1)/($H$74:$H$103-$G$74:$G$103+1)) -> 5467.7732 | F33: =SUMPRODUCT(($D$74:$D$103=$A33)*$F$74:$F$103*(((($H$74:$H$103<EOMONTH(F$32,0))*$H$74:$H$103+($H$74:$H$103>=EOMONTH(F$32,0))*EOMONTH(F$32,0))-(($G$74:$G$103>F$32)*$G$74:$G$103+($G$74:$G$103<=F$32)*F$32)+1)>0)*((($H$74:$H$103<EOMONTH(F$32,0))*$H$74:$H$103+($H$74:$H$103>=EOMONTH(F$32,0))*EOMONTH(F$32,0))-(($G$74:$G$103>F$32)*$G$74:$G$103+($G$74:$G$103<=F$32)*F$32)+1)/($H$74:$H$103-$G$74:$G$103+1)) -> 12617.938 | G33: =SUMPRODUCT(($D$74:$D$103=$A33)*$F$74:$F$103*(((($H$74:$H$103<EOMONTH(G$32,0))*$H$74:$H$103+($H$74:$H$103>=EOMONTH(G$32,0))*EOMONTH(G$32,0))-(($G$74:$G$103>G$32)*$G$74:$G$103+($G$74:$G$103<=G$32)*G$32)+1)>0)*((($H$74:$H$103<EOMONTH(G$32,0))*$H$74:$H$103+($H$74:$H$103>=EOMONTH(G$32,0))*EOMONTH(G$32,0))-(($G$74:$G$103>G$32)*$G$74:$G$103+($G$74:$G$103<=G$32)*G$32)+1)/($H$74:$H$103-$G$74:$G$103+1)) -> 13038.536 | H33: =SUMPRODUCT(($D$74:$D$103=$A33)*$F$74:$F$103*(((($H$74:$H$103<EOMONTH(H$32,0))*$H$74:$H$103+($H$74:$H$103>=EOMONTH(H$32,0))*EOMONTH(H$32,0))-(($G$74:$G$103>H$32)*$G$74:$G$103+($G$74:$G$103<=H$32)*H$32)+1)>0)*((($H$74:$H$103<EOMONTH(H$32,0))*$H$74:$H$103+($H$74:$H$103>=EOMONTH(H$32,0))*EOMONTH(H$32,0))-(($G$74:$G$103>H$32)*$G$74:$G$103+($G$74:$G$103<=H$32)*H$32)+1)/($H$74:$H$103-$G$74:$G$103+1)) -> 13038.536 | I33: =SUMPRODUCT(($D$74:$D$103=$A33)*$F$74:$F$103*(((($H$74:$H$103<EOMONTH(I$32,0))*$H$74:$H$103+($H$74:$H$103>=EOMONTH(I$32,0))*EOMONTH(I$32,0))-(($G$74:$G$103>I$32)*$G$74:$G$103+($G$74:$G$103<=I$32)*I$32)+1)>0)*((($H$74:$H$103<EOMONTH(I$32,0))*$H$74:$H$103+($H$74:$H$103>=EOMONTH(I$32,0))*EOMONTH(I$32,0))-(($G$74:$G$103>I$32)*$G$74:$G$103+($G$74:$G$103<=I$32)*I$32)+1)/($H$74:$H$103-$G$74:$G$103+1)) -> 11776.742 | J33: =SUMPRODUCT(($D$74:$D$103=$A33)*$F$74:$F$103*(((($H$74:$H$103<EOMONTH(J$32,0))*$H$74:$H$103+($H$74:$H$103>=EOMONTH(J$32,0))*EOMONTH(J$32,0))-(($G$74:$G$103>J$32)*$G$74:$G$103+($G$74:$G$103<=J$32)*J$32)+1)>0)*((($H$74:$H$103<EOMONTH(J$32,0))*$H$74:$H$103+($H$74:$H$103>=EOMONTH(J$32,0))*EOMONTH(J$32,0))-(($G$74:$G$103>J$32)*$G$74:$G$103+($G$74:$G$103<=J$32)*J$32)+1)/($H$74:$H$103-$G$74:$G$103+1)) -> 13038.536 | K33: =SUMPRODUCT(($D$74:$D$103=$A33)*$F$74:$F$103*(((($H$74:$H$103<EOMONTH(K$32,0))*$H$74:$H$103+($H$74:$H$103>=EOMONTH(K$32,0))*EOMONTH(K$32,0))-(($G$74:$G$103>K$32)*$G$74:$G$103+($G$74:$G$103<=K$32)*K$32)+1)>0)*((($H$74:$H$103<EOMONTH(K$32,0))*$H$74:$H$103+($H$74:$H$103>=EOMONTH(K$32,0))*EOMONTH(K$32,0))-(($G$74:$G$103>K$32)*$G$74:$G$103+($G$74:$G$103<=K$32)*K$32)+1)/($H$74:$H$103-$G$74:$G$103+1)) -> 12617.938 | ... O33: =SUMPRODUCT(($D$74:$D$103=$A33)*$F$74:$F$103*(((($H$74:$H$103<EOMONTH(O$32,0))*$H$74:$H$103+($H$74:$H$103>=EOMONTH(O$32,0))*EOMONTH(O$32,0))-(($G$74:$G$103>O$32)*$G$74:$G$103+($G$74:$G$103<=O$32)*O$32)+1)>0)*((($H$74:$H$103<EOMONTH(O$32,0))*$H$74:$H$103+($H$74:$H$103>=EOMONTH(O$32,0))*EOMONTH(O$32,0))-(($G$74:$G$103>O$32)*$G$74:$G$103+($G$74:$G$103<=O$32)*O$32)+1)/($H$74:$H$103-$G$74:$G$103+1)) -> 2102.9897 | P33: =SUM(D33:O33) -> 122394
A34: 342-02 | B34: 342 | C34: ADMINISTRAÇÃO LOCAL | D34: =SUMPRODUCT(($D$74:$D$103=$A34)*$F$74:$F$103*(((($H$74:$H$103<EOMONTH(D$32,0))*$H$74:$H$103+($H$74:$H$103>=EOMONTH(D$32,0))*EOMONTH(D$32,0))-(($G$74:$G$103>D$32)*$G$74:$G$103+($G$74:$G$103<=D$32)*D$32)+1)>0)*((($H$74:$H$103<EOMONTH(D$32,0))*$H$74:$H$103+($H$74:$H$103>=EOMONTH(D$32,0))*EOMONTH(D$32,0))-(($G$74:$G$103>D$32)*$G$74:$G$103+($G$74:$G$103<=D$32)*D$32)+1)/($H$74:$H$103-$G$74:$G$103+1)) -> 0 | E34: =SUMPRODUCT(($D$74:$D$103=$A34)*$F$74:$F$103*(((($H$74:$H$103<EOMONTH(E$32,0))*$H$74:$H$103+($H$74:$H$103>=EOMONTH(E$32,0))*EOMONTH(E$32,0))-(($G$74:$G$103>E$32)*$G$74:$G$103+($G$74:$G$103<=E$32)*E$32)+1)>0)*((($H$74:$H$103<EOMONTH(E$32,0))*$H$74:$H$103+($H$74:$H$103>=EOMONTH(E$32,0))*EOMONTH(E$32,0))-(($G$74:$G$103>E$32)*$G$74:$G$103+($G$74:$G$103<=E$32)*E$32)+1)/($H$74:$H$103-$G$74:$G$103+1)) -> 21439.323 | F34: =SUMPRODUCT(($D$74:$D$103=$A34)*$F$74:$F$103*(((($H$74:$H$103<EOMONTH(F$32,0))*$H$74:$H$103+($H$74:$H$103>=EOMONTH(F$32,0))*EOMONTH(F$32,0))-(($G$74:$G$103>F$32)*$G$74:$G$103+($G$74:$G$103<=F$32)*F$32)+1)>0)*((($H$74:$H$103<EOMONTH(F$32,0))*$H$74:$H$103+($H$74:$H$103>=EOMONTH(F$32,0))*EOMONTH(F$32,0))-(($G$74:$G$103>F$32)*$G$74:$G$103+($G$74:$G$103<=F$32)*F$32)+1)/($H$74:$H$103-$G$74:$G$103+1)) -> 49475.361 | G34: =SUMPRODUCT(($D$74:$D$103=$A34)*$F$74:$F$103*(((($H$74:$H$103<EOMONTH(G$32,0))*$H$74:$H$103+($H$74:$H$103>=EOMONTH(G$32,0))*EOMONTH(G$32,0))-(($G$74:$G$103>G$32)*$G$74:$G$103+($G$74:$G$103<=G$32)*G$32)+1)>0)*((($H$74:$H$103<EOMONTH(G$32,0))*$H$74:$H$103+($H$74:$H$103>=EOMONTH(G$32,0))*EOMONTH(G$32,0))-(($G$74:$G$103>G$32)*$G$74:$G$103+($G$74:$G$103<=G$32)*G$32)+1)/($H$74:$H$103-$G$74:$G$103+1)) -> 51124.54 | H34: =SUMPRODUCT(($D$74:$D$103=$A34)*$F$74:$F$103*(((($H$74:$H$103<EOMONTH(H$32,0))*$H$74:$H$103+($H$74:$H$103>=EOMONTH(H$32,0))*EOMONTH(H$32,0))-(($G$74:$G$103>H$32)*$G$74:$G$103+($G$74:$G$103<=H$32)*H$32)+1)>0)*((($H$74:$H$103<EOMONTH(H$32,0))*$H$74:$H$103+($H$74:$H$103>=EOMONTH(H$32,0))*EOMONTH(H$32,0))-(($G$74:$G$103>H$32)*$G$74:$G$103+($G$74:$G$103<=H$32)*H$32)+1)/($H$74:$H$103-$G$74:$G$103+1)) -> 51124.54 | I34: =SUMPRODUCT(($D$74:$D$103=$A34)*$F$74:$F$103*(((($H$74:$H$103<EOMONTH(I$32,0))*$H$74:$H$103+($H$74:$H$103>=EOMONTH(I$32,0))*EOMONTH(I$32,0))-(($G$74:$G$103>I$32)*$G$74:$G$103+($G$74:$G$103<=I$32)*I$32)+1)>0)*((($H$74:$H$103<EOMONTH(I$32,0))*$H$74:$H$103+($H$74:$H$103>=EOMONTH(I$32,0))*EOMONTH(I$32,0))-(($G$74:$G$103>I$32)*$G$74:$G$103+($G$74:$G$103<=I$32)*I$32)+1)/($H$74:$H$103-$G$74:$G$103+1)) -> 46177.003 | J34: =SUMPRODUCT(($D$74:$D$103=$A34)*$F$74:$F$103*(((($H$74:$H$103<EOMONTH(J$32,0))*$H$74:$H$103+($H$74:$H$103>=EOMONTH(J$32,0))*EOMONTH(J$32,0))-(($G$74:$G$103>J$32)*$G$74:$G$103+($G$74:$G$103<=J$32)*J$32)+1)>0)*((($H$74:$H$103<EOMONTH(J$32,0))*$H$74:$H$103+($H$74:$H$103>=EOMONTH(J$32,0))*EOMONTH(J$32,0))-(($G$74:$G$103>J$32)*$G$74:$G$103+($G$74:$G$103<=J$32)*J$32)+1)/($H$74:$H$103-$G$74:$G$103+1)) -> 51124.54 | K34: =SUMPRODUCT(($D$74:$D$103=$A34)*$F$74:$F$103*(((($H$74:$H$103<EOMONTH(K$32,0))*$H$74:$H$103+($H$74:$H$103>=EOMONTH(K$32,0))*EOMONTH(K$32,0))-(($G$74:$G$103>K$32)*$G$74:$G$103+($G$74:$G$103<=K$32)*K$32)+1)>0)*((($H$74:$H$103<EOMONTH(K$32,0))*$H$74:$H$103+($H$74:$H$103>=EOMONTH(K$32,0))*EOMONTH(K$32,0))-(($G$74:$G$103>K$32)*$G$74:$G$103+($G$74:$G$103<=K$32)*K$32)+1)/($H$74:$H$103-$G$74:$G$103+1)) -> 49475.361 | ... O34: =SUMPRODUCT(($D$74:$D$103=$A34)*$F$74:$F$103*(((($H$74:$H$103<EOMONTH(O$32,0))*$H$74:$H$103+($H$74:$H$103>=EOMONTH(O$32,0))*EOMONTH(O$32,0))-(($G$74:$G$103>O$32)*$G$74:$G$103+($G$74:$G$103<=O$32)*O$32)+1)>0)*((($H$74:$H$103<EOMONTH(O$32,0))*$H$74:$H$103+($H$74:$H$103>=EOMONTH(O$32,0))*EOMONTH(O$32,0))-(($G$74:$G$103>O$32)*$G$74:$G$103+($G$74:$G$103<=O$32)*O$32)+1)/($H$74:$H$103-$G$74:$G$103+1)) -> 8245.8935 | P34: =SUM(D34:O34) -> 479911
A35: 342-03 | B35: 342 | C35: TERRAPLANAGEM E DESVIO DE TUBULAÇÃO | D35: =SUMPRODUCT(($D$74:$D$103=$A35)*$F$74:$F$103*(((($H$74:$H$103<EOMONTH(D$32,0))*$H$74:$H$103+($H$74:$H$103>=EOMONTH(D$32,0))*EOMONTH(D$32,0))-(($G$74:$G$103>D$32)*$G$74:$G$103+($G$74:$G$103<=D$32)*D$32)+1)>0)*((($H$74:$H$103<EOMONTH(D$32,0))*$H$74:$H$103+($H$74:$H$103>=EOMONTH(D$32,0))*EOMONTH(D$32,0))-(($G$74:$G$103>D$32)*$G$74:$G$103+($G$74:$G$103<=D$32)*D$32)+1)/($H$74:$H$103-$G$74:$G$103+1)) -> 0 | E35: =SUMPRODUCT(($D$74:$D$103=$A35)*$F$74:$F$103*(((($H$74:$H$103<EOMONTH(E$32,0))*$H$74:$H$103+($H$74:$H$103>=EOMONTH(E$32,0))*EOMONTH(E$32,0))-(($G$74:$G$103>E$32)*$G$74:$G$103+($G$74:$G$103<=E$32)*E$32)+1)>0)*((($H$74:$H$103<EOMONTH(E$32,0))*$H$74:$H$103+($H$74:$H$103>=EOMONTH(E$32,0))*EOMONTH(E$32,0))-(($G$74:$G$103>E$32)*$G$74:$G$103+($G$74:$G$103<=E$32)*E$32)+1)/($H$74:$H$103-$G$74:$G$103+1)) -> 131545.55 | F35: =SUMPRODUCT(($D$74:$D$103=$A35)*$F$74:$F$103*(((($H$74:$H$103<EOMONTH(F$32,0))*$H$74:$H$103+($H$74:$H$103>=EOMONTH(F$32,0))*EOMONTH(F$32,0))-(($G$74:$G$103>F$32)*$G$74:$G$103+($G$74:$G$103<=F$32)*F$32)+1)>0)*((($H$74:$H$103<EOMONTH(F$32,0))*$H$74:$H$103+($H$74:$H$103>=EOMONTH(F$32,0))*EOMONTH(F$32,0))-(($G$74:$G$103>F$32)*$G$74:$G$103+($G$74:$G$103<=F$32)*F$32)+1)/($H$74:$H$103-$G$74:$G$103+1)) -> 0 | G35: =SUMPRODUCT(($D$74:$D$103=$A35)*$F$74:$F$103*(((($H$74:$H$103<EOMONTH(G$32,0))*$H$74:$H$103+($H$74:$H$103>=EOMONTH(G$32,0))*EOMONTH(G$32,0))-(($G$74:$G$103>G$32)*$G$74:$G$103+($G$74:$G$103<=G$32)*G$32)+1)>0)*((($H$74:$H$103<EOMONTH(G$32,0))*$H$74:$H$103+($H$74:$H$103>=EOMONTH(G$32,0))*EOMONTH(G$32,0))-(($G$74:$G$103>G$32)*$G$74:$G$103+($G$74:$G$103<=G$32)*G$32)+1)/($H$74:$H$103-$G$74:$G$103+1)) -> 0 | H35: =SUMPRODUCT(($D$74:$D$103=$A35)*$F$74:$F$103*(((($H$74:$H$103<EOMONTH(H$32,0))*$H$74:$H$103+($H$74:$H$103>=EOMONTH(H$32,0))*EOMONTH(H$32,0))-(($G$74:$G$103>H$32)*$G$74:$G$103+($G$74:$G$103<=H$32)*H$32)+1)>0)*((($H$74:$H$103<EOMONTH(H$32,0))*$H$74:$H$103+($H$74:$H$103>=EOMONTH(H$32,0))*EOMONTH(H$32,0))-(($G$74:$G$103>H$32)*$G$74:$G$103+($G$74:$G$103<=H$32)*H$32)+1)/($H$74:$H$103-$G$74:$G$103+1)) -> 0 | I35: =SUMPRODUCT(($D$74:$D$103=$A35)*$F$74:$F$103*(((($H$74:$H$103<EOMONTH(I$32,0))*$H$74:$H$103+($H$74:$H$103>=EOMONTH(I$32,0))*EOMONTH(I$32,0))-(($G$74:$G$103>I$32)*$G$74:$G$103+($G$74:$G$103<=I$32)*I$32)+1)>0)*((($H$74:$H$103<EOMONTH(I$32,0))*$H$74:$H$103+($H$74:$H$103>=EOMONTH(I$32,0))*EOMONTH(I$32,0))-(($G$74:$G$103>I$32)*$G$74:$G$103+($G$74:$G$103<=I$32)*I$32)+1)/($H$74:$H$103-$G$74:$G$103+1)) -> 0 | J35: =SUMPRODUCT(($D$74:$D$103=$A35)*$F$74:$F$103*(((($H$74:$H$103<EOMONTH(J$32,0))*$H$74:$H$103+($H$74:$H$103>=EOMONTH(J$32,0))*EOMONTH(J$32,0))-(($G$74:$G$103>J$32)*$G$74:$G$103+($G$74:$G$103<=J$32)*J$32)+1)>0)*((($H$74:$H$103<EOMONTH(J$32,0))*$H$74:$H$103+($H$74:$H$103>=EOMONTH(J$32,0))*EOMONTH(J$32,0))-(($G$74:$G$103>J$32)*$G$74:$G$103+($G$74:$G$103<=J$32)*J$32)+1)/($H$74:$H$103-$G$74:$G$103+1)) -> 0 | K35: =SUMPRODUCT(($D$74:$D$103=$A35)*$F$74:$F$103*(((($H$74:$H$103<EOMONTH(K$32,0))*$H$74:$H$103+($H$74:$H$103>=EOMONTH(K$32,0))*EOMONTH(K$32,0))-(($G$74:$G$103>K$32)*$G$74:$G$103+($G$74:$G$103<=K$32)*K$32)+1)>0)*((($H$74:$H$103<EOMONTH(K$32,0))*$H$74:$H$103+($H$74:$H$103>=EOMONTH(K$32,0))*EOMONTH(K$32,0))-(($G$74:$G$103>K$32)*$G$74:$G$103+($G$74:$G$103<=K$32)*K$32)+1)/($H$74:$H$103-$G$74:$G$103+1)) -> 0 | ... O35: =SUMPRODUCT(($D$74:$D$103=$A35)*$F$74:$F$103*(((($H$74:$H$103<EOMONTH(O$32,0))*$H$74:$H$103+($H$74:$H$103>=EOMONTH(O$32,0))*EOMONTH(O$32,0))-(($G$74:$G$103>O$32)*$G$74:$G$103+($G$74:$G$103<=O$32)*O$32)+1)>0)*((($H$74:$H$103<EOMONTH(O$32,0))*$H$74:$H$103+($H$74:$H$103>=EOMONTH(O$32,0))*EOMONTH(O$32,0))-(($G$74:$G$103>O$32)*$G$74:$G$103+($G$74:$G$103<=O$32)*O$32)+1)/($H$74:$H$103-$G$74:$G$103+1)) -> 0 | P35: =SUM(D35:O35) -> 131545.55
A36: 342-04 | B36: 342 | C36: INTERLIGAÇÕES ETA × UTR | D36: =SUMPRODUCT(($D$74:$D$103=$A36)*$F$74:$F$103*(((($H$74:$H$103<EOMONTH(D$32,0))*$H$74:$H$103+($H$74:$H$103>=EOMONTH(D$32,0))*EOMONTH(D$32,0))-(($G$74:$G$103>D$32)*$G$74:$G$103+($G$74:$G$103<=D$32)*D$32)+1)>0)*((($H$74:$H$103<EOMONTH(D$32,0))*$H$74:$H$103+($H$74:$H$103>=EOMONTH(D$32,0))*EOMONTH(D$32,0))-(($G$74:$G$103>D$32)*$G$74:$G$103+($G$74:$G$103<=D$32)*D$32)+1)/($H$74:$H$103-$G$74:$G$103+1)) -> 0 | E36: =SUMPRODUCT(($D$74:$D$103=$A36)*$F$74:$F$103*(((($H$74:$H$103<EOMONTH(E$32,0))*$H$74:$H$103+($H$74:$H$103>=EOMONTH(E$32,0))*EOMONTH(E$32,0))-(($G$74:$G$103>E$32)*$G$74:$G$103+($G$74:$G$103<=E$32)*E$32)+1)>0)*((($H$74:$H$103<EOMONTH(E$32,0))*$H$74:$H$103+($H$74:$H$103>=EOMONTH(E$32,0))*EOMONTH(E$32,0))-(($G$74:$G$103>E$32)*$G$74:$G$103+($G$74:$G$103<=E$32)*E$32)+1)/($H$74:$H$103-$G$74:$G$103+1)) -> 0 | F36: =SUMPRODUCT(($D$74:$D$103=$A36)*$F$74:$F$103*(((($H$74:$H$103<EOMONTH(F$32,0))*$H$74:$H$103+($H$74:$H$103>=EOMONTH(F$32,0))*EOMONTH(F$32,0))-(($G$74:$G$103>F$32)*$G$74:$G$103+($G$74:$G$103<=F$32)*F$32)+1)>0)*((($H$74:$H$103<EOMONTH(F$32,0))*$H$74:$H$103+($H$74:$H$103>=EOMONTH(F$32,0))*EOMONTH(F$32,0))-(($G$74:$G$103>F$32)*$G$74:$G$103+($G$74:$G$103<=F$32)*F$32)+1)/($H$74:$H$103-$G$74:$G$103+1)) -> 0 | G36: =SUMPRODUCT(($D$74:$D$103=$A36)*$F$74:$F$103*(((($H$74:$H$103<EOMONTH(G$32,0))*$H$74:$H$103+($H$74:$H$103>=EOMONTH(G$32,0))*EOMONTH(G$32,0))-(($G$74:$G$103>G$32)*$G$74:$G$103+($G$74:$G$103<=G$32)*G$32)+1)>0)*((($H$74:$H$103<EOMONTH(G$32,0))*$H$74:$H$103+($H$74:$H$103>=EOMONTH(G$32,0))*EOMONTH(G$32,0))-(($G$74:$G$103>G$32)*$G$74:$G$103+($G$74:$G$103<=G$32)*G$32)+1)/($H$74:$H$103-$G$74:$G$103+1)) -> 334559.95 | H36: =SUMPRODUCT(($D$74:$D$103=$A36)*$F$74:$F$103*(((($H$74:$H$103<EOMONTH(H$32,0))*$H$74:$H$103+($H$74:$H$103>=EOMONTH(H$32,0))*EOMONTH(H$32,0))-(($G$74:$G$103>H$32)*$G$74:$G$103+($G$74:$G$103<=H$32)*H$32)+1)>0)*((($H$74:$H$103<EOMONTH(H$32,0))*$H$74:$H$103+($H$74:$H$103>=EOMONTH(H$32,0))*EOMONTH(H$32,0))-(($G$74:$G$103>H$32)*$G$74:$G$103+($G$74:$G$103<=H$32)*H$32)+1)/($H$74:$H$103-$G$74:$G$103+1)) -> 0 | I36: =SUMPRODUCT(($D$74:$D$103=$A36)*$F$74:$F$103*(((($H$74:$H$103<EOMONTH(I$32,0))*$H$74:$H$103+($H$74:$H$103>=EOMONTH(I$32,0))*EOMONTH(I$32,0))-(($G$74:$G$103>I$32)*$G$74:$G$103+($G$74:$G$103<=I$32)*I$32)+1)>0)*((($H$74:$H$103<EOMONTH(I$32,0))*$H$74:$H$103+($H$74:$H$103>=EOMONTH(I$32,0))*EOMONTH(I$32,0))-(($G$74:$G$103>I$32)*$G$74:$G$103+($G$74:$G$103<=I$32)*I$32)+1)/($H$74:$H$103-$G$74:$G$103+1)) -> 0 | J36: =SUMPRODUCT(($D$74:$D$103=$A36)*$F$74:$F$103*(((($H$74:$H$103<EOMONTH(J$32,0))*$H$74:$H$103+($H$74:$H$103>=EOMONTH(J$32,0))*EOMONTH(J$32,0))-(($G$74:$G$103>J$32)*$G$74:$G$103+($G$74:$G$103<=J$32)*J$32)+1)>0)*((($H$74:$H$103<EOMONTH(J$32,0))*$H$74:$H$103+($H$74:$H$103>=EOMONTH(J$32,0))*EOMONTH(J$32,0))-(($G$74:$G$103>J$32)*$G$74:$G$103+($G$74:$G$103<=J$32)*J$32)+1)/($H$74:$H$103-$G$74:$G$103+1)) -> 0 | K36: =SUMPRODUCT(($D$74:$D$103=$A36)*$F$74:$F$103*(((($H$74:$H$103<EOMONTH(K$32,0))*$H$74:$H$103+($H$74:$H$103>=EOMONTH(K$32,0))*EOMONTH(K$32,0))-(($G$74:$G$103>K$32)*$G$74:$G$103+($G$74:$G$103<=K$32)*K$32)+1)>0)*((($H$74:$H$103<EOMONTH(K$32,0))*$H$74:$H$103+($H$74:$H$103>=EOMONTH(K$32,0))*EOMONTH(K$32,0))-(($G$74:$G$103>K$32)*$G$74:$G$103+($G$74:$G$103<=K$32)*K$32)+1)/($H$74:$H$103-$G$74:$G$103+1)) -> 0 | ... O36: =SUMPRODUCT(($D$74:$D$103=$A36)*$F$74:$F$103*(((($H$74:$H$103<EOMONTH(O$32,0))*$H$74:$H$103+($H$74:$H$103>=EOMONTH(O$32,0))*EOMONTH(O$32,0))-(($G$74:$G$103>O$32)*$G$74:$G$103+($G$74:$G$103<=O$32)*O$32)+1)>0)*((($H$74:$H$103<EOMONTH(O$32,0))*$H$74:$H$103+($H$74:$H$103>=EOMONTH(O$32,0))*EOMONTH(O$32,0))-(($G$74:$G$103>O$32)*$G$74:$G$103+($G$74:$G$103<=O$32)*O$32)+1)/($H$74:$H$103-$G$74:$G$103+1)) -> 0 | P36: =SUM(D36:O36) -> 334559.95
A37: 342-05 | B37: 342 | C37: INTERLIGAÇÕES LINHA DE RECALQUE UTR × ETA | D37: =SUMPRODUCT(($D$74:$D$103=$A37)*$F$74:$F$103*(((($H$74:$H$103<EOMONTH(D$32,0))*$H$74:$H$103+($H$74:$H$103>=EOMONTH(D$32,0))*EOMONTH(D$32,0))-(($G$74:$G$103>D$32)*$G$74:$G$103+($G$74:$G$103<=D$32)*D$32)+1)>0)*((($H$74:$H$103<EOMONTH(D$32,0))*$H$74:$H$103+($H$74:$H$103>=EOMONTH(D$32,0))*EOMONTH(D$32,0))-(($G$74:$G$103>D$32)*$G$74:$G$103+($G$74:$G$103<=D$32)*D$32)+1)/($H$74:$H$103-$G$74:$G$103+1)) -> 0 | E37: =SUMPRODUCT(($D$74:$D$103=$A37)*$F$74:$F$103*(((($H$74:$H$103<EOMONTH(E$32,0))*$H$74:$H$103+($H$74:$H$103>=EOMONTH(E$32,0))*EOMONTH(E$32,0))-(($G$74:$G$103>E$32)*$G$74:$G$103+($G$74:$G$103<=E$32)*E$32)+1)>0)*((($H$74:$H$103<EOMONTH(E$32,0))*$H$74:$H$103+($H$74:$H$103>=EOMONTH(E$32,0))*EOMONTH(E$32,0))-(($G$74:$G$103>E$32)*$G$74:$G$103+($G$74:$G$103<=E$32)*E$32)+1)/($H$74:$H$103-$G$74:$G$103+1)) -> 0 | F37: =SUMPRODUCT(($D$74:$D$103=$A37)*$F$74:$F$103*(((($H$74:$H$103<EOMONTH(F$32,0))*$H$74:$H$103+($H$74:$H$103>=EOMONTH(F$32,0))*EOMONTH(F$32,0))-(($G$74:$G$103>F$32)*$G$74:$G$103+($G$74:$G$103<=F$32)*F$32)+1)>0)*((($H$74:$H$103<EOMONTH(F$32,0))*$H$74:$H$103+($H$74:$H$103>=EOMONTH(F$32,0))*EOMONTH(F$32,0))-(($G$74:$G$103>F$32)*$G$74:$G$103+($G$74:$G$103<=F$32)*F$32)+1)/($H$74:$H$103-$G$74:$G$103+1)) -> 0 | G37: =SUMPRODUCT(($D$74:$D$103=$A37)*$F$74:$F$103*(((($H$74:$H$103<EOMONTH(G$32,0))*$H$74:$H$103+($H$74:$H$103>=EOMONTH(G$32,0))*EOMONTH(G$32,0))-(($G$74:$G$103>G$32)*$G$74:$G$103+($G$74:$G$103<=G$32)*G$32)+1)>0)*((($H$74:$H$103<EOMONTH(G$32,0))*$H$74:$H$103+($H$74:$H$103>=EOMONTH(G$32,0))*EOMONTH(G$32,0))-(($G$74:$G$103>G$32)*$G$74:$G$103+($G$74:$G$103<=G$32)*G$32)+1)/($H$74:$H$103-$G$74:$G$103+1)) -> 54857.68 | H37: =SUMPRODUCT(($D$74:$D$103=$A37)*$F$74:$F$103*(((($H$74:$H$103<EOMONTH(H$32,0))*$H$74:$H$103+($H$74:$H$103>=EOMONTH(H$32,0))*EOMONTH(H$32,0))-(($G$74:$G$103>H$32)*$G$74:$G$103+($G$74:$G$103<=H$32)*H$32)+1)>0)*((($H$74:$H$103<EOMONTH(H$32,0))*$H$74:$H$103+($H$74:$H$103>=EOMONTH(H$32,0))*EOMONTH(H$32,0))-(($G$74:$G$103>H$32)*$G$74:$G$103+($G$74:$G$103<=H$32)*H$32)+1)/($H$74:$H$103-$G$74:$G$103+1)) -> 0 | I37: =SUMPRODUCT(($D$74:$D$103=$A37)*$F$74:$F$103*(((($H$74:$H$103<EOMONTH(I$32,0))*$H$74:$H$103+($H$74:$H$103>=EOMONTH(I$32,0))*EOMONTH(I$32,0))-(($G$74:$G$103>I$32)*$G$74:$G$103+($G$74:$G$103<=I$32)*I$32)+1)>0)*((($H$74:$H$103<EOMONTH(I$32,0))*$H$74:$H$103+($H$74:$H$103>=EOMONTH(I$32,0))*EOMONTH(I$32,0))-(($G$74:$G$103>I$32)*$G$74:$G$103+($G$74:$G$103<=I$32)*I$32)+1)/($H$74:$H$103-$G$74:$G$103+1)) -> 0 | J37: =SUMPRODUCT(($D$74:$D$103=$A37)*$F$74:$F$103*(((($H$74:$H$103<EOMONTH(J$32,0))*$H$74:$H$103+($H$74:$H$103>=EOMONTH(J$32,0))*EOMONTH(J$32,0))-(($G$74:$G$103>J$32)*$G$74:$G$103+($G$74:$G$103<=J$32)*J$32)+1)>0)*((($H$74:$H$103<EOMONTH(J$32,0))*$H$74:$H$103+($H$74:$H$103>=EOMONTH(J$32,0))*EOMONTH(J$32,0))-(($G$74:$G$103>J$32)*$G$74:$G$103+($G$74:$G$103<=J$32)*J$32)+1)/($H$74:$H$103-$G$74:$G$103+1)) -> 0 | K37: =SUMPRODUCT(($D$74:$D$103=$A37)*$F$74:$F$103*(((($H$74:$H$103<EOMONTH(K$32,0))*$H$74:$H$103+($H$74:$H$103>=EOMONTH(K$32,0))*EOMONTH(K$32,0))-(($G$74:$G$103>K$32)*$G$74:$G$103+($G$74:$G$103<=K$32)*K$32)+1)>0)*((($H$74:$H$103<EOMONTH(K$32,0))*$H$74:$H$103+($H$74:$H$103>=EOMONTH(K$32,0))*EOMONTH(K$32,0))-(($G$74:$G$103>K$32)*$G$74:$G$103+($G$74:$G$103<=K$32)*K$32)+1)/($H$74:$H$103-$G$74:$G$103+1)) -> 0 | ... O37: =SUMPRODUCT(($D$74:$D$103=$A37)*$F$74:$F$103*(((($H$74:$H$103<EOMONTH(O$32,0))*$H$74:$H$103+($H$74:$H$103>=EOMONTH(O$32,0))*EOMONTH(O$32,0))-(($G$74:$G$103>O$32)*$G$74:$G$103+($G$74:$G$103<=O$32)*O$32)+1)>0)*((($H$74:$H$103<EOMONTH(O$32,0))*$H$74:$H$103+($H$74:$H$103>=EOMONTH(O$32,0))*EOMONTH(O$32,0))-(($G$74:$G$103>O$32)*$G$74:$G$103+($G$74:$G$103<=O$32)*O$32)+1)/($H$74:$H$103-$G$74:$G$103+1)) -> 0 | P37: =SUM(D37:O37) -> 54857.68
A38: 342-06 | B38: 342 | C38: DRENAGENS, ESGOTAMENTO E CAIXA DE CHEGADA | D38: =SUMPRODUCT(($D$74:$D$103=$A38)*$F$74:$F$103*(((($H$74:$H$103<EOMONTH(D$32,0))*$H$74:$H$103+($H$74:$H$103>=EOMONTH(D$32,0))*EOMONTH(D$32,0))-(($G$74:$G$103>D$32)*$G$74:$G$103+($G$74:$G$103<=D$32)*D$32)+1)>0)*((($H$74:$H$103<EOMONTH(D$32,0))*$H$74:$H$103+($H$74:$H$103>=EOMONTH(D$32,0))*EOMONTH(D$32,0))-(($G$74:$G$103>D$32)*$G$74:$G$103+($G$74:$G$103<=D$32)*D$32)+1)/($H$74:$H$103-$G$74:$G$103+1)) -> 0 | E38: =SUMPRODUCT(($D$74:$D$103=$A38)*$F$74:$F$103*(((($H$74:$H$103<EOMONTH(E$32,0))*$H$74:$H$103+($H$74:$H$103>=EOMONTH(E$32,0))*EOMONTH(E$32,0))-(($G$74:$G$103>E$32)*$G$74:$G$103+($G$74:$G$103<=E$32)*E$32)+1)>0)*((($H$74:$H$103<EOMONTH(E$32,0))*$H$74:$H$103+($H$74:$H$103>=EOMONTH(E$32,0))*EOMONTH(E$32,0))-(($G$74:$G$103>E$32)*$G$74:$G$103+($G$74:$G$103<=E$32)*E$32)+1)/($H$74:$H$103-$G$74:$G$103+1)) -> 0 | F38: =SUMPRODUCT(($D$74:$D$103=$A38)*$F$74:$F$103*(((($H$74:$H$103<EOMONTH(F$32,0))*$H$74:$H$103+($H$74:$H$103>=EOMONTH(F$32,0))*EOMONTH(F$32,0))-(($G$74:$G$103>F$32)*$G$74:$G$103+($G$74:$G$103<=F$32)*F$32)+1)>0)*((($H$74:$H$103<EOMONTH(F$32,0))*$H$74:$H$103+($H$74:$H$103>=EOMONTH(F$32,0))*EOMONTH(F$32,0))-(($G$74:$G$103>F$32)*$G$74:$G$103+($G$74:$G$103<=F$32)*F$32)+1)/($H$74:$H$103-$G$74:$G$103+1)) -> 32001.724 | G38: =SUMPRODUCT(($D$74:$D$103=$A38)*$F$74:$F$103*(((($H$74:$H$103<EOMONTH(G$32,0))*$H$74:$H$103+($H$74:$H$103>=EOMONTH(G$32,0))*EOMONTH(G$32,0))-(($G$74:$G$103>G$32)*$G$74:$G$103+($G$74:$G$103<=G$32)*G$32)+1)>0)*((($H$74:$H$103<EOMONTH(G$32,0))*$H$74:$H$103+($H$74:$H$103>=EOMONTH(G$32,0))*EOMONTH(G$32,0))-(($G$74:$G$103>G$32)*$G$74:$G$103+($G$74:$G$103<=G$32)*G$32)+1)/($H$74:$H$103-$G$74:$G$103+1)) -> 40002.156 | H38: =SUMPRODUCT(($D$74:$D$103=$A38)*$F$74:$F$103*(((($H$74:$H$103<EOMONTH(H$32,0))*$H$74:$H$103+($H$74:$H$103>=EOMONTH(H$32,0))*EOMONTH(H$32,0))-(($G$74:$G$103>H$32)*$G$74:$G$103+($G$74:$G$103<=H$32)*H$32)+1)>0)*((($H$74:$H$103<EOMONTH(H$32,0))*$H$74:$H$103+($H$74:$H$103>=EOMONTH(H$32,0))*EOMONTH(H$32,0))-(($G$74:$G$103>H$32)*$G$74:$G$103+($G$74:$G$103<=H$32)*H$32)+1)/($H$74:$H$103-$G$74:$G$103+1)) -> 0 | I38: =SUMPRODUCT(($D$74:$D$103=$A38)*$F$74:$F$103*(((($H$74:$H$103<EOMONTH(I$32,0))*$H$74:$H$103+($H$74:$H$103>=EOMONTH(I$32,0))*EOMONTH(I$32,0))-(($G$74:$G$103>I$32)*$G$74:$G$103+($G$74:$G$103<=I$32)*I$32)+1)>0)*((($H$74:$H$103<EOMONTH(I$32,0))*$H$74:$H$103+($H$74:$H$103>=EOMONTH(I$32,0))*EOMONTH(I$32,0))-(($G$74:$G$103>I$32)*$G$74:$G$103+($G$74:$G$103<=I$32)*I$32)+1)/($H$74:$H$103-$G$74:$G$103+1)) -> 0 | J38: =SUMPRODUCT(($D$74:$D$103=$A38)*$F$74:$F$103*(((($H$74:$H$103<EOMONTH(J$32,0))*$H$74:$H$103+($H$74:$H$103>=EOMONTH(J$32,0))*EOMONTH(J$32,0))-(($G$74:$G$103>J$32)*$G$74:$G$103+($G$74:$G$103<=J$32)*J$32)+1)>0)*((($H$74:$H$103<EOMONTH(J$32,0))*$H$74:$H$103+($H$74:$H$103>=EOMONTH(J$32,0))*EOMONTH(J$32,0))-(($G$74:$G$103>J$32)*$G$74:$G$103+($G$74:$G$103<=J$32)*J$32)+1)/($H$74:$H$103-$G$74:$G$103+1)) -> 0 | K38: =SUMPRODUCT(($D$74:$D$103=$A38)*$F$74:$F$103*(((($H$74:$H$103<EOMONTH(K$32,0))*$H$74:$H$103+($H$74:$H$103>=EOMONTH(K$32,0))*EOMONTH(K$32,0))-(($G$74:$G$103>K$32)*$G$74:$G$103+($G$74:$G$103<=K$32)*K$32)+1)>0)*((($H$74:$H$103<EOMONTH(K$32,0))*$H$74:$H$103+($H$74:$H$103>=EOMONTH(K$32,0))*EOMONTH(K$32,0))-(($G$74:$G$103>K$32)*$G$74:$G$103+($G$74:$G$103<=K$32)*K$32)+1)/($H$74:$H$103-$G$74:$G$103+1)) -> 0 | ... O38: =SUMPRODUCT(($D$74:$D$103=$A38)*$F$74:$F$103*(((($H$74:$H$103<EOMONTH(O$32,0))*$H$74:$H$103+($H$74:$H$103>=EOMONTH(O$32,0))*EOMONTH(O$32,0))-(($G$74:$G$103>O$32)*$G$74:$G$103+($G$74:$G$103<=O$32)*O$32)+1)>0)*((($H$74:$H$103<EOMONTH(O$32,0))*$H$74:$H$103+($H$74:$H$103>=EOMONTH(O$32,0))*EOMONTH(O$32,0))-(($G$74:$G$103>O$32)*$G$74:$G$103+($G$74:$G$103<=O$32)*O$32)+1)/($H$74:$H$103-$G$74:$G$103+1)) -> 0 | P38: =SUM(D38:O38) -> 72003.88
A39: 342-07 | B39: 342 | C39: TANQUE DE LODO | D39: =SUMPRODUCT(($D$74:$D$103=$A39)*$F$74:$F$103*(((($H$74:$H$103<EOMONTH(D$32,0))*$H$74:$H$103+($H$74:$H$103>=EOMONTH(D$32,0))*EOMONTH(D$32,0))-(($G$74:$G$103>D$32)*$G$74:$G$103+($G$74:$G$103<=D$32)*D$32)+1)>0)*((($H$74:$H$103<EOMONTH(D$32,0))*$H$74:$H$103+($H$74:$H$103>=EOMONTH(D$32,0))*EOMONTH(D$32,0))-(($G$74:$G$103>D$32)*$G$74:$G$103+($G$74:$G$103<=D$32)*D$32)+1)/($H$74:$H$103-$G$74:$G$103+1)) -> 0 | E39: =SUMPRODUCT(($D$74:$D$103=$A39)*$F$74:$F$103*(((($H$74:$H$103<EOMONTH(E$32,0))*$H$74:$H$103+($H$74:$H$103>=EOMONTH(E$32,0))*EOMONTH(E$32,0))-(($G$74:$G$103>E$32)*$G$74:$G$103+($G$74:$G$103<=E$32)*E$32)+1)>0)*((($H$74:$H$103<EOMONTH(E$32,0))*$H$74:$H$103+($H$74:$H$103>=EOMONTH(E$32,0))*EOMONTH(E$32,0))-(($G$74:$G$103>E$32)*$G$74:$G$103+($G$74:$G$103<=E$32)*E$32)+1)/($H$74:$H$103-$G$74:$G$103+1)) -> 0 | F39: =SUMPRODUCT(($D$74:$D$103=$A39)*$F$74:$F$103*(((($H$74:$H$103<EOMONTH(F$32,0))*$H$74:$H$103+($H$74:$H$103>=EOMONTH(F$32,0))*EOMONTH(F$32,0))-(($G$74:$G$103>F$32)*$G$74:$G$103+($G$74:$G$103<=F$32)*F$32)+1)>0)*((($H$74:$H$103<EOMONTH(F$32,0))*$H$74:$H$103+($H$74:$H$103>=EOMONTH(F$32,0))*EOMONTH(F$32,0))-(($G$74:$G$103>F$32)*$G$74:$G$103+($G$74:$G$103<=F$32)*F$32)+1)/($H$74:$H$103-$G$74:$G$103+1)) -> 20399.37 | G39: =SUMPRODUCT(($D$74:$D$103=$A39)*$F$74:$F$103*(((($H$74:$H$103<EOMONTH(G$32,0))*$H$74:$H$103+($H$74:$H$103>=EOMONTH(G$32,0))*EOMONTH(G$32,0))-(($G$74:$G$103>G$32)*$G$74:$G$103+($G$74:$G$103<=G$32)*G$32)+1)>0)*((($H$74:$H$103<EOMONTH(G$32,0))*$H$74:$H$103+($H$74:$H$103>=EOMONTH(G$32,0))*EOMONTH(G$32,0))-(($G$74:$G$103>G$32)*$G$74:$G$103+($G$74:$G$103<=G$32)*G$32)+1)/($H$74:$H$103-$G$74:$G$103+1)) -> 234077.11 | H39: =SUMPRODUCT(($D$74:$D$103=$A39)*$F$74:$F$103*(((($H$74:$H$103<EOMONTH(H$32,0))*$H$74:$H$103+($H$74:$H$103>=EOMONTH(H$32,0))*EOMONTH(H$32,0))-(($G$74:$G$103>H$32)*$G$74:$G$103+($G$74:$G$103<=H$32)*H$32)+1)>0)*((($H$74:$H$103<EOMONTH(H$32,0))*$H$74:$H$103+($H$74:$H$103>=EOMONTH(H$32,0))*EOMONTH(H$32,0))-(($G$74:$G$103>H$32)*$G$74:$G$103+($G$74:$G$103<=H$32)*H$32)+1)/($H$74:$H$103-$G$74:$G$103+1)) -> 148248.84 | I39: =SUMPRODUCT(($D$74:$D$103=$A39)*$F$74:$F$103*(((($H$74:$H$103<EOMONTH(I$32,0))*$H$74:$H$103+($H$74:$H$103>=EOMONTH(I$32,0))*EOMONTH(I$32,0))-(($G$74:$G$103>I$32)*$G$74:$G$103+($G$74:$G$103<=I$32)*I$32)+1)>0)*((($H$74:$H$103<EOMONTH(I$32,0))*$H$74:$H$103+($H$74:$H$103>=EOMONTH(I$32,0))*EOMONTH(I$32,0))-(($G$74:$G$103>I$32)*$G$74:$G$103+($G$74:$G$103<=I$32)*I$32)+1)/($H$74:$H$103-$G$74:$G$103+1)) -> 0 | J39: =SUMPRODUCT(($D$74:$D$103=$A39)*$F$74:$F$103*(((($H$74:$H$103<EOMONTH(J$32,0))*$H$74:$H$103+($H$74:$H$103>=EOMONTH(J$32,0))*EOMONTH(J$32,0))-(($G$74:$G$103>J$32)*$G$74:$G$103+($G$74:$G$103<=J$32)*J$32)+1)>0)*((($H$74:$H$103<EOMONTH(J$32,0))*$H$74:$H$103+($H$74:$H$103>=EOMONTH(J$32,0))*EOMONTH(J$32,0))-(($G$74:$G$103>J$32)*$G$74:$G$103+($G$74:$G$103<=J$32)*J$32)+1)/($H$74:$H$103-$G$74:$G$103+1)) -> 67644.598 | K39: =SUMPRODUCT(($D$74:$D$103=$A39)*$F$74:$F$103*(((($H$74:$H$103<EOMONTH(K$32,0))*$H$74:$H$103+($H$74:$H$103>=EOMONTH(K$32,0))*EOMONTH(K$32,0))-(($G$74:$G$103>K$32)*$G$74:$G$103+($G$74:$G$103<=K$32)*K$32)+1)>0)*((($H$74:$H$103<EOMONTH(K$32,0))*$H$74:$H$103+($H$74:$H$103>=EOMONTH(K$32,0))*EOMONTH(K$32,0))-(($G$74:$G$103>K$32)*$G$74:$G$103+($G$74:$G$103<=K$32)*K$32)+1)/($H$74:$H$103-$G$74:$G$103+1)) -> 652699.59 | ... O39: =SUMPRODUCT(($D$74:$D$103=$A39)*$F$74:$F$103*(((($H$74:$H$103<EOMONTH(O$32,0))*$H$74:$H$103+($H$74:$H$103>=EOMONTH(O$32,0))*EOMONTH(O$32,0))-(($G$74:$G$103>O$32)*$G$74:$G$103+($G$74:$G$103<=O$32)*O$32)+1)>0)*((($H$74:$H$103<EOMONTH(O$32,0))*$H$74:$H$103+($H$74:$H$103>=EOMONTH(O$32,0))*EOMONTH(O$32,0))-(($G$74:$G$103>O$32)*$G$74:$G$103+($G$74:$G$103<=O$32)*O$32)+1)/($H$74:$H$103-$G$74:$G$103+1)) -> 0 | P39: =SUM(D39:O39) -> 1180517.8
A40: 342-08 | B40: 342 | C40: ESTAÇÃO ELEVATÓRIA DE RECIRCULAÇÃO DE LODO | D40: =SUMPRODUCT(($D$74:$D$103=$A40)*$F$74:$F$103*(((($H$74:$H$103<EOMONTH(D$32,0))*$H$74:$H$103+($H$74:$H$103>=EOMONTH(D$32,0))*EOMONTH(D$32,0))-(($G$74:$G$103>D$32)*$G$74:$G$103+($G$74:$G$103<=D$32)*D$32)+1)>0)*((($H$74:$H$103<EOMONTH(D$32,0))*$H$74:$H$103+($H$74:$H$103>=EOMONTH(D$32,0))*EOMONTH(D$32,0))-(($G$74:$G$103>D$32)*$G$74:$G$103+($G$74:$G$103<=D$32)*D$32)+1)/($H$74:$H$103-$G$74:$G$103+1)) -> 0 | E40: =SUMPRODUCT(($D$74:$D$103=$A40)*$F$74:$F$103*(((($H$74:$H$103<EOMONTH(E$32,0))*$H$74:$H$103+($H$74:$H$103>=EOMONTH(E$32,0))*EOMONTH(E$32,0))-(($G$74:$G$103>E$32)*$G$74:$G$103+($G$74:$G$103<=E$32)*E$32)+1)>0)*((($H$74:$H$103<EOMONTH(E$32,0))*$H$74:$H$103+($H$74:$H$103>=EOMONTH(E$32,0))*EOMONTH(E$32,0))-(($G$74:$G$103>E$32)*$G$74:$G$103+($G$74:$G$103<=E$32)*E$32)+1)/($H$74:$H$103-$G$74:$G$103+1)) -> 0 | F40: =SUMPRODUCT(($D$74:$D$103=$A40)*$F$74:$F$103*(((($H$74:$H$103<EOMONTH(F$32,0))*$H$74:$H$103+($H$74:$H$103>=EOMONTH(F$32,0))*EOMONTH(F$32,0))-(($G$74:$G$103>F$32)*$G$74:$G$103+($G$74:$G$103<=F$32)*F$32)+1)>0)*((($H$74:$H$103<EOMONTH(F$32,0))*$H$74:$H$103+($H$74:$H$103>=EOMONTH(F$32,0))*EOMONTH(F$32,0))-(($G$74:$G$103>F$32)*$G$74:$G$103+($G$74:$G$103<=F$32)*F$32)+1)/($H$74:$H$103-$G$74:$G$103+1)) -> 0 | G40: =SUMPRODUCT(($D$74:$D$103=$A40)*$F$74:$F$103*(((($H$74:$H$103<EOMONTH(G$32,0))*$H$74:$H$103+($H$74:$H$103>=EOMONTH(G$32,0))*EOMONTH(G$32,0))-(($G$74:$G$103>G$32)*$G$74:$G$103+($G$74:$G$103<=G$32)*G$32)+1)>0)*((($H$74:$H$103<EOMONTH(G$32,0))*$H$74:$H$103+($H$74:$H$103>=EOMONTH(G$32,0))*EOMONTH(G$32,0))-(($G$74:$G$103>G$32)*$G$74:$G$103+($G$74:$G$103<=G$32)*G$32)+1)/($H$74:$H$103-$G$74:$G$103+1)) -> 0 | H40: =SUMPRODUCT(($D$74:$D$103=$A40)*$F$74:$F$103*(((($H$74:$H$103<EOMONTH(H$32,0))*$H$74:$H$103+($H$74:$H$103>=EOMONTH(H$32,0))*EOMONTH(H$32,0))-(($G$74:$G$103>H$32)*$G$74:$G$103+($G$74:$G$103<=H$32)*H$32)+1)>0)*((($H$74:$H$103<EOMONTH(H$32,0))*$H$74:$H$103+($H$74:$H$103>=EOMONTH(H$32,0))*EOMONTH(H$32,0))-(($G$74:$G$103>H$32)*$G$74:$G$103+($G$74:$G$103<=H$32)*H$32)+1)/($H$74:$H$103-$G$74:$G$103+1)) -> 13202.942 | I40: =SUMPRODUCT(($D$74:$D$103=$A40)*$F$74:$F$103*(((($H$74:$H$103<EOMONTH(I$32,0))*$H$74:$H$103+($H$74:$H$103>=EOMONTH(I$32,0))*EOMONTH(I$32,0))-(($G$74:$G$103>I$32)*$G$74:$G$103+($G$74:$G$103<=I$32)*I$32)+1)>0)*((($H$74:$H$103<EOMONTH(I$32,0))*$H$74:$H$103+($H$74:$H$103>=EOMONTH(I$32,0))*EOMONTH(I$32,0))-(($G$74:$G$103>I$32)*$G$74:$G$103+($G$74:$G$103<=I$32)*I$32)+1)/($H$74:$H$103-$G$74:$G$103+1)) -> 130727.93 | J40: =SUMPRODUCT(($D$74:$D$103=$A40)*$F$74:$F$103*(((($H$74:$H$103<EOMONTH(J$32,0))*$H$74:$H$103+($H$74:$H$103>=EOMONTH(J$32,0))*EOMONTH(J$32,0))-(($G$74:$G$103>J$32)*$G$74:$G$103+($G$74:$G$103<=J$32)*J$32)+1)>0)*((($H$74:$H$103<EOMONTH(J$32,0))*$H$74:$H$103+($H$74:$H$103>=EOMONTH(J$32,0))*EOMONTH(J$32,0))-(($G$74:$G$103>J$32)*$G$74:$G$103+($G$74:$G$103<=J$32)*J$32)+1)/($H$74:$H$103-$G$74:$G$103+1)) -> 18503.951 | K40: =SUMPRODUCT(($D$74:$D$103=$A40)*$F$74:$F$103*(((($H$74:$H$103<EOMONTH(K$32,0))*$H$74:$H$103+($H$74:$H$103>=EOMONTH(K$32,0))*EOMONTH(K$32,0))-(($G$74:$G$103>K$32)*$G$74:$G$103+($G$74:$G$103<=K$32)*K$32)+1)>0)*((($H$74:$H$103<EOMONTH(K$32,0))*$H$74:$H$103+($H$74:$H$103>=EOMONTH(K$32,0))*EOMONTH(K$32,0))-(($G$74:$G$103>K$32)*$G$74:$G$103+($G$74:$G$103<=K$32)*K$32)+1)/($H$74:$H$103-$G$74:$G$103+1)) -> 63755.08 | ... O40: =SUMPRODUCT(($D$74:$D$103=$A40)*$F$74:$F$103*(((($H$74:$H$103<EOMONTH(O$32,0))*$H$74:$H$103+($H$74:$H$103>=EOMONTH(O$32,0))*EOMONTH(O$32,0))-(($G$74:$G$103>O$32)*$G$74:$G$103+($G$74:$G$103<=O$32)*O$32)+1)>0)*((($H$74:$H$103<EOMONTH(O$32,0))*$H$74:$H$103+($H$74:$H$103>=EOMONTH(O$32,0))*EOMONTH(O$32,0))-(($G$74:$G$103>O$32)*$G$74:$G$103+($G$74:$G$103<=O$32)*O$32)+1)/($H$74:$H$103-$G$74:$G$103+1)) -> 0 | P40: =SUM(D40:O40) -> 530787.26
A41: 342-09 | B41: 342 | C41: URBANIZAÇÃO, CANALETAS, CAIXAS E SERVIÇOS COMPLEMENTARES | D41: =SUMPRODUCT(($D$74:$D$103=$A41)*$F$74:$F$103*(((($H$74:$H$103<EOMONTH(D$32,0))*$H$74:$H$103+($H$74:$H$103>=EOMONTH(D$32,0))*EOMONTH(D$32,0))-(($G$74:$G$103>D$32)*$G$74:$G$103+($G$74:$G$103<=D$32)*D$32)+1)>0)*((($H$74:$H$103<EOMONTH(D$32,0))*$H$74:$H$103+($H$74:$H$103>=EOMONTH(D$32,0))*EOMONTH(D$32,0))-(($G$74:$G$103>D$32)*$G$74:$G$103+($G$74:$G$103<=D$32)*D$32)+1)/($H$74:$H$103-$G$74:$G$103+1)) -> 0 | E41: =SUMPRODUCT(($D$74:$D$103=$A41)*$F$74:$F$103*(((($H$74:$H$103<EOMONTH(E$32,0))*$H$74:$H$103+($H$74:$H$103>=EOMONTH(E$32,0))*EOMONTH(E$32,0))-(($G$74:$G$103>E$32)*$G$74:$G$103+($G$74:$G$103<=E$32)*E$32)+1)>0)*((($H$74:$H$103<EOMONTH(E$32,0))*$H$74:$H$103+($H$74:$H$103>=EOMONTH(E$32,0))*EOMONTH(E$32,0))-(($G$74:$G$103>E$32)*$G$74:$G$103+($G$74:$G$103<=E$32)*E$32)+1)/($H$74:$H$103-$G$74:$G$103+1)) -> 0 | F41: =SUMPRODUCT(($D$74:$D$103=$A41)*$F$74:$F$103*(((($H$74:$H$103<EOMONTH(F$32,0))*$H$74:$H$103+($H$74:$H$103>=EOMONTH(F$32,0))*EOMONTH(F$32,0))-(($G$74:$G$103>F$32)*$G$74:$G$103+($G$74:$G$103<=F$32)*F$32)+1)>0)*((($H$74:$H$103<EOMONTH(F$32,0))*$H$74:$H$103+($H$74:$H$103>=EOMONTH(F$32,0))*EOMONTH(F$32,0))-(($G$74:$G$103>F$32)*$G$74:$G$103+($G$74:$G$103<=F$32)*F$32)+1)/($H$74:$H$103-$G$74:$G$103+1)) -> 0 | G41: =SUMPRODUCT(($D$74:$D$103=$A41)*$F$74:$F$103*(((($H$74:$H$103<EOMONTH(G$32,0))*$H$74:$H$103+($H$74:$H$103>=EOMONTH(G$32,0))*EOMONTH(G$32,0))-(($G$74:$G$103>G$32)*$G$74:$G$103+($G$74:$G$103<=G$32)*G$32)+1)>0)*((($H$74:$H$103<EOMONTH(G$32,0))*$H$74:$H$103+($H$74:$H$103>=EOMONTH(G$32,0))*EOMONTH(G$32,0))-(($G$74:$G$103>G$32)*$G$74:$G$103+($G$74:$G$103<=G$32)*G$32)+1)/($H$74:$H$103-$G$74:$G$103+1)) -> 0 | H41: =SUMPRODUCT(($D$74:$D$103=$A41)*$F$74:$F$103*(((($H$74:$H$103<EOMONTH(H$32,0))*$H$74:$H$103+($H$74:$H$103>=EOMONTH(H$32,0))*EOMONTH(H$32,0))-(($G$74:$G$103>H$32)*$G$74:$G$103+($G$74:$G$103<=H$32)*H$32)+1)>0)*((($H$74:$H$103<EOMONTH(H$32,0))*$H$74:$H$103+($H$74:$H$103>=EOMONTH(H$32,0))*EOMONTH(H$32,0))-(($G$74:$G$103>H$32)*$G$74:$G$103+($G$74:$G$103<=H$32)*H$32)+1)/($H$74:$H$103-$G$74:$G$103+1)) -> 0 | I41: =SUMPRODUCT(($D$74:$D$103=$A41)*$F$74:$F$103*(((($H$74:$H$103<EOMONTH(I$32,0))*$H$74:$H$103+($H$74:$H$103>=EOMONTH(I$32,0))*EOMONTH(I$32,0))-(($G$74:$G$103>I$32)*$G$74:$G$103+($G$74:$G$103<=I$32)*I$32)+1)>0)*((($H$74:$H$103<EOMONTH(I$32,0))*$H$74:$H$103+($H$74:$H$103>=EOMONTH(I$32,0))*EOMONTH(I$32,0))-(($G$74:$G$103>I$32)*$G$74:$G$103+($G$74:$G$103<=I$32)*I$32)+1)/($H$74:$H$103-$G$74:$G$103+1)) -> 0 | J41: =SUMPRODUCT(($D$74:$D$103=$A41)*$F$74:$F$103*(((($H$74:$H$103<EOMONTH(J$32,0))*$H$74:$H$103+($H$74:$H$103>=EOMONTH(J$32,0))*EOMONTH(J$32,0))-(($G$74:$G$103>J$32)*$G$74:$G$103+($G$74:$G$103<=J$32)*J$32)+1)>0)*((($H$74:$H$103<EOMONTH(J$32,0))*$H$74:$H$103+($H$74:$H$103>=EOMONTH(J$32,0))*EOMONTH(J$32,0))-(($G$74:$G$103>J$32)*$G$74:$G$103+($G$74:$G$103<=J$32)*J$32)+1)/($H$74:$H$103-$G$74:$G$103+1)) -> 0 | K41: =SUMPRODUCT(($D$74:$D$103=$A41)*$F$74:$F$103*(((($H$74:$H$103<EOMONTH(K$32,0))*$H$74:$H$103+($H$74:$H$103>=EOMONTH(K$32,0))*EOMONTH(K$32,0))-(($G$74:$G$103>K$32)*$G$74:$G$103+($G$74:$G$103<=K$32)*K$32)+1)>0)*((($H$74:$H$103<EOMONTH(K$32,0))*$H$74:$H$103+($H$74:$H$103>=EOMONTH(K$32,0))*EOMONTH(K$32,0))-(($G$74:$G$103>K$32)*$G$74:$G$103+($G$74:$G$103<=K$32)*K$32)+1)/($H$74:$H$103-$G$74:$G$103+1)) -> 0 | ... O41: =SUMPRODUCT(($D$74:$D$103=$A41)*$F$74:$F$103*(((($H$74:$H$103<EOMONTH(O$32,0))*$H$74:$H$103+($H$74:$H$103>=EOMONTH(O$32,0))*EOMONTH(O$32,0))-(($G$74:$G$103>O$32)*$G$74:$G$103+($G$74:$G$103<=O$32)*O$32)+1)>0)*((($H$74:$H$103<EOMONTH(O$32,0))*$H$74:$H$103+($H$74:$H$103>=EOMONTH(O$32,0))*EOMONTH(O$32,0))-(($G$74:$G$103>O$32)*$G$74:$G$103+($G$74:$G$103<=O$32)*O$32)+1)/($H$74:$H$103-$G$74:$G$103+1)) -> 0 | P41: =SUM(D41:O41) -> 218637.74
A42: 342-10 | B42: 342 | C42: REDE DE DISTRIBUIÇÃO DE ENERGIA | D42: =SUMPRODUCT(($D$74:$D$103=$A42)*$F$74:$F$103*(((($H$74:$H$103<EOMONTH(D$32,0))*$H$74:$H$103+($H$74:$H$103>=EOMONTH(D$32,0))*EOMONTH(D$32,0))-(($G$74:$G$103>D$32)*$G$74:$G$103+($G$74:$G$103<=D$32)*D$32)+1)>0)*((($H$74:$H$103<EOMONTH(D$32,0))*$H$74:$H$103+($H$74:$H$103>=EOMONTH(D$32,0))*EOMONTH(D$32,0))-(($G$74:$G$103>D$32)*$G$74:$G$103+($G$74:$G$103<=D$32)*D$32)+1)/($H$74:$H$103-$G$74:$G$103+1)) -> 0 | E42: =SUMPRODUCT(($D$74:$D$103=$A42)*$F$74:$F$103*(((($H$74:$H$103<EOMONTH(E$32,0))*$H$74:$H$103+($H$74:$H$103>=EOMONTH(E$32,0))*EOMONTH(E$32,0))-(($G$74:$G$103>E$32)*$G$74:$G$103+($G$74:$G$103<=E$32)*E$32)+1)>0)*((($H$74:$H$103<EOMONTH(E$32,0))*$H$74:$H$103+($H$74:$H$103>=EOMONTH(E$32,0))*EOMONTH(E$32,0))-(($G$74:$G$103>E$32)*$G$74:$G$103+($G$74:$G$103<=E$32)*E$32)+1)/($H$74:$H$103-$G$74:$G$103+1)) -> 0 | F42: =SUMPRODUCT(($D$74:$D$103=$A42)*$F$74:$F$103*(((($H$74:$H$103<EOMONTH(F$32,0))*$H$74:$H$103+($H$74:$H$103>=EOMONTH(F$32,0))*EOMONTH(F$32,0))-(($G$74:$G$103>F$32)*$G$74:$G$103+($G$74:$G$103<=F$32)*F$32)+1)>0)*((($H$74:$H$103<EOMONTH(F$32,0))*$H$74:$H$103+($H$74:$H$103>=EOMONTH(F$32,0))*EOMONTH(F$32,0))-(($G$74:$G$103>F$32)*$G$74:$G$103+($G$74:$G$103<=F$32)*F$32)+1)/($H$74:$H$103-$G$74:$G$103+1)) -> 0 | G42: =SUMPRODUCT(($D$74:$D$103=$A42)*$F$74:$F$103*(((($H$74:$H$103<EOMONTH(G$32,0))*$H$74:$H$103+($H$74:$H$103>=EOMONTH(G$32,0))*EOMONTH(G$32,0))-(($G$74:$G$103>G$32)*$G$74:$G$103+($G$74:$G$103<=G$32)*G$32)+1)>0)*((($H$74:$H$103<EOMONTH(G$32,0))*$H$74:$H$103+($H$74:$H$103>=EOMONTH(G$32,0))*EOMONTH(G$32,0))-(($G$74:$G$103>G$32)*$G$74:$G$103+($G$74:$G$103<=G$32)*G$32)+1)/($H$74:$H$103-$G$74:$G$103+1)) -> 0 | H42: =SUMPRODUCT(($D$74:$D$103=$A42)*$F$74:$F$103*(((($H$74:$H$103<EOMONTH(H$32,0))*$H$74:$H$103+($H$74:$H$103>=EOMONTH(H$32,0))*EOMONTH(H$32,0))-(($G$74:$G$103>H$32)*$G$74:$G$103+($G$74:$G$103<=H$32)*H$32)+1)>0)*((($H$74:$H$103<EOMONTH(H$32,0))*$H$74:$H$103+($H$74:$H$103>=EOMONTH(H$32,0))*EOMONTH(H$32,0))-(($G$74:$G$103>H$32)*$G$74:$G$103+($G$74:$G$103<=H$32)*H$32)+1)/($H$74:$H$103-$G$74:$G$103+1)) -> 0 | I42: =SUMPRODUCT(($D$74:$D$103=$A42)*$F$74:$F$103*(((($H$74:$H$103<EOMONTH(I$32,0))*$H$74:$H$103+($H$74:$H$103>=EOMONTH(I$32,0))*EOMONTH(I$32,0))-(($G$74:$G$103>I$32)*$G$74:$G$103+($G$74:$G$103<=I$32)*I$32)+1)>0)*((($H$74:$H$103<EOMONTH(I$32,0))*$H$74:$H$103+($H$74:$H$103>=EOMONTH(I$32,0))*EOMONTH(I$32,0))-(($G$74:$G$103>I$32)*$G$74:$G$103+($G$74:$G$103<=I$32)*I$32)+1)/($H$74:$H$103-$G$74:$G$103+1)) -> 86305.24 | J42: =SUMPRODUCT(($D$74:$D$103=$A42)*$F$74:$F$103*(((($H$74:$H$103<EOMONTH(J$32,0))*$H$74:$H$103+($H$74:$H$103>=EOMONTH(J$32,0))*EOMONTH(J$32,0))-(($G$74:$G$103>J$32)*$G$74:$G$103+($G$74:$G$103<=J$32)*J$32)+1)>0)*((($H$74:$H$103<EOMONTH(J$32,0))*$H$74:$H$103+($H$74:$H$103>=EOMONTH(J$32,0))*EOMONTH(J$32,0))-(($G$74:$G$103>J$32)*$G$74:$G$103+($G$74:$G$103<=J$32)*J$32)+1)/($H$74:$H$103-$G$74:$G$103+1)) -> 18493.98 | K42: =SUMPRODUCT(($D$74:$D$103=$A42)*$F$74:$F$103*(((($H$74:$H$103<EOMONTH(K$32,0))*$H$74:$H$103+($H$74:$H$103>=EOMONTH(K$32,0))*EOMONTH(K$32,0))-(($G$74:$G$103>K$32)*$G$74:$G$103+($G$74:$G$103<=K$32)*K$32)+1)>0)*((($H$74:$H$103<EOMONTH(K$32,0))*$H$74:$H$103+($H$74:$H$103>=EOMONTH(K$32,0))*EOMONTH(K$32,0))-(($G$74:$G$103>K$32)*$G$74:$G$103+($G$74:$G$103<=K$32)*K$32)+1)/($H$74:$H$103-$G$74:$G$103+1)) -> 0 | ... O42: =SUMPRODUCT(($D$74:$D$103=$A42)*$F$74:$F$103*(((($H$74:$H$103<EOMONTH(O$32,0))*$H$74:$H$103+($H$74:$H$103>=EOMONTH(O$32,0))*EOMONTH(O$32,0))-(($G$74:$G$103>O$32)*$G$74:$G$103+($G$74:$G$103<=O$32)*O$32)+1)>0)*((($H$74:$H$103<EOMONTH(O$32,0))*$H$74:$H$103+($H$74:$H$103>=EOMONTH(O$32,0))*EOMONTH(O$32,0))-(($G$74:$G$103>O$32)*$G$74:$G$103+($G$74:$G$103<=O$32)*O$32)+1)/($H$74:$H$103-$G$74:$G$103+1)) -> 0 | P42: =SUM(D42:O42) -> 104799.22
A43: 342-11 | B43: 342 | C43: PROJETOS EXECUTIVOS / AS BUILT | D43: =SUMPRODUCT(($D$74:$D$103=$A43)*$F$74:$F$103*(((($H$74:$H$103<EOMONTH(D$32,0))*$H$74:$H$103+($H$74:$H$103>=EOMONTH(D$32,0))*EOMONTH(D$32,0))-(($G$74:$G$103>D$32)*$G$74:$G$103+($G$74:$G$103<=D$32)*D$32)+1)>0)*((($H$74:$H$103<EOMONTH(D$32,0))*$H$74:$H$103+($H$74:$H$103>=EOMONTH(D$32,0))*EOMONTH(D$32,0))-(($G$74:$G$103>D$32)*$G$74:$G$103+($G$74:$G$103<=D$32)*D$32)+1)/($H$74:$H$103-$G$74:$G$103+1)) -> 11363.028 | E43: =SUMPRODUCT(($D$74:$D$103=$A43)*$F$74:$F$103*(((($H$74:$H$103<EOMONTH(E$32,0))*$H$74:$H$103+($H$74:$H$103>=EOMONTH(E$32,0))*EOMONTH(E$32,0))-(($G$74:$G$103>E$32)*$G$74:$G$103+($G$74:$G$103<=E$32)*E$32)+1)>0)*((($H$74:$H$103<EOMONTH(E$32,0))*$H$74:$H$103+($H$74:$H$103>=EOMONTH(E$32,0))*EOMONTH(E$32,0))-(($G$74:$G$103>E$32)*$G$74:$G$103+($G$74:$G$103<=E$32)*E$32)+1)/($H$74:$H$103-$G$74:$G$103+1)) -> 12580.495 | F43: =SUMPRODUCT(($D$74:$D$103=$A43)*$F$74:$F$103*(((($H$74:$H$103<EOMONTH(F$32,0))*$H$74:$H$103+($H$74:$H$103>=EOMONTH(F$32,0))*EOMONTH(F$32,0))-(($G$74:$G$103>F$32)*$G$74:$G$103+($G$74:$G$103<=F$32)*F$32)+1)>0)*((($H$74:$H$103<EOMONTH(F$32,0))*$H$74:$H$103+($H$74:$H$103>=EOMONTH(F$32,0))*EOMONTH(F$32,0))-(($G$74:$G$103>F$32)*$G$74:$G$103+($G$74:$G$103<=F$32)*F$32)+1)/($H$74:$H$103-$G$74:$G$103+1)) -> 1217.4673 | G43: =SUMPRODUCT(($D$74:$D$103=$A43)*$F$74:$F$103*(((($H$74:$H$103<EOMONTH(G$32,0))*$H$74:$H$103+($H$74:$H$103>=EOMONTH(G$32,0))*EOMONTH(G$32,0))-(($G$74:$G$103>G$32)*$G$74:$G$103+($G$74:$G$103<=G$32)*G$32)+1)>0)*((($H$74:$H$103<EOMONTH(G$32,0))*$H$74:$H$103+($H$74:$H$103>=EOMONTH(G$32,0))*EOMONTH(G$32,0))-(($G$74:$G$103>G$32)*$G$74:$G$103+($G$74:$G$103<=G$32)*G$32)+1)/($H$74:$H$103-$G$74:$G$103+1)) -> 0 | H43: =SUMPRODUCT(($D$74:$D$103=$A43)*$F$74:$F$103*(((($H$74:$H$103<EOMONTH(H$32,0))*$H$74:$H$103+($H$74:$H$103>=EOMONTH(H$32,0))*EOMONTH(H$32,0))-(($G$74:$G$103>H$32)*$G$74:$G$103+($G$74:$G$103<=H$32)*H$32)+1)>0)*((($H$74:$H$103<EOMONTH(H$32,0))*$H$74:$H$103+($H$74:$H$103>=EOMONTH(H$32,0))*EOMONTH(H$32,0))-(($G$74:$G$103>H$32)*$G$74:$G$103+($G$74:$G$103<=H$32)*H$32)+1)/($H$74:$H$103-$G$74:$G$103+1)) -> 0 | I43: =SUMPRODUCT(($D$74:$D$103=$A43)*$F$74:$F$103*(((($H$74:$H$103<EOMONTH(I$32,0))*$H$74:$H$103+($H$74:$H$103>=EOMONTH(I$32,0))*EOMONTH(I$32,0))-(($G$74:$G$103>I$32)*$G$74:$G$103+($G$74:$G$103<=I$32)*I$32)+1)>0)*((($H$74:$H$103<EOMONTH(I$32,0))*$H$74:$H$103+($H$74:$H$103>=EOMONTH(I$32,0))*EOMONTH(I$32,0))-(($G$74:$G$103>I$32)*$G$74:$G$103+($G$74:$G$103<=I$32)*I$32)+1)/($H$74:$H$103-$G$74:$G$103+1)) -> 0 | J43: =SUMPRODUCT(($D$74:$D$103=$A43)*$F$74:$F$103*(((($H$74:$H$103<EOMONTH(J$32,0))*$H$74:$H$103+($H$74:$H$103>=EOMONTH(J$32,0))*EOMONTH(J$32,0))-(($G$74:$G$103>J$32)*$G$74:$G$103+($G$74:$G$103<=J$32)*J$32)+1)>0)*((($H$74:$H$103<EOMONTH(J$32,0))*$H$74:$H$103+($H$74:$H$103>=EOMONTH(J$32,0))*EOMONTH(J$32,0))-(($G$74:$G$103>J$32)*$G$74:$G$103+($G$74:$G$103<=J$32)*J$32)+1)/($H$74:$H$103-$G$74:$G$103+1)) -> 0 | K43: =SUMPRODUCT(($D$74:$D$103=$A43)*$F$74:$F$103*(((($H$74:$H$103<EOMONTH(K$32,0))*$H$74:$H$103+($H$74:$H$103>=EOMONTH(K$32,0))*EOMONTH(K$32,0))-(($G$74:$G$103>K$32)*$G$74:$G$103+($G$74:$G$103<=K$32)*K$32)+1)>0)*((($H$74:$H$103<EOMONTH(K$32,0))*$H$74:$H$103+($H$74:$H$103>=EOMONTH(K$32,0))*EOMONTH(K$32,0))-(($G$74:$G$103>K$32)*$G$74:$G$103+($G$74:$G$103<=K$32)*K$32)+1)/($H$74:$H$103-$G$74:$G$103+1)) -> 0 | ... O43: =SUMPRODUCT(($D$74:$D$103=$A43)*$F$74:$F$103*(((($H$74:$H$103<EOMONTH(O$32,0))*$H$74:$H$103+($H$74:$H$103>=EOMONTH(O$32,0))*EOMONTH(O$32,0))-(($G$74:$G$103>O$32)*$G$74:$G$103+($G$74:$G$103<=O$32)*O$32)+1)>0)*((($H$74:$H$103<EOMONTH(O$32,0))*$H$74:$H$103+($H$74:$H$103>=EOMONTH(O$32,0))*EOMONTH(O$32,0))-(($G$74:$G$103>O$32)*$G$74:$G$103+($G$74:$G$103<=O$32)*O$32)+1)/($H$74:$H$103-$G$74:$G$103+1)) -> 2795.67 | P43: =SUM(D43:O43) -> 27956.66
A44: 343-01 | B44: 343 | C44: Canteiro de Obras | D44: 104484.47 | E44: 104484.47 | F44: 104484.47 | G44: 104484.47 | H44: 104484.47 | I44: 104484.47 | J44: 104484.47 | K44: 104484.47 | L44: 104484.47 | M44: 0 | N44: 0 | O44: 0 | P44: =SUM(D44:O44) -> 940360.23
A45: 343-02 | B45: 343 | C45: Subadutora | D45: 0 | E45: 239178.67 | F45: 239178.67 | G45: 239178.67 | H45: 239178.67 | I45: 239178.67 | J45: 239178.67 | K45: 239178.67 | L45: 0 | M45: 0 | N45: 0 | O45: 0 | P45: =SUM(D45:O45) -> 1674250.7
A46: 343-03 | B46: 343 | C46: Caixas e Interligações | D46: 0 | E46: 41565.63 | F46: 41565.63 | G46: 41565.63 | H46: 41565.63 | I46: 41565.63 | J46: 41565.63 | K46: 41565.63 | L46: 0 | M46: 0 | N46: 0 | O46: 0 | P46: =SUM(D46:O46) -> 290959.41
A47: 343-04 | B47: 343 | C47: Hidromecânico | D47: 0 | E47: 240575.8 | F47: 240575.8 | G47: 240575.8 | H47: 240575.8 | I47: 240575.8 | J47: 240575.8 | K47: 240575.8 | L47: 0 | M47: 0 | N47: 0 | O47: 0 | P47: =SUM(D47:O47) -> 1684030.6
A48: 343-06 | B48: 343 | C48: Adm. Local | D48: 76647.49 | E48: 76647.49 | F48: 76647.49 | G48: 76647.49 | H48: 76647.49 | I48: 76647.49 | J48: 76647.49 | K48: 76647.49 | L48: 76647.49 | M48: 0 | N48: 0 | O48: 0 | P48: =SUM(D48:O48) -> 689827.41
C49: Total das etapas 342 | D49: =SUMIFS(D$33:D$48,$B$33:$B$48,"342") -> 11363.028 | E49: =SUMIFS(E$33:E$48,$B$33:$B$48,"342") -> 171033.14 | F49: =SUMIFS(F$33:F$48,$B$33:$B$48,"342") -> 115711.86 | G49: =SUMIFS(G$33:G$48,$B$33:$B$48,"342") -> 727659.97 | H49: =SUMIFS(H$33:H$48,$B$33:$B$48,"342") -> 225614.86 | I49: =SUMIFS(I$33:I$48,$B$33:$B$48,"342") -> 274986.91 | J49: =SUMIFS(J$33:J$48,$B$33:$B$48,"342") -> 168805.6 | K49: =SUMIFS(K$33:K$48,$B$33:$B$48,"342") -> 778547.97 | ... P49: =SUMIFS(P$33:P$48,$B$33:$B$48,"342") -> 3257970.7
C50: Total das etapas 343 (contrato) | D50: =SUMIFS(D$33:D$48,$B$33:$B$48,"343") -> 181131.96 | E50: =SUMIFS(E$33:E$48,$B$33:$B$48,"343") -> 702452.06 | F50: =SUMIFS(F$33:F$48,$B$33:$B$48,"343") -> 702452.06 | G50: =SUMIFS(G$33:G$48,$B$33:$B$48,"343") -> 702452.06 | H50: =SUMIFS(H$33:H$48,$B$33:$B$48,"343") -> 702452.06 | I50: =SUMIFS(I$33:I$48,$B$33:$B$48,"343") -> 702452.06 | J50: =SUMIFS(J$33:J$48,$B$33:$B$48,"343") -> 702452.06 | K50: =SUMIFS(K$33:K$48,$B$33:$B$48,"343") -> 702452.06 | ... P50: =SUMIFS(P$33:P$48,$B$33:$B$48,"343") -> 5279428.3
A51: ="342: cronograma R$ "&FIXED(P49,2)&" · contrato R$ "&FIXED('03. CONTRATOS'!$B$8,2)&" · diferença R$ "&FIXED(P49-'03. CONTRATOS'!$B$8,2) -> 342: cronograma R$ 3,257,970.74 · contrato R$ 3,258,000.00 · diferença R$ -29.26
A52: ="343: cronograma CAESB R$ "&FIXED(P50,2)&" · contrato R$ "&FIXED('03. CONTRATOS'!$D$8,2)&" · diferença R$ "&FIXED(P50-'03. CONTRATOS'!$D$8,2) -> 343: cronograma CAESB R$ 5,279,428.34 · contrato R$ 5,226,634.03 · diferença R$ 52,794.31
A55: POR OBRA E MÊS: valor do cronograma, custo previsto (estudo) e custo real lançado (08. CUSTOS, por competência)
A56: Obra | C56: Linha | D56: =D$32 -> 46266 | E56: =E$32 -> 46296 | F56: =F$32 -> 46327 | G56: =G$32 -> 46357 | H56: =H$32 -> 46388 | I56: =I$32 -> 46419 | J56: =J$32 -> 46447 | K56: =K$32 -> 46478 | ... O56: =O$32 -> 46600 | P56: Total
A57: 342 | C57: Valor do cronograma (R$) | D57: =SUMIFS(D$33:D$48,$B$33:$B$48,"342") -> 11363.028 | E57: =SUMIFS(E$33:E$48,$B$33:$B$48,"342") -> 171033.14 | F57: =SUMIFS(F$33:F$48,$B$33:$B$48,"342") -> 115711.86 | G57: =SUMIFS(G$33:G$48,$B$33:$B$48,"342") -> 727659.97 | H57: =SUMIFS(H$33:H$48,$B$33:$B$48,"342") -> 225614.86 | I57: =SUMIFS(I$33:I$48,$B$33:$B$48,"342") -> 274986.91 | J57: =SUMIFS(J$33:J$48,$B$33:$B$48,"342") -> 168805.6 | K57: =SUMIFS(K$33:K$48,$B$33:$B$48,"342") -> 778547.97 | ... O57: =SUMIFS(O$33:O$48,$B$33:$B$48,"342") -> 13144.553 | P57: =SUM(D57:O57) -> 3257970.7
A58: 342 | C58: Custo previsto no estudo (R$) | D58: =INDEX('FLUXO PROJETADO TAF'!$C$32:$R$32,MATCH(D$56,'FLUXO PROJETADO TAF'!$C$21:$R$21,0)) -> 0 | E58: =INDEX('FLUXO PROJETADO TAF'!$C$32:$R$32,MATCH(E$56,'FLUXO PROJETADO TAF'!$C$21:$R$21,0)) -> 29525.98 | F58: =INDEX('FLUXO PROJETADO TAF'!$C$32:$R$32,MATCH(F$56,'FLUXO PROJETADO TAF'!$C$21:$R$21,0)) -> 279112.44 | G58: =INDEX('FLUXO PROJETADO TAF'!$C$32:$R$32,MATCH(G$56,'FLUXO PROJETADO TAF'!$C$21:$R$21,0)) -> 371786.73 | H58: =INDEX('FLUXO PROJETADO TAF'!$C$32:$R$32,MATCH(H$56,'FLUXO PROJETADO TAF'!$C$21:$R$21,0)) -> 480863.72 | I58: =INDEX('FLUXO PROJETADO TAF'!$C$32:$R$32,MATCH(I$56,'FLUXO PROJETADO TAF'!$C$21:$R$21,0)) -> 243697.02 | J58: =INDEX('FLUXO PROJETADO TAF'!$C$32:$R$32,MATCH(J$56,'FLUXO PROJETADO TAF'!$C$21:$R$21,0)) -> 259211.77 | K58: =INDEX('FLUXO PROJETADO TAF'!$C$32:$R$32,MATCH(K$56,'FLUXO PROJETADO TAF'!$C$21:$R$21,0)) -> 172447.72 | ... O58: =INDEX('FLUXO PROJETADO TAF'!$C$32:$R$32,MATCH(O$56,'FLUXO PROJETADO TAF'!$C$21:$R$21,0)) -> 163887.89 | P58: =SUM(D58:O58) -> 3169728.1
A59: 342 | C59: Custo real lançado (08) | D59: =IF(ISTEXT(INDEX('FLUXO PROJETADO TAF'!$C$41:$R$41,MATCH(D$56,'FLUXO PROJETADO TAF'!$C$21:$R$21,0))),"sem lanç.",INDEX('FLUXO PROJETADO TAF'!$C$41:$R$41,MATCH(D$56,'FLUXO PROJETADO TAF'!$C$21:$R$21,0))) -> sem lanç. | E59: =IF(ISTEXT(INDEX('FLUXO PROJETADO TAF'!$C$41:$R$41,MATCH(E$56,'FLUXO PROJETADO TAF'!$C$21:$R$21,0))),"sem lanç.",INDEX('FLUXO PROJETADO TAF'!$C$41:$R$41,MATCH(E$56,'FLUXO PROJETADO TAF'!$C$21:$R$21,0))) -> sem lanç. | F59: =IF(ISTEXT(INDEX('FLUXO PROJETADO TAF'!$C$41:$R$41,MATCH(F$56,'FLUXO PROJETADO TAF'!$C$21:$R$21,0))),"sem lanç.",INDEX('FLUXO PROJETADO TAF'!$C$41:$R$41,MATCH(F$56,'FLUXO PROJETADO TAF'!$C$21:$R$21,0))) -> sem lanç. | G59: =IF(ISTEXT(INDEX('FLUXO PROJETADO TAF'!$C$41:$R$41,MATCH(G$56,'FLUXO PROJETADO TAF'!$C$21:$R$21,0))),"sem lanç.",INDEX('FLUXO PROJETADO TAF'!$C$41:$R$41,MATCH(G$56,'FLUXO PROJETADO TAF'!$C$21:$R$21,0))) -> sem lanç. | H59: =IF(ISTEXT(INDEX('FLUXO PROJETADO TAF'!$C$41:$R$41,MATCH(H$56,'FLUXO PROJETADO TAF'!$C$21:$R$21,0))),"sem lanç.",INDEX('FLUXO PROJETADO TAF'!$C$41:$R$41,MATCH(H$56,'FLUXO PROJETADO TAF'!$C$21:$R$21,0))) -> sem lanç. | I59: =IF(ISTEXT(INDEX('FLUXO PROJETADO TAF'!$C$41:$R$41,MATCH(I$56,'FLUXO PROJETADO TAF'!$C$21:$R$21,0))),"sem lanç.",INDEX('FLUXO PROJETADO TAF'!$C$41:$R$41,MATCH(I$56,'FLUXO PROJETADO TAF'!$C$21:$R$21,0))) -> sem lanç. | J59: =IF(ISTEXT(INDEX('FLUXO PROJETADO TAF'!$C$41:$R$41,MATCH(J$56,'FLUXO PROJETADO TAF'!$C$21:$R$21,0))),"sem lanç.",INDEX('FLUXO PROJETADO TAF'!$C$41:$R$41,MATCH(J$56,'FLUXO PROJETADO TAF'!$C$21:$R$21,0))) -> sem lanç. | K59: =IF(ISTEXT(INDEX('FLUXO PROJETADO TAF'!$C$41:$R$41,MATCH(K$56,'FLUXO PROJETADO TAF'!$C$21:$R$21,0))),"sem lanç.",INDEX('FLUXO PROJETADO TAF'!$C$41:$R$41,MATCH(K$56,'FLUXO PROJETADO TAF'!$C$21:$R$21,0))) -> sem lanç. | ... O59: =IF(ISTEXT(INDEX('FLUXO PROJETADO TAF'!$C$41:$R$41,MATCH(O$56,'FLUXO PROJETADO TAF'!$C$21:$R$21,0))),"sem lanç.",INDEX('FLUXO PROJETADO TAF'!$C$41:$R$41,MATCH(O$56,'FLUXO PROJETADO TAF'!$C$21:$R$21,0))) -> sem lanç. | P59: =IF(COUNT(D59:O59)=0,"sem lançamento",SUM(D59:O59)) -> sem lançamento
A60: 342 | C60: Diferença (real menos previsto) | D60: =IF(ISTEXT(D59),"",D59-D58) | E60: =IF(ISTEXT(E59),"",E59-E58) | F60: =IF(ISTEXT(F59),"",F59-F58) | G60: =IF(ISTEXT(G59),"",G59-G58) | H60: =IF(ISTEXT(H59),"",H59-H58) | I60: =IF(ISTEXT(I59),"",I59-I58) | J60: =IF(ISTEXT(J59),"",J59-J58) | K60: =IF(ISTEXT(K59),"",K59-K58) | ... P60: =IF(ISTEXT(P59),"",P59-P58)
A61: 343 | C61: Valor do cronograma (R$) | D61: =SUMIFS(D$33:D$48,$B$33:$B$48,"343") -> 181131.96 | E61: =SUMIFS(E$33:E$48,$B$33:$B$48,"343") -> 702452.06 | F61: =SUMIFS(F$33:F$48,$B$33:$B$48,"343") -> 702452.06 | G61: =SUMIFS(G$33:G$48,$B$33:$B$48,"343") -> 702452.06 | H61: =SUMIFS(H$33:H$48,$B$33:$B$48,"343") -> 702452.06 | I61: =SUMIFS(I$33:I$48,$B$33:$B$48,"343") -> 702452.06 | J61: =SUMIFS(J$33:J$48,$B$33:$B$48,"343") -> 702452.06 | K61: =SUMIFS(K$33:K$48,$B$33:$B$48,"343") -> 702452.06 | ... O61: =SUMIFS(O$33:O$48,$B$33:$B$48,"343") -> 0 | P61: =SUM(D61:O61) -> 5279428.3
A62: 343 | C62: Custo previsto no estudo (R$) | D62: =INDEX('FLUXO PROJETADO TAF'!$C$54:$R$54,MATCH(D$56,'FLUXO PROJETADO TAF'!$C$21:$R$21,0)) -> 55670.76 | E62: =INDEX('FLUXO PROJETADO TAF'!$C$54:$R$54,MATCH(E$56,'FLUXO PROJETADO TAF'!$C$21:$R$21,0)) -> 764972.02 | F62: =INDEX('FLUXO PROJETADO TAF'!$C$54:$R$54,MATCH(F$56,'FLUXO PROJETADO TAF'!$C$21:$R$21,0)) -> 580682.84 | G62: =INDEX('FLUXO PROJETADO TAF'!$C$54:$R$54,MATCH(G$56,'FLUXO PROJETADO TAF'!$C$21:$R$21,0)) -> 440042.97 | H62: =INDEX('FLUXO PROJETADO TAF'!$C$54:$R$54,MATCH(H$56,'FLUXO PROJETADO TAF'!$C$21:$R$21,0)) -> 388619.2 | I62: =INDEX('FLUXO PROJETADO TAF'!$C$54:$R$54,MATCH(I$56,'FLUXO PROJETADO TAF'!$C$21:$R$21,0)) -> 349757.27 | J62: =INDEX('FLUXO PROJETADO TAF'!$C$54:$R$54,MATCH(J$56,'FLUXO PROJETADO TAF'!$C$21:$R$21,0)) -> 427481.11 | K62: =INDEX('FLUXO PROJETADO TAF'!$C$54:$R$54,MATCH(K$56,'FLUXO PROJETADO TAF'!$C$21:$R$21,0)) -> 382352.07 | ... O62: =INDEX('FLUXO PROJETADO TAF'!$C$54:$R$54,MATCH(O$56,'FLUXO PROJETADO TAF'!$C$21:$R$21,0)) -> 0 | P62: =SUM(D62:O62) -> 3605617.7
A63: 343 | C63: Custo real lançado (08) | D63: =IF(ISTEXT(INDEX('FLUXO PROJETADO TAF'!$C$63:$R$63,MATCH(D$56,'FLUXO PROJETADO TAF'!$C$21:$R$21,0))),"sem lanç.",INDEX('FLUXO PROJETADO TAF'!$C$63:$R$63,MATCH(D$56,'FLUXO PROJETADO TAF'!$C$21:$R$21,0))) -> sem lanç. | E63: =IF(ISTEXT(INDEX('FLUXO PROJETADO TAF'!$C$63:$R$63,MATCH(E$56,'FLUXO PROJETADO TAF'!$C$21:$R$21,0))),"sem lanç.",INDEX('FLUXO PROJETADO TAF'!$C$63:$R$63,MATCH(E$56,'FLUXO PROJETADO TAF'!$C$21:$R$21,0))) -> sem lanç. | F63: =IF(ISTEXT(INDEX('FLUXO PROJETADO TAF'!$C$63:$R$63,MATCH(F$56,'FLUXO PROJETADO TAF'!$C$21:$R$21,0))),"sem lanç.",INDEX('FLUXO PROJETADO TAF'!$C$63:$R$63,MATCH(F$56,'FLUXO PROJETADO TAF'!$C$21:$R$21,0))) -> sem lanç. | G63: =IF(ISTEXT(INDEX('FLUXO PROJETADO TAF'!$C$63:$R$63,MATCH(G$56,'FLUXO PROJETADO TAF'!$C$21:$R$21,0))),"sem lanç.",INDEX('FLUXO PROJETADO TAF'!$C$63:$R$63,MATCH(G$56,'FLUXO PROJETADO TAF'!$C$21:$R$21,0))) -> sem lanç. | H63: =IF(ISTEXT(INDEX('FLUXO PROJETADO TAF'!$C$63:$R$63,MATCH(H$56,'FLUXO PROJETADO TAF'!$C$21:$R$21,0))),"sem lanç.",INDEX('FLUXO PROJETADO TAF'!$C$63:$R$63,MATCH(H$56,'FLUXO PROJETADO TAF'!$C$21:$R$21,0))) -> sem lanç. | I63: =IF(ISTEXT(INDEX('FLUXO PROJETADO TAF'!$C$63:$R$63,MATCH(I$56,'FLUXO PROJETADO TAF'!$C$21:$R$21,0))),"sem lanç.",INDEX('FLUXO PROJETADO TAF'!$C$63:$R$63,MATCH(I$56,'FLUXO PROJETADO TAF'!$C$21:$R$21,0))) -> sem lanç. | J63: =IF(ISTEXT(INDEX('FLUXO PROJETADO TAF'!$C$63:$R$63,MATCH(J$56,'FLUXO PROJETADO TAF'!$C$21:$R$21,0))),"sem lanç.",INDEX('FLUXO PROJETADO TAF'!$C$63:$R$63,MATCH(J$56,'FLUXO PROJETADO TAF'!$C$21:$R$21,0))) -> sem lanç. | K63: =IF(ISTEXT(INDEX('FLUXO PROJETADO TAF'!$C$63:$R$63,MATCH(K$56,'FLUXO PROJETADO TAF'!$C$21:$R$21,0))),"sem lanç.",INDEX('FLUXO PROJETADO TAF'!$C$63:$R$63,MATCH(K$56,'FLUXO PROJETADO TAF'!$C$21:$R$21,0))) -> sem lanç. | ... O63: =IF(ISTEXT(INDEX('FLUXO PROJETADO TAF'!$C$63:$R$63,MATCH(O$56,'FLUXO PROJETADO TAF'!$C$21:$R$21,0))),"sem lanç.",INDEX('FLUXO PROJETADO TAF'!$C$63:$R$63,MATCH(O$56,'FLUXO PROJETADO TAF'!$C$21:$R$21,0))) -> sem lanç. | P63: =IF(COUNT(D63:O63)=0,"sem lançamento",SUM(D63:O63)) -> sem lançamento
A64: 343 | C64: Diferença (real menos previsto) | D64: =IF(ISTEXT(D63),"",D63-D62) | E64: =IF(ISTEXT(E63),"",E63-E62) | F64: =IF(ISTEXT(F63),"",F63-F62) | G64: =IF(ISTEXT(G63),"",G63-G62) | H64: =IF(ISTEXT(H63),"",H63-H62) | I64: =IF(ISTEXT(I63),"",I63-I62) | J64: =IF(ISTEXT(J63),"",J63-J62) | K64: =IF(ISTEXT(K63),"",K63-K62) | ... P64: =IF(ISTEXT(P63),"",P63-P62)
A65: TAF | C65: Valor do cronograma (R$) | D65: =D57+D61 -> 192494.99 | E65: =E57+E61 -> 873485.2 | F65: =F57+F61 -> 818163.92 | G65: =G57+G61 -> 1430112 | H65: =H57+H61 -> 928066.92 | I65: =I57+I61 -> 977438.97 | J65: =J57+J61 -> 871257.66 | K65: =K57+K61 -> 1481000 | ... O65: =O57+O61 -> 13144.553 | P65: =SUM(D65:O65) -> 8537399.1
A66: TAF | C66: Custo previsto no estudo (R$) | D66: =INDEX('FLUXO PROJETADO TAF'!$C$71:$R$71,MATCH(D$56,'FLUXO PROJETADO TAF'!$C$21:$R$21,0)) -> 55670.76 | E66: =INDEX('FLUXO PROJETADO TAF'!$C$71:$R$71,MATCH(E$56,'FLUXO PROJETADO TAF'!$C$21:$R$21,0)) -> 794498 | F66: =INDEX('FLUXO PROJETADO TAF'!$C$71:$R$71,MATCH(F$56,'FLUXO PROJETADO TAF'!$C$21:$R$21,0)) -> 859795.28 | G66: =INDEX('FLUXO PROJETADO TAF'!$C$71:$R$71,MATCH(G$56,'FLUXO PROJETADO TAF'!$C$21:$R$21,0)) -> 811829.7 | H66: =INDEX('FLUXO PROJETADO TAF'!$C$71:$R$71,MATCH(H$56,'FLUXO PROJETADO TAF'!$C$21:$R$21,0)) -> 869482.92 | I66: =INDEX('FLUXO PROJETADO TAF'!$C$71:$R$71,MATCH(I$56,'FLUXO PROJETADO TAF'!$C$21:$R$21,0)) -> 593454.29 | J66: =INDEX('FLUXO PROJETADO TAF'!$C$71:$R$71,MATCH(J$56,'FLUXO PROJETADO TAF'!$C$21:$R$21,0)) -> 686692.88 | K66: =INDEX('FLUXO PROJETADO TAF'!$C$71:$R$71,MATCH(K$56,'FLUXO PROJETADO TAF'!$C$21:$R$21,0)) -> 554799.79 | ... O66: =INDEX('FLUXO PROJETADO TAF'!$C$71:$R$71,MATCH(O$56,'FLUXO PROJETADO TAF'!$C$21:$R$21,0)) -> 163887.89 | P66: =SUM(D66:O66) -> 6775345.8
A67: TAF | C67: Custo real lançado (08) | D67: =IF(ISTEXT(INDEX('FLUXO PROJETADO TAF'!$C$78:$R$78,MATCH(D$56,'FLUXO PROJETADO TAF'!$C$21:$R$21,0))),"sem lanç.",INDEX('FLUXO PROJETADO TAF'!$C$78:$R$78,MATCH(D$56,'FLUXO PROJETADO TAF'!$C$21:$R$21,0))) -> sem lanç. | E67: =IF(ISTEXT(INDEX('FLUXO PROJETADO TAF'!$C$78:$R$78,MATCH(E$56,'FLUXO PROJETADO TAF'!$C$21:$R$21,0))),"sem lanç.",INDEX('FLUXO PROJETADO TAF'!$C$78:$R$78,MATCH(E$56,'FLUXO PROJETADO TAF'!$C$21:$R$21,0))) -> sem lanç. | F67: =IF(ISTEXT(INDEX('FLUXO PROJETADO TAF'!$C$78:$R$78,MATCH(F$56,'FLUXO PROJETADO TAF'!$C$21:$R$21,0))),"sem lanç.",INDEX('FLUXO PROJETADO TAF'!$C$78:$R$78,MATCH(F$56,'FLUXO PROJETADO TAF'!$C$21:$R$21,0))) -> sem lanç. | G67: =IF(ISTEXT(INDEX('FLUXO PROJETADO TAF'!$C$78:$R$78,MATCH(G$56,'FLUXO PROJETADO TAF'!$C$21:$R$21,0))),"sem lanç.",INDEX('FLUXO PROJETADO TAF'!$C$78:$R$78,MATCH(G$56,'FLUXO PROJETADO TAF'!$C$21:$R$21,0))) -> sem lanç. | H67: =IF(ISTEXT(INDEX('FLUXO PROJETADO TAF'!$C$78:$R$78,MATCH(H$56,'FLUXO PROJETADO TAF'!$C$21:$R$21,0))),"sem lanç.",INDEX('FLUXO PROJETADO TAF'!$C$78:$R$78,MATCH(H$56,'FLUXO PROJETADO TAF'!$C$21:$R$21,0))) -> sem lanç. | I67: =IF(ISTEXT(INDEX('FLUXO PROJETADO TAF'!$C$78:$R$78,MATCH(I$56,'FLUXO PROJETADO TAF'!$C$21:$R$21,0))),"sem lanç.",INDEX('FLUXO PROJETADO TAF'!$C$78:$R$78,MATCH(I$56,'FLUXO PROJETADO TAF'!$C$21:$R$21,0))) -> sem lanç. | J67: =IF(ISTEXT(INDEX('FLUXO PROJETADO TAF'!$C$78:$R$78,MATCH(J$56,'FLUXO PROJETADO TAF'!$C$21:$R$21,0))),"sem lanç.",INDEX('FLUXO PROJETADO TAF'!$C$78:$R$78,MATCH(J$56,'FLUXO PROJETADO TAF'!$C$21:$R$21,0))) -> sem lanç. | K67: =IF(ISTEXT(INDEX('FLUXO PROJETADO TAF'!$C$78:$R$78,MATCH(K$56,'FLUXO PROJETADO TAF'!$C$21:$R$21,0))),"sem lanç.",INDEX('FLUXO PROJETADO TAF'!$C$78:$R$78,MATCH(K$56,'FLUXO PROJETADO TAF'!$C$21:$R$21,0))) -> sem lanç. | ... O67: =IF(ISTEXT(INDEX('FLUXO PROJETADO TAF'!$C$78:$R$78,MATCH(O$56,'FLUXO PROJETADO TAF'!$C$21:$R$21,0))),"sem lanç.",INDEX('FLUXO PROJETADO TAF'!$C$78:$R$78,MATCH(O$56,'FLUXO PROJETADO TAF'!$C$21:$R$21,0))) -> sem lanç. | P67: =IF(COUNT(D67:O67)=0,"sem lançamento",SUM(D67:O67)) -> sem lançamento
A68: TAF | C68: Diferença (real menos previsto) | D68: =IF(ISTEXT(D67),"",D67-D66) | E68: =IF(ISTEXT(E67),"",E67-E66) | F68: =IF(ISTEXT(F67),"",F67-F66) | G68: =IF(ISTEXT(G67),"",G67-G66) | H68: =IF(ISTEXT(H67),"",H67-H66) | I68: =IF(ISTEXT(I67),"",I67-I66) | J68: =IF(ISTEXT(J67),"",J67-J66) | K68: =IF(ISTEXT(K67),"",K67-K66) | ... P68: =IF(ISTEXT(P67),"",P67-P66)
A69: Nota: o custo previsto é o fluxo de saídas (342: estudo REV13, aba 09; 343: motor, aba 19). O valor do cronograma é receita, não custo. A grade vai de set/26 a ago/27: a 342 ainda paga R$ 42.731 depois de ago/27 (estudo REV13, aba 09), que está na 04 e no FLUXO.
A72: EVENTOS DA 342: VALOR DO ANEXO VII E DATAS DE EXECUÇÃO DO PLANO (estudo REV13, aba 05; cenário 1)
A73: Evento | B73: Obra | C73: Descrição | D73: Etapa (ID) | E73: Medição | F73: Valor do evento (R$) | G73: Início (plano) | H73: Fim (plano) | I73: Corte do BM que mede a conclusão | J73: Dias corridos | K73: Restrições abertas (05C) | L73: Situação no corte | M73: Quantidade (estudo REV13, aba 37) | N73: Antecessor (aba 37) | O73: % físico apontado (05B, até o corte) | P73: Data do aceite (digitar) | Q73: Critério de conclusão (proposta: validar com a fiscalização) | AG73: Documento de aceite
A74: 1.1.1 | B74: 342 | C74: Canteiro | D74: 342-01 | E74: %: proporcional | F74: 122394 | G74: 46314 | H74: 46604 | I74: 46619 | J74: =H74-G74+1 -> 291 | K74: =COUNTIFS('05C. RESTRIÇÕES'!$B$5:$B$204,"342",'05C. RESTRIÇÕES'!$C$5:$C$204,A74,'05C. RESTRIÇÕES'!$H$5:$H$204,"ABERTA") -> 3 | L74: =IF(ISNUMBER(P74),"aceito",IF(H74<DATA_GESTAO,"devia estar concluído",IF(G74<=DATA_GESTAO,"em execução",IF(G74-DATA_GESTAO<=42,"começa em até 6 semanas","futuro"))))&IF(COUNTIFS('05C. RESTRIÇÕES'!$B$5:$B$204,"342",'05C. RESTRIÇÕES'!$C$5:$C$204,A74,'05C. RESTRIÇÕES'!$L$5:$L$204,"VENCIDA")>0," · restrição vencida","") -> começa em até 6 semanas | M74: 1 | N74: nenhum | O74: proporcional ao BM | P74: a cada BM (06) | Q74: medição proporcional no BM | AG74: BM aprovado (06)
A75: 2.1.1 | B75: 342 | C75: Administração local | D75: 342-02 | E75: %: proporcional | F75: 479911 | G75: 46314 | H75: 46604 | I75: 46619 | J75: =H75-G75+1 -> 291 | K75: =COUNTIFS('05C. RESTRIÇÕES'!$B$5:$B$204,"342",'05C. RESTRIÇÕES'!$C$5:$C$204,A75,'05C. RESTRIÇÕES'!$H$5:$H$204,"ABERTA") -> 0 | L75: =IF(ISNUMBER(P75),"aceito",IF(H75<DATA_GESTAO,"devia estar concluído",IF(G75<=DATA_GESTAO,"em execução",IF(G75-DATA_GESTAO<=42,"começa em até 6 semanas","futuro"))))&IF(COUNTIFS('05C. RESTRIÇÕES'!$B$5:$B$204,"342",'05C. RESTRIÇÕES'!$C$5:$C$204,A75,'05C. RESTRIÇÕES'!$L$5:$L$204,"VENCIDA")>0," · restrição vencida","") -> começa em até 6 semanas | M75: 1 | N75: nenhum | O75: proporcional ao BM | P75: a cada BM (06) | Q75: medição proporcional no BM | AG75: BM aprovado (06)
A76: 3.1.1 | B76: 342 | C76: Terraplenagem e desvio | D76: 342-03 | E76: UN: só na conclusão | F76: 131545.55 | G76: 46314 | H76: 46325 | I76: 46346 | J76: =H76-G76+1 -> 12 | K76: =COUNTIFS('05C. RESTRIÇÕES'!$B$5:$B$204,"342",'05C. RESTRIÇÕES'!$C$5:$C$204,A76,'05C. RESTRIÇÕES'!$H$5:$H$204,"ABERTA") -> 8 | L76: =IF(ISNUMBER(P76),"aceito",IF(H76<DATA_GESTAO,"devia estar concluído",IF(G76<=DATA_GESTAO,"em execução",IF(G76-DATA_GESTAO<=42,"começa em até 6 semanas","futuro"))))&IF(COUNTIFS('05C. RESTRIÇÕES'!$B$5:$B$204,"342",'05C. RESTRIÇÕES'!$C$5:$C$204,A76,'05C. RESTRIÇÕES'!$L$5:$L$204,"VENCIDA")>0," · restrição vencida","") -> começa em até 6 semanas · restrição vencida | M76: 1619 | N76: nenhum | O76: =IF(COUNTIFS('05B. APONTAMENTO DIÁRIO'!$B$5:$B$1004,"342",'05B. APONTAMENTO DIÁRIO'!$C$5:$C$1004,$A76,'05B. APONTAMENTO DIÁRIO'!$A$5:$A$1004,"<="&DATA_GESTAO)=0,"sem apontamento",IF(COUNTIFS('05B. APONTAMENTO DIÁRIO'!$B$5:$B$1004,"342",'05B. APONTAMENTO DIÁRIO'!$C$5:$C$1004,$A76,'05B. APONTAMENTO DIÁRIO'!$A$5:$A$1004,"<="&DATA_GESTAO,'05B. APONTAMENTO DIÁRIO'!$G$5:$G$1004,"m³")=0,"unidade diferente",SUMIFS('05B. APONTAMENTO DIÁRIO'!$F$5:$F$1004,'05B. APONTAMENTO DIÁRIO'!$B$5:$B$1004,"342",'05B. APONTAMENTO DIÁRIO'!$C$5:$C$1004,$A76,'05B. APONTAMENTO DIÁRIO'!$A$5:$A$1004,"<="&DATA_GESTAO,'05B. APONTAMENTO DIÁRIO'!$G$5:$G$1004,"m³")/$M76)) -> sem apontamento | P76: PENDENTE | Q76: a definir com a fiscalização (quantidade da aba 37: 1619 m³) | AG76: a definir com a fiscalização
A77: 3.2.1 | B77: 342 | C77: Interligação ETA–UTR | D77: 342-04 | E77: UN: só na conclusão | F77: 334559.95 | G77: 46358 | H77: 46380 | I77: 46407 | J77: =H77-G77+1 -> 23 | K77: =COUNTIFS('05C. RESTRIÇÕES'!$B$5:$B$204,"342",'05C. RESTRIÇÕES'!$C$5:$C$204,A77,'05C. RESTRIÇÕES'!$H$5:$H$204,"ABERTA") -> 3 | L77: =IF(ISNUMBER(P77),"aceito",IF(H77<DATA_GESTAO,"devia estar concluído",IF(G77<=DATA_GESTAO,"em execução",IF(G77-DATA_GESTAO<=42,"começa em até 6 semanas","futuro"))))&IF(COUNTIFS('05C. RESTRIÇÕES'!$B$5:$B$204,"342",'05C. RESTRIÇÕES'!$C$5:$C$204,A77,'05C. RESTRIÇÕES'!$L$5:$L$204,"VENCIDA")>0," · restrição vencida","") -> futuro · restrição vencida | M77: 246 | N77: nenhum | O77: =IF(COUNTIFS('05B. APONTAMENTO DIÁRIO'!$B$5:$B$1004,"342",'05B. APONTAMENTO DIÁRIO'!$C$5:$C$1004,$A77,'05B. APONTAMENTO DIÁRIO'!$A$5:$A$1004,"<="&DATA_GESTAO)=0,"sem apontamento",IF(COUNTIFS('05B. APONTAMENTO DIÁRIO'!$B$5:$B$1004,"342",'05B. APONTAMENTO DIÁRIO'!$C$5:$C$1004,$A77,'05B. APONTAMENTO DIÁRIO'!$A$5:$A$1004,"<="&DATA_GESTAO,'05B. APONTAMENTO DIÁRIO'!$G$5:$G$1004,"m")=0,"unidade diferente",SUMIFS('05B. APONTAMENTO DIÁRIO'!$F$5:$F$1004,'05B. APONTAMENTO DIÁRIO'!$B$5:$B$1004,"342",'05B. APONTAMENTO DIÁRIO'!$C$5:$C$1004,$A77,'05B. APONTAMENTO DIÁRIO'!$A$5:$A$1004,"<="&DATA_GESTAO,'05B. APONTAMENTO DIÁRIO'!$G$5:$G$1004,"m")/$M77)) -> sem apontamento | P77: PENDENTE | Q77: 246 m assentados e teste hidrostático e desinfecção aprovados (aba 37 ID 28; Anexo VII p.8) | AG77: laudo do teste assinado pela fiscalização
A78: 3.3.1 | B78: 342 | C78: Recalque UTR–ETA | D78: 342-05 | E78: UN: só na conclusão | F78: 54857.68 | G78: 46370 | H78: 46387 | I78: 46407 | J78: =H78-G78+1 -> 18 | K78: =COUNTIFS('05C. RESTRIÇÕES'!$B$5:$B$204,"342",'05C. RESTRIÇÕES'!$C$5:$C$204,A78,'05C. RESTRIÇÕES'!$H$5:$H$204,"ABERTA") -> 1 | L78: =IF(ISNUMBER(P78),"aceito",IF(H78<DATA_GESTAO,"devia estar concluído",IF(G78<=DATA_GESTAO,"em execução",IF(G78-DATA_GESTAO<=42,"começa em até 6 semanas","futuro"))))&IF(COUNTIFS('05C. RESTRIÇÕES'!$B$5:$B$204,"342",'05C. RESTRIÇÕES'!$C$5:$C$204,A78,'05C. RESTRIÇÕES'!$L$5:$L$204,"VENCIDA")>0," · restrição vencida","") -> futuro | M78: 365 | N78: nenhum | O78: =IF(COUNTIFS('05B. APONTAMENTO DIÁRIO'!$B$5:$B$1004,"342",'05B. APONTAMENTO DIÁRIO'!$C$5:$C$1004,$A78,'05B. APONTAMENTO DIÁRIO'!$A$5:$A$1004,"<="&DATA_GESTAO)=0,"sem apontamento",IF(COUNTIFS('05B. APONTAMENTO DIÁRIO'!$B$5:$B$1004,"342",'05B. APONTAMENTO DIÁRIO'!$C$5:$C$1004,$A78,'05B. APONTAMENTO DIÁRIO'!$A$5:$A$1004,"<="&DATA_GESTAO,'05B. APONTAMENTO DIÁRIO'!$G$5:$G$1004,"m")=0,"unidade diferente",SUMIFS('05B. APONTAMENTO DIÁRIO'!$F$5:$F$1004,'05B. APONTAMENTO DIÁRIO'!$B$5:$B$1004,"342",'05B. APONTAMENTO DIÁRIO'!$C$5:$C$1004,$A78,'05B. APONTAMENTO DIÁRIO'!$A$5:$A$1004,"<="&DATA_GESTAO,'05B. APONTAMENTO DIÁRIO'!$G$5:$G$1004,"m")/$M78)) -> sem apontamento | P78: PENDENTE | Q78: 365 m assentados e teste hidrostático aprovado (aba 37 ID 29) | AG78: laudo do teste assinado pela fiscalização
A79: 3.4.1 | B79: 342 | C79: Drenagens/esgotamento/caixa de chegada | D79: 342-06 | E79: UN: só na conclusão | F79: 72003.88 | G79: 46349 | H79: 46366 | I79: 46376 | J79: =H79-G79+1 -> 18 | K79: =COUNTIFS('05C. RESTRIÇÕES'!$B$5:$B$204,"342",'05C. RESTRIÇÕES'!$C$5:$C$204,A79,'05C. RESTRIÇÕES'!$H$5:$H$204,"ABERTA") -> 3 | L79: =IF(ISNUMBER(P79),"aceito",IF(H79<DATA_GESTAO,"devia estar concluído",IF(G79<=DATA_GESTAO,"em execução",IF(G79-DATA_GESTAO<=42,"começa em até 6 semanas","futuro"))))&IF(COUNTIFS('05C. RESTRIÇÕES'!$B$5:$B$204,"342",'05C. RESTRIÇÕES'!$C$5:$C$204,A79,'05C. RESTRIÇÕES'!$L$5:$L$204,"VENCIDA")>0," · restrição vencida","") -> começa em até 6 semanas · restrição vencida | M79: 194.45 | N79: nenhum | O79: =IF(COUNTIFS('05B. APONTAMENTO DIÁRIO'!$B$5:$B$1004,"342",'05B. APONTAMENTO DIÁRIO'!$C$5:$C$1004,$A79,'05B. APONTAMENTO DIÁRIO'!$A$5:$A$1004,"<="&DATA_GESTAO)=0,"sem apontamento",IF(COUNTIFS('05B. APONTAMENTO DIÁRIO'!$B$5:$B$1004,"342",'05B. APONTAMENTO DIÁRIO'!$C$5:$C$1004,$A79,'05B. APONTAMENTO DIÁRIO'!$A$5:$A$1004,"<="&DATA_GESTAO,'05B. APONTAMENTO DIÁRIO'!$G$5:$G$1004,"m")=0,"unidade diferente",SUMIFS('05B. APONTAMENTO DIÁRIO'!$F$5:$F$1004,'05B. APONTAMENTO DIÁRIO'!$B$5:$B$1004,"342",'05B. APONTAMENTO DIÁRIO'!$C$5:$C$1004,$A79,'05B. APONTAMENTO DIÁRIO'!$A$5:$A$1004,"<="&DATA_GESTAO,'05B. APONTAMENTO DIÁRIO'!$G$5:$G$1004,"m")/$M79)) -> sem apontamento | P79: PENDENTE | Q79: a definir com a fiscalização (quantidade da aba 37: 194,45 m) | AG79: a definir com a fiscalização
A80: 3.5.1 | B80: 342 | C80: Tanque: limpeza, locação e movimento de terra | D80: 342-07 | E80: UN: só na conclusão | F80: 20399.37 | G80: 46329 | H80: 46342 | I80: 46346 | J80: =H80-G80+1 -> 14 | K80: =COUNTIFS('05C. RESTRIÇÕES'!$B$5:$B$204,"342",'05C. RESTRIÇÕES'!$C$5:$C$204,A80,'05C. RESTRIÇÕES'!$H$5:$H$204,"ABERTA") -> 1 | L80: =IF(ISNUMBER(P80),"aceito",IF(H80<DATA_GESTAO,"devia estar concluído",IF(G80<=DATA_GESTAO,"em execução",IF(G80-DATA_GESTAO<=42,"começa em até 6 semanas","futuro"))))&IF(COUNTIFS('05C. RESTRIÇÕES'!$B$5:$B$204,"342",'05C. RESTRIÇÕES'!$C$5:$C$204,A80,'05C. RESTRIÇÕES'!$L$5:$L$204,"VENCIDA")>0," · restrição vencida","") -> começa em até 6 semanas · restrição vencida | M80: 698.76 | N80: nenhum | O80: =IF(COUNTIFS('05B. APONTAMENTO DIÁRIO'!$B$5:$B$1004,"342",'05B. APONTAMENTO DIÁRIO'!$C$5:$C$1004,$A80,'05B. APONTAMENTO DIÁRIO'!$A$5:$A$1004,"<="&DATA_GESTAO)=0,"sem apontamento",IF(COUNTIFS('05B. APONTAMENTO DIÁRIO'!$B$5:$B$1004,"342",'05B. APONTAMENTO DIÁRIO'!$C$5:$C$1004,$A80,'05B. APONTAMENTO DIÁRIO'!$A$5:$A$1004,"<="&DATA_GESTAO,'05B. APONTAMENTO DIÁRIO'!$G$5:$G$1004,"m²")=0,"unidade diferente",SUMIFS('05B. APONTAMENTO DIÁRIO'!$F$5:$F$1004,'05B. APONTAMENTO DIÁRIO'!$B$5:$B$1004,"342",'05B. APONTAMENTO DIÁRIO'!$C$5:$C$1004,$A80,'05B. APONTAMENTO DIÁRIO'!$A$5:$A$1004,"<="&DATA_GESTAO,'05B. APONTAMENTO DIÁRIO'!$G$5:$G$1004,"m²")/$M80)) -> sem apontamento | P80: PENDENTE | Q80: a definir com a fiscalização (quantidade da aba 37: 698,76 m²) | AG80: a definir com a fiscalização
A81: 3.5.2 | B81: 342 | C81: Tanque: estrutura de concreto | D81: 342-07 | E81: %: proporcional | F81: 382325.95 | G81: 46358 | H81: 46406 | I81: 46407 | J81: =H81-G81+1 -> 49 | K81: =COUNTIFS('05C. RESTRIÇÕES'!$B$5:$B$204,"342",'05C. RESTRIÇÕES'!$C$5:$C$204,A81,'05C. RESTRIÇÕES'!$H$5:$H$204,"ABERTA") -> 4 | L81: =IF(ISNUMBER(P81),"aceito",IF(H81<DATA_GESTAO,"devia estar concluído",IF(G81<=DATA_GESTAO,"em execução",IF(G81-DATA_GESTAO<=42,"começa em até 6 semanas","futuro"))))&IF(COUNTIFS('05C. RESTRIÇÕES'!$B$5:$B$204,"342",'05C. RESTRIÇÕES'!$C$5:$C$204,A81,'05C. RESTRIÇÕES'!$L$5:$L$204,"VENCIDA")>0," · restrição vencida","") -> futuro | M81: 124.46 | N81: 3.5.1 | O81: =IF(COUNTIFS('05B. APONTAMENTO DIÁRIO'!$B$5:$B$1004,"342",'05B. APONTAMENTO DIÁRIO'!$C$5:$C$1004,$A81,'05B. APONTAMENTO DIÁRIO'!$A$5:$A$1004,"<="&DATA_GESTAO)=0,"sem apontamento",IF(COUNTIFS('05B. APONTAMENTO DIÁRIO'!$B$5:$B$1004,"342",'05B. APONTAMENTO DIÁRIO'!$C$5:$C$1004,$A81,'05B. APONTAMENTO DIÁRIO'!$A$5:$A$1004,"<="&DATA_GESTAO,'05B. APONTAMENTO DIÁRIO'!$G$5:$G$1004,"m³")=0,"unidade diferente",SUMIFS('05B. APONTAMENTO DIÁRIO'!$F$5:$F$1004,'05B. APONTAMENTO DIÁRIO'!$B$5:$B$1004,"342",'05B. APONTAMENTO DIÁRIO'!$C$5:$C$1004,$A81,'05B. APONTAMENTO DIÁRIO'!$A$5:$A$1004,"<="&DATA_GESTAO,'05B. APONTAMENTO DIÁRIO'!$G$5:$G$1004,"m³")/$M81)) -> sem apontamento | P81: a cada BM (06) | Q81: medição proporcional no BM | AG81: BM aprovado (06)
A82: 3.5.3 | B82: 342 | C82: Tanque: impermeabilização | D82: 342-07 | E82: UN: só na conclusão | F82: 38289.15 | G82: 46462 | H82: 46476 | I82: 46497 | J82: =H82-G82+1 -> 15 | K82: =COUNTIFS('05C. RESTRIÇÕES'!$B$5:$B$204,"342",'05C. RESTRIÇÕES'!$C$5:$C$204,A82,'05C. RESTRIÇÕES'!$H$5:$H$204,"ABERTA") -> 1 | L82: =IF(ISNUMBER(P82),"aceito",IF(H82<DATA_GESTAO,"devia estar concluído",IF(G82<=DATA_GESTAO,"em execução",IF(G82-DATA_GESTAO<=42,"começa em até 6 semanas","futuro"))))&IF(COUNTIFS('05C. RESTRIÇÕES'!$B$5:$B$204,"342",'05C. RESTRIÇÕES'!$C$5:$C$204,A82,'05C. RESTRIÇÕES'!$L$5:$L$204,"VENCIDA")>0," · restrição vencida","") -> futuro | M82: 1216.11 | N82: 3.5.2 | O82: =IF(COUNTIFS('05B. APONTAMENTO DIÁRIO'!$B$5:$B$1004,"342",'05B. APONTAMENTO DIÁRIO'!$C$5:$C$1004,$A82,'05B. APONTAMENTO DIÁRIO'!$A$5:$A$1004,"<="&DATA_GESTAO)=0,"sem apontamento",IF(COUNTIFS('05B. APONTAMENTO DIÁRIO'!$B$5:$B$1004,"342",'05B. APONTAMENTO DIÁRIO'!$C$5:$C$1004,$A82,'05B. APONTAMENTO DIÁRIO'!$A$5:$A$1004,"<="&DATA_GESTAO,'05B. APONTAMENTO DIÁRIO'!$G$5:$G$1004,"m²")=0,"unidade diferente",SUMIFS('05B. APONTAMENTO DIÁRIO'!$F$5:$F$1004,'05B. APONTAMENTO DIÁRIO'!$B$5:$B$1004,"342",'05B. APONTAMENTO DIÁRIO'!$C$5:$C$1004,$A82,'05B. APONTAMENTO DIÁRIO'!$A$5:$A$1004,"<="&DATA_GESTAO,'05B. APONTAMENTO DIÁRIO'!$G$5:$G$1004,"m²")/$M82)) -> sem apontamento | P82: PENDENTE | Q82: a definir com a fiscalização (quantidade da aba 37: 1216,11 m²) | AG82: a definir com a fiscalização
A83: 3.5.4 | B83: 342 | C83: Tanque: suporte da manta | D83: 342-07 | E83: UN: só na conclusão | F83: 117421.79 | G83: 46475 | H83: 46486 | I83: 46497 | J83: =H83-G83+1 -> 12 | K83: =COUNTIFS('05C. RESTRIÇÕES'!$B$5:$B$204,"342",'05C. RESTRIÇÕES'!$C$5:$C$204,A83,'05C. RESTRIÇÕES'!$H$5:$H$204,"ABERTA") -> 0 | L83: =IF(ISNUMBER(P83),"aceito",IF(H83<DATA_GESTAO,"devia estar concluído",IF(G83<=DATA_GESTAO,"em execução",IF(G83-DATA_GESTAO<=42,"começa em até 6 semanas","futuro"))))&IF(COUNTIFS('05C. RESTRIÇÕES'!$B$5:$B$204,"342",'05C. RESTRIÇÕES'!$C$5:$C$204,A83,'05C. RESTRIÇÕES'!$L$5:$L$204,"VENCIDA")>0," · restrição vencida","") -> futuro | M83: 888 | N83: 3.5.2 | O83: =IF(COUNTIFS('05B. APONTAMENTO DIÁRIO'!$B$5:$B$1004,"342",'05B. APONTAMENTO DIÁRIO'!$C$5:$C$1004,$A83,'05B. APONTAMENTO DIÁRIO'!$A$5:$A$1004,"<="&DATA_GESTAO)=0,"sem apontamento",IF(COUNTIFS('05B. APONTAMENTO DIÁRIO'!$B$5:$B$1004,"342",'05B. APONTAMENTO DIÁRIO'!$C$5:$C$1004,$A83,'05B. APONTAMENTO DIÁRIO'!$A$5:$A$1004,"<="&DATA_GESTAO,'05B. APONTAMENTO DIÁRIO'!$G$5:$G$1004,"m²")=0,"unidade diferente",SUMIFS('05B. APONTAMENTO DIÁRIO'!$F$5:$F$1004,'05B. APONTAMENTO DIÁRIO'!$B$5:$B$1004,"342",'05B. APONTAMENTO DIÁRIO'!$C$5:$C$1004,$A83,'05B. APONTAMENTO DIÁRIO'!$A$5:$A$1004,"<="&DATA_GESTAO,'05B. APONTAMENTO DIÁRIO'!$G$5:$G$1004,"m²")/$M83)) -> sem apontamento | P83: PENDENTE | Q83: a definir com a fiscalização (quantidade da aba 37: 888 m²) | AG83: a definir com a fiscalização
A84: 3.5.5 | B84: 342 | C84: Tanque: manta geotêxtil | D84: 342-07 | E84: UN: só na conclusão | F84: 25108.52 | G84: 46489 | H84: 46497 | I84: 46497 | J84: =H84-G84+1 -> 9 | K84: =COUNTIFS('05C. RESTRIÇÕES'!$B$5:$B$204,"342",'05C. RESTRIÇÕES'!$C$5:$C$204,A84,'05C. RESTRIÇÕES'!$H$5:$H$204,"ABERTA") -> 0 | L84: =IF(ISNUMBER(P84),"aceito",IF(H84<DATA_GESTAO,"devia estar concluído",IF(G84<=DATA_GESTAO,"em execução",IF(G84-DATA_GESTAO<=42,"começa em até 6 semanas","futuro"))))&IF(COUNTIFS('05C. RESTRIÇÕES'!$B$5:$B$204,"342",'05C. RESTRIÇÕES'!$C$5:$C$204,A84,'05C. RESTRIÇÕES'!$L$5:$L$204,"VENCIDA")>0," · restrição vencida","") -> futuro | M84: 920 | N84: 3.5.4 | O84: =IF(COUNTIFS('05B. APONTAMENTO DIÁRIO'!$B$5:$B$1004,"342",'05B. APONTAMENTO DIÁRIO'!$C$5:$C$1004,$A84,'05B. APONTAMENTO DIÁRIO'!$A$5:$A$1004,"<="&DATA_GESTAO)=0,"sem apontamento",IF(COUNTIFS('05B. APONTAMENTO DIÁRIO'!$B$5:$B$1004,"342",'05B. APONTAMENTO DIÁRIO'!$C$5:$C$1004,$A84,'05B. APONTAMENTO DIÁRIO'!$A$5:$A$1004,"<="&DATA_GESTAO,'05B. APONTAMENTO DIÁRIO'!$G$5:$G$1004,"m²")=0,"unidade diferente",SUMIFS('05B. APONTAMENTO DIÁRIO'!$F$5:$F$1004,'05B. APONTAMENTO DIÁRIO'!$B$5:$B$1004,"342",'05B. APONTAMENTO DIÁRIO'!$C$5:$C$1004,$A84,'05B. APONTAMENTO DIÁRIO'!$A$5:$A$1004,"<="&DATA_GESTAO,'05B. APONTAMENTO DIÁRIO'!$G$5:$G$1004,"m²")/$M84)) -> sem apontamento | P84: PENDENTE | Q84: a definir com a fiscalização (quantidade da aba 37: 920 m²) | AG84: a definir com a fiscalização
A85: 3.5.6 | B85: 342 | C85: Tanque: instalações hidráulicas | D85: 342-07 | E85: UN: só na conclusão | F85: 539524.73 | G85: 46483 | H85: 46493 | I85: 46497 | J85: =H85-G85+1 -> 11 | K85: =COUNTIFS('05C. RESTRIÇÕES'!$B$5:$B$204,"342",'05C. RESTRIÇÕES'!$C$5:$C$204,A85,'05C. RESTRIÇÕES'!$H$5:$H$204,"ABERTA") -> 1 | L85: =IF(ISNUMBER(P85),"aceito",IF(H85<DATA_GESTAO,"devia estar concluído",IF(G85<=DATA_GESTAO,"em execução",IF(G85-DATA_GESTAO<=42,"começa em até 6 semanas","futuro"))))&IF(COUNTIFS('05C. RESTRIÇÕES'!$B$5:$B$204,"342",'05C. RESTRIÇÕES'!$C$5:$C$204,A85,'05C. RESTRIÇÕES'!$L$5:$L$204,"VENCIDA")>0," · restrição vencida","") -> futuro | M85: 1 | N85: 3.5.3 | O85: =IF(COUNTIFS('05B. APONTAMENTO DIÁRIO'!$B$5:$B$1004,"342",'05B. APONTAMENTO DIÁRIO'!$C$5:$C$1004,$A85,'05B. APONTAMENTO DIÁRIO'!$A$5:$A$1004,"<="&DATA_GESTAO)=0,"sem apontamento",IF(COUNTIFS('05B. APONTAMENTO DIÁRIO'!$B$5:$B$1004,"342",'05B. APONTAMENTO DIÁRIO'!$C$5:$C$1004,$A85,'05B. APONTAMENTO DIÁRIO'!$A$5:$A$1004,"<="&DATA_GESTAO,'05B. APONTAMENTO DIÁRIO'!$G$5:$G$1004,"un")=0,"unidade diferente",SUMIFS('05B. APONTAMENTO DIÁRIO'!$F$5:$F$1004,'05B. APONTAMENTO DIÁRIO'!$B$5:$B$1004,"342",'05B. APONTAMENTO DIÁRIO'!$C$5:$C$1004,$A85,'05B. APONTAMENTO DIÁRIO'!$A$5:$A$1004,"<="&DATA_GESTAO,'05B. APONTAMENTO DIÁRIO'!$G$5:$G$1004,"un")/$M85)) -> sem apontamento | P85: PENDENTE | Q85: instalações montadas e teste de estanqueidade do tanque aprovado (aba 37 ID 30) | AG85: laudo do teste de estanqueidade assinado
A86: 3.5.7 | B86: 342 | C86: Tanque: conclusão e limpeza | D86: 342-07 | E86: UN: só na conclusão | F86: 57448.29 | G86: 46510 | H86: 46518 | I86: 46527 | J86: =H86-G86+1 -> 9 | K86: =COUNTIFS('05C. RESTRIÇÕES'!$B$5:$B$204,"342",'05C. RESTRIÇÕES'!$C$5:$C$204,A86,'05C. RESTRIÇÕES'!$H$5:$H$204,"ABERTA") -> 0 | L86: =IF(ISNUMBER(P86),"aceito",IF(H86<DATA_GESTAO,"devia estar concluído",IF(G86<=DATA_GESTAO,"em execução",IF(G86-DATA_GESTAO<=42,"começa em até 6 semanas","futuro"))))&IF(COUNTIFS('05C. RESTRIÇÕES'!$B$5:$B$204,"342",'05C. RESTRIÇÕES'!$C$5:$C$204,A86,'05C. RESTRIÇÕES'!$L$5:$L$204,"VENCIDA")>0," · restrição vencida","") -> futuro | M86: 698.76 | N86: 3.5.6 | O86: =IF(COUNTIFS('05B. APONTAMENTO DIÁRIO'!$B$5:$B$1004,"342",'05B. APONTAMENTO DIÁRIO'!$C$5:$C$1004,$A86,'05B. APONTAMENTO DIÁRIO'!$A$5:$A$1004,"<="&DATA_GESTAO)=0,"sem apontamento",IF(COUNTIFS('05B. APONTAMENTO DIÁRIO'!$B$5:$B$1004,"342",'05B. APONTAMENTO DIÁRIO'!$C$5:$C$1004,$A86,'05B. APONTAMENTO DIÁRIO'!$A$5:$A$1004,"<="&DATA_GESTAO,'05B. APONTAMENTO DIÁRIO'!$G$5:$G$1004,"m²")=0,"unidade diferente",SUMIFS('05B. APONTAMENTO DIÁRIO'!$F$5:$F$1004,'05B. APONTAMENTO DIÁRIO'!$B$5:$B$1004,"342",'05B. APONTAMENTO DIÁRIO'!$C$5:$C$1004,$A86,'05B. APONTAMENTO DIÁRIO'!$A$5:$A$1004,"<="&DATA_GESTAO,'05B. APONTAMENTO DIÁRIO'!$G$5:$G$1004,"m²")/$M86)) -> sem apontamento | P86: PENDENTE | Q86: a definir com a fiscalização (quantidade da aba 37: 698,76 m²) | AG86: a definir com a fiscalização
A87: 3.6.1 | B87: 342 | C87: Elevatória: serviços preparatórios | D87: 342-08 | E87: UN: só na conclusão | F87: 14403.21 | G87: 46408 | H87: 46419 | I87: 46438 | J87: =H87-G87+1 -> 12 | K87: =COUNTIFS('05C. RESTRIÇÕES'!$B$5:$B$204,"342",'05C. RESTRIÇÕES'!$C$5:$C$204,A87,'05C. RESTRIÇÕES'!$H$5:$H$204,"ABERTA") -> 0 | L87: =IF(ISNUMBER(P87),"aceito",IF(H87<DATA_GESTAO,"devia estar concluído",IF(G87<=DATA_GESTAO,"em execução",IF(G87-DATA_GESTAO<=42,"começa em até 6 semanas","futuro"))))&IF(COUNTIFS('05C. RESTRIÇÕES'!$B$5:$B$204,"342",'05C. RESTRIÇÕES'!$C$5:$C$204,A87,'05C. RESTRIÇÕES'!$L$5:$L$204,"VENCIDA")>0," · restrição vencida","") -> futuro | M87: 602.75 | N87: nenhum | O87: =IF(COUNTIFS('05B. APONTAMENTO DIÁRIO'!$B$5:$B$1004,"342",'05B. APONTAMENTO DIÁRIO'!$C$5:$C$1004,$A87,'05B. APONTAMENTO DIÁRIO'!$A$5:$A$1004,"<="&DATA_GESTAO)=0,"sem apontamento",IF(COUNTIFS('05B. APONTAMENTO DIÁRIO'!$B$5:$B$1004,"342",'05B. APONTAMENTO DIÁRIO'!$C$5:$C$1004,$A87,'05B. APONTAMENTO DIÁRIO'!$A$5:$A$1004,"<="&DATA_GESTAO,'05B. APONTAMENTO DIÁRIO'!$G$5:$G$1004,"m²")=0,"unidade diferente",SUMIFS('05B. APONTAMENTO DIÁRIO'!$F$5:$F$1004,'05B. APONTAMENTO DIÁRIO'!$B$5:$B$1004,"342",'05B. APONTAMENTO DIÁRIO'!$C$5:$C$1004,$A87,'05B. APONTAMENTO DIÁRIO'!$A$5:$A$1004,"<="&DATA_GESTAO,'05B. APONTAMENTO DIÁRIO'!$G$5:$G$1004,"m²")/$M87)) -> sem apontamento | P87: PENDENTE | Q87: a definir com a fiscalização (quantidade da aba 37: 602,75 m²) | AG87: a definir com a fiscalização
A88: 3.6.2 | B88: 342 | C88: Elevatória: estrutura de concreto | D88: 342-08 | E88: %: proporcional | F88: 148031.61 | G88: 46433 | H88: 46448 | I88: 46466 | J88: =H88-G88+1 -> 16 | K88: =COUNTIFS('05C. RESTRIÇÕES'!$B$5:$B$204,"342",'05C. RESTRIÇÕES'!$C$5:$C$204,A88,'05C. RESTRIÇÕES'!$H$5:$H$204,"ABERTA") -> 0 | L88: =IF(ISNUMBER(P88),"aceito",IF(H88<DATA_GESTAO,"devia estar concluído",IF(G88<=DATA_GESTAO,"em execução",IF(G88-DATA_GESTAO<=42,"começa em até 6 semanas","futuro"))))&IF(COUNTIFS('05C. RESTRIÇÕES'!$B$5:$B$204,"342",'05C. RESTRIÇÕES'!$C$5:$C$204,A88,'05C. RESTRIÇÕES'!$L$5:$L$204,"VENCIDA")>0," · restrição vencida","") -> futuro | M88: 51.44 | N88: 3.6.1 | O88: =IF(COUNTIFS('05B. APONTAMENTO DIÁRIO'!$B$5:$B$1004,"342",'05B. APONTAMENTO DIÁRIO'!$C$5:$C$1004,$A88,'05B. APONTAMENTO DIÁRIO'!$A$5:$A$1004,"<="&DATA_GESTAO)=0,"sem apontamento",IF(COUNTIFS('05B. APONTAMENTO DIÁRIO'!$B$5:$B$1004,"342",'05B. APONTAMENTO DIÁRIO'!$C$5:$C$1004,$A88,'05B. APONTAMENTO DIÁRIO'!$A$5:$A$1004,"<="&DATA_GESTAO,'05B. APONTAMENTO DIÁRIO'!$G$5:$G$1004,"m³")=0,"unidade diferente",SUMIFS('05B. APONTAMENTO DIÁRIO'!$F$5:$F$1004,'05B. APONTAMENTO DIÁRIO'!$B$5:$B$1004,"342",'05B. APONTAMENTO DIÁRIO'!$C$5:$C$1004,$A88,'05B. APONTAMENTO DIÁRIO'!$A$5:$A$1004,"<="&DATA_GESTAO,'05B. APONTAMENTO DIÁRIO'!$G$5:$G$1004,"m³")/$M88)) -> sem apontamento | P88: a cada BM (06) | Q88: medição proporcional no BM | AG88: BM aprovado (06)
A89: 3.6.3 | B89: 342 | C89: Elevatória: impermeabilização | D89: 342-08 | E89: UN: só na conclusão | F89: 6973.31 | G89: 46489 | H89: 46496 | I89: 46497 | J89: =H89-G89+1 -> 8 | K89: =COUNTIFS('05C. RESTRIÇÕES'!$B$5:$B$204,"342",'05C. RESTRIÇÕES'!$C$5:$C$204,A89,'05C. RESTRIÇÕES'!$H$5:$H$204,"ABERTA") -> 0 | L89: =IF(ISNUMBER(P89),"aceito",IF(H89<DATA_GESTAO,"devia estar concluído",IF(G89<=DATA_GESTAO,"em execução",IF(G89-DATA_GESTAO<=42,"começa em até 6 semanas","futuro"))))&IF(COUNTIFS('05C. RESTRIÇÕES'!$B$5:$B$204,"342",'05C. RESTRIÇÕES'!$C$5:$C$204,A89,'05C. RESTRIÇÕES'!$L$5:$L$204,"VENCIDA")>0," · restrição vencida","") -> futuro | M89: 153.61 | N89: nenhum | O89: =IF(COUNTIFS('05B. APONTAMENTO DIÁRIO'!$B$5:$B$1004,"342",'05B. APONTAMENTO DIÁRIO'!$C$5:$C$1004,$A89,'05B. APONTAMENTO DIÁRIO'!$A$5:$A$1004,"<="&DATA_GESTAO)=0,"sem apontamento",IF(COUNTIFS('05B. APONTAMENTO DIÁRIO'!$B$5:$B$1004,"342",'05B. APONTAMENTO DIÁRIO'!$C$5:$C$1004,$A89,'05B. APONTAMENTO DIÁRIO'!$A$5:$A$1004,"<="&DATA_GESTAO,'05B. APONTAMENTO DIÁRIO'!$G$5:$G$1004,"m²")=0,"unidade diferente",SUMIFS('05B. APONTAMENTO DIÁRIO'!$F$5:$F$1004,'05B. APONTAMENTO DIÁRIO'!$B$5:$B$1004,"342",'05B. APONTAMENTO DIÁRIO'!$C$5:$C$1004,$A89,'05B. APONTAMENTO DIÁRIO'!$A$5:$A$1004,"<="&DATA_GESTAO,'05B. APONTAMENTO DIÁRIO'!$G$5:$G$1004,"m²")/$M89)) -> sem apontamento | P89: PENDENTE | Q89: a definir com a fiscalização (quantidade da aba 37: 153,61 m²) | AG89: a definir com a fiscalização
A90: 3.6.4 | B90: 342 | C90: Elevatória: manta geotêxtil | D90: 342-08 | E90: UN: só na conclusão | F90: 2438.24 | G90: 46489 | H90: 46489 | I90: 46497 | J90: =H90-G90+1 -> 1 | K90: =COUNTIFS('05C. RESTRIÇÕES'!$B$5:$B$204,"342",'05C. RESTRIÇÕES'!$C$5:$C$204,A90,'05C. RESTRIÇÕES'!$H$5:$H$204,"ABERTA") -> 0 | L90: =IF(ISNUMBER(P90),"aceito",IF(H90<DATA_GESTAO,"devia estar concluído",IF(G90<=DATA_GESTAO,"em execução",IF(G90-DATA_GESTAO<=42,"começa em até 6 semanas","futuro"))))&IF(COUNTIFS('05C. RESTRIÇÕES'!$B$5:$B$204,"342",'05C. RESTRIÇÕES'!$C$5:$C$204,A90,'05C. RESTRIÇÕES'!$L$5:$L$204,"VENCIDA")>0," · restrição vencida","") -> futuro | M90: 89.34 | N90: nenhum | O90: =IF(COUNTIFS('05B. APONTAMENTO DIÁRIO'!$B$5:$B$1004,"342",'05B. APONTAMENTO DIÁRIO'!$C$5:$C$1004,$A90,'05B. APONTAMENTO DIÁRIO'!$A$5:$A$1004,"<="&DATA_GESTAO)=0,"sem apontamento",IF(COUNTIFS('05B. APONTAMENTO DIÁRIO'!$B$5:$B$1004,"342",'05B. APONTAMENTO DIÁRIO'!$C$5:$C$1004,$A90,'05B. APONTAMENTO DIÁRIO'!$A$5:$A$1004,"<="&DATA_GESTAO,'05B. APONTAMENTO DIÁRIO'!$G$5:$G$1004,"m²")=0,"unidade diferente",SUMIFS('05B. APONTAMENTO DIÁRIO'!$F$5:$F$1004,'05B. APONTAMENTO DIÁRIO'!$B$5:$B$1004,"342",'05B. APONTAMENTO DIÁRIO'!$C$5:$C$1004,$A90,'05B. APONTAMENTO DIÁRIO'!$A$5:$A$1004,"<="&DATA_GESTAO,'05B. APONTAMENTO DIÁRIO'!$G$5:$G$1004,"m²")/$M90)) -> sem apontamento | P90: PENDENTE | Q90: a definir com a fiscalização (quantidade da aba 37: 89,34 m²) | AG90: a definir com a fiscalização
A91: 3.6.5 | B91: 342 | C91: Elevatória: instalações hidráulicas | D91: 342-08 | E91: UN: só na conclusão | F91: 54343.53 | G91: 46503 | H91: 46503 | I91: 46527 | J91: =H91-G91+1 -> 1 | K91: =COUNTIFS('05C. RESTRIÇÕES'!$B$5:$B$204,"342",'05C. RESTRIÇÕES'!$C$5:$C$204,A91,'05C. RESTRIÇÕES'!$H$5:$H$204,"ABERTA") -> 0 | L91: =IF(ISNUMBER(P91),"aceito",IF(H91<DATA_GESTAO,"devia estar concluído",IF(G91<=DATA_GESTAO,"em execução",IF(G91-DATA_GESTAO<=42,"começa em até 6 semanas","futuro"))))&IF(COUNTIFS('05C. RESTRIÇÕES'!$B$5:$B$204,"342",'05C. RESTRIÇÕES'!$C$5:$C$204,A91,'05C. RESTRIÇÕES'!$L$5:$L$204,"VENCIDA")>0," · restrição vencida","") -> futuro | M91: 1 | N91: 3.6.3 | O91: =IF(COUNTIFS('05B. APONTAMENTO DIÁRIO'!$B$5:$B$1004,"342",'05B. APONTAMENTO DIÁRIO'!$C$5:$C$1004,$A91,'05B. APONTAMENTO DIÁRIO'!$A$5:$A$1004,"<="&DATA_GESTAO)=0,"sem apontamento",IF(COUNTIFS('05B. APONTAMENTO DIÁRIO'!$B$5:$B$1004,"342",'05B. APONTAMENTO DIÁRIO'!$C$5:$C$1004,$A91,'05B. APONTAMENTO DIÁRIO'!$A$5:$A$1004,"<="&DATA_GESTAO,'05B. APONTAMENTO DIÁRIO'!$G$5:$G$1004,"un")=0,"unidade diferente",SUMIFS('05B. APONTAMENTO DIÁRIO'!$F$5:$F$1004,'05B. APONTAMENTO DIÁRIO'!$B$5:$B$1004,"342",'05B. APONTAMENTO DIÁRIO'!$C$5:$C$1004,$A91,'05B. APONTAMENTO DIÁRIO'!$A$5:$A$1004,"<="&DATA_GESTAO,'05B. APONTAMENTO DIÁRIO'!$G$5:$G$1004,"un")/$M91)) -> sem apontamento | P91: PENDENTE | Q91: a definir com a fiscalização (quantidade da aba 37: 1 un) | AG91: a definir com a fiscalização
A92: 3.6.6 | B92: 342 | C92: Guindaste giratório de coluna | D92: 342-08 | E92: UN: só na conclusão | F92: 92956.69 | G92: 46510 | H92: 46527 | I92: 46527 | J92: =H92-G92+1 -> 18 | K92: =COUNTIFS('05C. RESTRIÇÕES'!$B$5:$B$204,"342",'05C. RESTRIÇÕES'!$C$5:$C$204,A92,'05C. RESTRIÇÕES'!$H$5:$H$204,"ABERTA") -> 1 | L92: =IF(ISNUMBER(P92),"aceito",IF(H92<DATA_GESTAO,"devia estar concluído",IF(G92<=DATA_GESTAO,"em execução",IF(G92-DATA_GESTAO<=42,"começa em até 6 semanas","futuro"))))&IF(COUNTIFS('05C. RESTRIÇÕES'!$B$5:$B$204,"342",'05C. RESTRIÇÕES'!$C$5:$C$204,A92,'05C. RESTRIÇÕES'!$L$5:$L$204,"VENCIDA")>0," · restrição vencida","") -> futuro | M92: 1 | N92: nenhum | O92: =IF(COUNTIFS('05B. APONTAMENTO DIÁRIO'!$B$5:$B$1004,"342",'05B. APONTAMENTO DIÁRIO'!$C$5:$C$1004,$A92,'05B. APONTAMENTO DIÁRIO'!$A$5:$A$1004,"<="&DATA_GESTAO)=0,"sem apontamento",IF(COUNTIFS('05B. APONTAMENTO DIÁRIO'!$B$5:$B$1004,"342",'05B. APONTAMENTO DIÁRIO'!$C$5:$C$1004,$A92,'05B. APONTAMENTO DIÁRIO'!$A$5:$A$1004,"<="&DATA_GESTAO,'05B. APONTAMENTO DIÁRIO'!$G$5:$G$1004,"un")=0,"unidade diferente",SUMIFS('05B. APONTAMENTO DIÁRIO'!$F$5:$F$1004,'05B. APONTAMENTO DIÁRIO'!$B$5:$B$1004,"342",'05B. APONTAMENTO DIÁRIO'!$C$5:$C$1004,$A92,'05B. APONTAMENTO DIÁRIO'!$A$5:$A$1004,"<="&DATA_GESTAO,'05B. APONTAMENTO DIÁRIO'!$G$5:$G$1004,"un")/$M92)) -> sem apontamento | P92: PENDENTE | Q92: a definir com a fiscalização (quantidade da aba 37: 1 un) | AG92: a definir com a fiscalização
A93: 3.6.7 | B93: 342 | C93: Conjuntos motor-bomba | D93: 342-08 | E93: UN: só na conclusão | F93: 196129.57 | G93: 46528 | H93: 46528 | I93: 46558 | J93: =H93-G93+1 -> 1 | K93: =COUNTIFS('05C. RESTRIÇÕES'!$B$5:$B$204,"342",'05C. RESTRIÇÕES'!$C$5:$C$204,A93,'05C. RESTRIÇÕES'!$H$5:$H$204,"ABERTA") -> 2 | L93: =IF(ISNUMBER(P93),"aceito",IF(H93<DATA_GESTAO,"devia estar concluído",IF(G93<=DATA_GESTAO,"em execução",IF(G93-DATA_GESTAO<=42,"começa em até 6 semanas","futuro"))))&IF(COUNTIFS('05C. RESTRIÇÕES'!$B$5:$B$204,"342",'05C. RESTRIÇÕES'!$C$5:$C$204,A93,'05C. RESTRIÇÕES'!$L$5:$L$204,"VENCIDA")>0," · restrição vencida","") -> futuro | M93: 2 | N93: 3.6.6 | O93: =IF(COUNTIFS('05B. APONTAMENTO DIÁRIO'!$B$5:$B$1004,"342",'05B. APONTAMENTO DIÁRIO'!$C$5:$C$1004,$A93,'05B. APONTAMENTO DIÁRIO'!$A$5:$A$1004,"<="&DATA_GESTAO)=0,"sem apontamento",IF(COUNTIFS('05B. APONTAMENTO DIÁRIO'!$B$5:$B$1004,"342",'05B. APONTAMENTO DIÁRIO'!$C$5:$C$1004,$A93,'05B. APONTAMENTO DIÁRIO'!$A$5:$A$1004,"<="&DATA_GESTAO,'05B. APONTAMENTO DIÁRIO'!$G$5:$G$1004,"un")=0,"unidade diferente",SUMIFS('05B. APONTAMENTO DIÁRIO'!$F$5:$F$1004,'05B. APONTAMENTO DIÁRIO'!$B$5:$B$1004,"342",'05B. APONTAMENTO DIÁRIO'!$C$5:$C$1004,$A93,'05B. APONTAMENTO DIÁRIO'!$A$5:$A$1004,"<="&DATA_GESTAO,'05B. APONTAMENTO DIÁRIO'!$G$5:$G$1004,"un")/$M93)) -> sem apontamento | P93: PENDENTE | Q93: 2 conjuntos montados e comissionados (aba 37 ID 33; Anexo VII p.3) | AG93: relatório de comissionamento assinado
A94: 3.6.8 | B94: 342 | C94: Elevatória: conclusão e limpeza | D94: 342-08 | E94: UN: só na conclusão | F94: 15511.1 | G94: 46545 | H94: 46549 | I94: 46558 | J94: =H94-G94+1 -> 5 | K94: =COUNTIFS('05C. RESTRIÇÕES'!$B$5:$B$204,"342",'05C. RESTRIÇÕES'!$C$5:$C$204,A94,'05C. RESTRIÇÕES'!$H$5:$H$204,"ABERTA") -> 0 | L94: =IF(ISNUMBER(P94),"aceito",IF(H94<DATA_GESTAO,"devia estar concluído",IF(G94<=DATA_GESTAO,"em execução",IF(G94-DATA_GESTAO<=42,"começa em até 6 semanas","futuro"))))&IF(COUNTIFS('05C. RESTRIÇÕES'!$B$5:$B$204,"342",'05C. RESTRIÇÕES'!$C$5:$C$204,A94,'05C. RESTRIÇÕES'!$L$5:$L$204,"VENCIDA")>0," · restrição vencida","") -> futuro | M94: 1 | N94: 3.6.7 | O94: =IF(COUNTIFS('05B. APONTAMENTO DIÁRIO'!$B$5:$B$1004,"342",'05B. APONTAMENTO DIÁRIO'!$C$5:$C$1004,$A94,'05B. APONTAMENTO DIÁRIO'!$A$5:$A$1004,"<="&DATA_GESTAO)=0,"sem apontamento",IF(COUNTIFS('05B. APONTAMENTO DIÁRIO'!$B$5:$B$1004,"342",'05B. APONTAMENTO DIÁRIO'!$C$5:$C$1004,$A94,'05B. APONTAMENTO DIÁRIO'!$A$5:$A$1004,"<="&DATA_GESTAO,'05B. APONTAMENTO DIÁRIO'!$G$5:$G$1004,"vb")=0,"unidade diferente",SUMIFS('05B. APONTAMENTO DIÁRIO'!$F$5:$F$1004,'05B. APONTAMENTO DIÁRIO'!$B$5:$B$1004,"342",'05B. APONTAMENTO DIÁRIO'!$C$5:$C$1004,$A94,'05B. APONTAMENTO DIÁRIO'!$A$5:$A$1004,"<="&DATA_GESTAO,'05B. APONTAMENTO DIÁRIO'!$G$5:$G$1004,"vb")/$M94)) -> sem apontamento | P94: PENDENTE | Q94: a definir com a fiscalização (quantidade da aba 37: 1 vb) | AG94: a definir com a fiscalização
A95: 3.7.2 | B95: 342 | C95: Cerca padrão Saneago | D95: 342-09 | E95: UN: só na conclusão | F95: 38662.82 | G95: 46526 | H95: 46546 | I95: 46558 | J95: =H95-G95+1 -> 21 | K95: =COUNTIFS('05C. RESTRIÇÕES'!$B$5:$B$204,"342",'05C. RESTRIÇÕES'!$C$5:$C$204,A95,'05C. RESTRIÇÕES'!$H$5:$H$204,"ABERTA") -> 1 | L95: =IF(ISNUMBER(P95),"aceito",IF(H95<DATA_GESTAO,"devia estar concluído",IF(G95<=DATA_GESTAO,"em execução",IF(G95-DATA_GESTAO<=42,"começa em até 6 semanas","futuro"))))&IF(COUNTIFS('05C. RESTRIÇÕES'!$B$5:$B$204,"342",'05C. RESTRIÇÕES'!$C$5:$C$204,A95,'05C. RESTRIÇÕES'!$L$5:$L$204,"VENCIDA")>0," · restrição vencida","") -> futuro | M95: 208.42 | N95: nenhum | O95: =IF(COUNTIFS('05B. APONTAMENTO DIÁRIO'!$B$5:$B$1004,"342",'05B. APONTAMENTO DIÁRIO'!$C$5:$C$1004,$A95,'05B. APONTAMENTO DIÁRIO'!$A$5:$A$1004,"<="&DATA_GESTAO)=0,"sem apontamento",IF(COUNTIFS('05B. APONTAMENTO DIÁRIO'!$B$5:$B$1004,"342",'05B. APONTAMENTO DIÁRIO'!$C$5:$C$1004,$A95,'05B. APONTAMENTO DIÁRIO'!$A$5:$A$1004,"<="&DATA_GESTAO,'05B. APONTAMENTO DIÁRIO'!$G$5:$G$1004,"m")=0,"unidade diferente",SUMIFS('05B. APONTAMENTO DIÁRIO'!$F$5:$F$1004,'05B. APONTAMENTO DIÁRIO'!$B$5:$B$1004,"342",'05B. APONTAMENTO DIÁRIO'!$C$5:$C$1004,$A95,'05B. APONTAMENTO DIÁRIO'!$A$5:$A$1004,"<="&DATA_GESTAO,'05B. APONTAMENTO DIÁRIO'!$G$5:$G$1004,"m")/$M95)) -> sem apontamento | P95: PENDENTE | Q95: a definir com a fiscalização (quantidade da aba 37: 208,42 m) | AG95: a definir com a fiscalização
A96: 3.7.3 | B96: 342 | C96: Calçada em bloco hexagonal | D96: 342-09 | E96: UN: só na conclusão | F96: 84972.48 | G96: 46541 | H96: 46552 | I96: 46558 | J96: =H96-G96+1 -> 12 | K96: =COUNTIFS('05C. RESTRIÇÕES'!$B$5:$B$204,"342",'05C. RESTRIÇÕES'!$C$5:$C$204,A96,'05C. RESTRIÇÕES'!$H$5:$H$204,"ABERTA") -> 0 | L96: =IF(ISNUMBER(P96),"aceito",IF(H96<DATA_GESTAO,"devia estar concluído",IF(G96<=DATA_GESTAO,"em execução",IF(G96-DATA_GESTAO<=42,"começa em até 6 semanas","futuro"))))&IF(COUNTIFS('05C. RESTRIÇÕES'!$B$5:$B$204,"342",'05C. RESTRIÇÕES'!$C$5:$C$204,A96,'05C. RESTRIÇÕES'!$L$5:$L$204,"VENCIDA")>0," · restrição vencida","") -> futuro | M96: 997.72 | N96: nenhum | O96: =IF(COUNTIFS('05B. APONTAMENTO DIÁRIO'!$B$5:$B$1004,"342",'05B. APONTAMENTO DIÁRIO'!$C$5:$C$1004,$A96,'05B. APONTAMENTO DIÁRIO'!$A$5:$A$1004,"<="&DATA_GESTAO)=0,"sem apontamento",IF(COUNTIFS('05B. APONTAMENTO DIÁRIO'!$B$5:$B$1004,"342",'05B. APONTAMENTO DIÁRIO'!$C$5:$C$1004,$A96,'05B. APONTAMENTO DIÁRIO'!$A$5:$A$1004,"<="&DATA_GESTAO,'05B. APONTAMENTO DIÁRIO'!$G$5:$G$1004,"m²")=0,"unidade diferente",SUMIFS('05B. APONTAMENTO DIÁRIO'!$F$5:$F$1004,'05B. APONTAMENTO DIÁRIO'!$B$5:$B$1004,"342",'05B. APONTAMENTO DIÁRIO'!$C$5:$C$1004,$A96,'05B. APONTAMENTO DIÁRIO'!$A$5:$A$1004,"<="&DATA_GESTAO,'05B. APONTAMENTO DIÁRIO'!$G$5:$G$1004,"m²")/$M96)) -> sem apontamento | P96: PENDENTE | Q96: a definir com a fiscalização (quantidade da aba 37: 997,72 m²) | AG96: a definir com a fiscalização
A97: 3.7.4 | B97: 342 | C97: Meio-fio | D97: 342-09 | E97: UN: só na conclusão | F97: 31185.55 | G97: 46552 | H97: 46562 | I97: 46588 | J97: =H97-G97+1 -> 11 | K97: =COUNTIFS('05C. RESTRIÇÕES'!$B$5:$B$204,"342",'05C. RESTRIÇÕES'!$C$5:$C$204,A97,'05C. RESTRIÇÕES'!$H$5:$H$204,"ABERTA") -> 0 | L97: =IF(ISNUMBER(P97),"aceito",IF(H97<DATA_GESTAO,"devia estar concluído",IF(G97<=DATA_GESTAO,"em execução",IF(G97-DATA_GESTAO<=42,"começa em até 6 semanas","futuro"))))&IF(COUNTIFS('05C. RESTRIÇÕES'!$B$5:$B$204,"342",'05C. RESTRIÇÕES'!$C$5:$C$204,A97,'05C. RESTRIÇÕES'!$L$5:$L$204,"VENCIDA")>0," · restrição vencida","") -> futuro | M97: 523.36 | N97: nenhum | O97: =IF(COUNTIFS('05B. APONTAMENTO DIÁRIO'!$B$5:$B$1004,"342",'05B. APONTAMENTO DIÁRIO'!$C$5:$C$1004,$A97,'05B. APONTAMENTO DIÁRIO'!$A$5:$A$1004,"<="&DATA_GESTAO)=0,"sem apontamento",IF(COUNTIFS('05B. APONTAMENTO DIÁRIO'!$B$5:$B$1004,"342",'05B. APONTAMENTO DIÁRIO'!$C$5:$C$1004,$A97,'05B. APONTAMENTO DIÁRIO'!$A$5:$A$1004,"<="&DATA_GESTAO,'05B. APONTAMENTO DIÁRIO'!$G$5:$G$1004,"m")=0,"unidade diferente",SUMIFS('05B. APONTAMENTO DIÁRIO'!$F$5:$F$1004,'05B. APONTAMENTO DIÁRIO'!$B$5:$B$1004,"342",'05B. APONTAMENTO DIÁRIO'!$C$5:$C$1004,$A97,'05B. APONTAMENTO DIÁRIO'!$A$5:$A$1004,"<="&DATA_GESTAO,'05B. APONTAMENTO DIÁRIO'!$G$5:$G$1004,"m")/$M97)) -> sem apontamento | P97: PENDENTE | Q97: a definir com a fiscalização (quantidade da aba 37: 523,36 m) | AG97: a definir com a fiscalização
A98: 3.7.5 | B98: 342 | C98: Grama | D98: 342-09 | E98: UN: só na conclusão | F98: 54026.59 | G98: 46576 | H98: 46589 | I98: 46619 | J98: =H98-G98+1 -> 14 | K98: =COUNTIFS('05C. RESTRIÇÕES'!$B$5:$B$204,"342",'05C. RESTRIÇÕES'!$C$5:$C$204,A98,'05C. RESTRIÇÕES'!$H$5:$H$204,"ABERTA") -> 0 | L98: =IF(ISNUMBER(P98),"aceito",IF(H98<DATA_GESTAO,"devia estar concluído",IF(G98<=DATA_GESTAO,"em execução",IF(G98-DATA_GESTAO<=42,"começa em até 6 semanas","futuro"))))&IF(COUNTIFS('05C. RESTRIÇÕES'!$B$5:$B$204,"342",'05C. RESTRIÇÕES'!$C$5:$C$204,A98,'05C. RESTRIÇÕES'!$L$5:$L$204,"VENCIDA")>0," · restrição vencida","") -> futuro | M98: 2452.02 | N98: 3.7.4 | O98: =IF(COUNTIFS('05B. APONTAMENTO DIÁRIO'!$B$5:$B$1004,"342",'05B. APONTAMENTO DIÁRIO'!$C$5:$C$1004,$A98,'05B. APONTAMENTO DIÁRIO'!$A$5:$A$1004,"<="&DATA_GESTAO)=0,"sem apontamento",IF(COUNTIFS('05B. APONTAMENTO DIÁRIO'!$B$5:$B$1004,"342",'05B. APONTAMENTO DIÁRIO'!$C$5:$C$1004,$A98,'05B. APONTAMENTO DIÁRIO'!$A$5:$A$1004,"<="&DATA_GESTAO,'05B. APONTAMENTO DIÁRIO'!$G$5:$G$1004,"m²")=0,"unidade diferente",SUMIFS('05B. APONTAMENTO DIÁRIO'!$F$5:$F$1004,'05B. APONTAMENTO DIÁRIO'!$B$5:$B$1004,"342",'05B. APONTAMENTO DIÁRIO'!$C$5:$C$1004,$A98,'05B. APONTAMENTO DIÁRIO'!$A$5:$A$1004,"<="&DATA_GESTAO,'05B. APONTAMENTO DIÁRIO'!$G$5:$G$1004,"m²")/$M98)) -> sem apontamento | P98: PENDENTE | Q98: a definir com a fiscalização (quantidade da aba 37: 2452,02 m²) | AG98: a definir com a fiscalização
A99: 3.7.6 | B99: 342 | C99: Portão padrão | D99: 342-09 | E99: UN: só na conclusão | F99: 7547.87 | G99: 46581 | H99: 46582 | I99: 46588 | J99: =H99-G99+1 -> 2 | K99: =COUNTIFS('05C. RESTRIÇÕES'!$B$5:$B$204,"342",'05C. RESTRIÇÕES'!$C$5:$C$204,A99,'05C. RESTRIÇÕES'!$H$5:$H$204,"ABERTA") -> 0 | L99: =IF(ISNUMBER(P99),"aceito",IF(H99<DATA_GESTAO,"devia estar concluído",IF(G99<=DATA_GESTAO,"em execução",IF(G99-DATA_GESTAO<=42,"começa em até 6 semanas","futuro"))))&IF(COUNTIFS('05C. RESTRIÇÕES'!$B$5:$B$204,"342",'05C. RESTRIÇÕES'!$C$5:$C$204,A99,'05C. RESTRIÇÕES'!$L$5:$L$204,"VENCIDA")>0," · restrição vencida","") -> futuro | M99: 1 | N99: nenhum | O99: =IF(COUNTIFS('05B. APONTAMENTO DIÁRIO'!$B$5:$B$1004,"342",'05B. APONTAMENTO DIÁRIO'!$C$5:$C$1004,$A99,'05B. APONTAMENTO DIÁRIO'!$A$5:$A$1004,"<="&DATA_GESTAO)=0,"sem apontamento",IF(COUNTIFS('05B. APONTAMENTO DIÁRIO'!$B$5:$B$1004,"342",'05B. APONTAMENTO DIÁRIO'!$C$5:$C$1004,$A99,'05B. APONTAMENTO DIÁRIO'!$A$5:$A$1004,"<="&DATA_GESTAO,'05B. APONTAMENTO DIÁRIO'!$G$5:$G$1004,"un")=0,"unidade diferente",SUMIFS('05B. APONTAMENTO DIÁRIO'!$F$5:$F$1004,'05B. APONTAMENTO DIÁRIO'!$B$5:$B$1004,"342",'05B. APONTAMENTO DIÁRIO'!$C$5:$C$1004,$A99,'05B. APONTAMENTO DIÁRIO'!$A$5:$A$1004,"<="&DATA_GESTAO,'05B. APONTAMENTO DIÁRIO'!$G$5:$G$1004,"un")/$M99)) -> sem apontamento | P99: PENDENTE | Q99: a definir com a fiscalização (quantidade da aba 37: 1 un) | AG99: a definir com a fiscalização
A100: 3.7.7 | B100: 342 | C100: Urbanização: conclusão e limpeza | D100: 342-09 | E100: UN: só na conclusão | F100: 2242.43 | G100: 46561 | H100: 46563 | I100: 46588 | J100: =H100-G100+1 -> 3 | K100: =COUNTIFS('05C. RESTRIÇÕES'!$B$5:$B$204,"342",'05C. RESTRIÇÕES'!$C$5:$C$204,A100,'05C. RESTRIÇÕES'!$H$5:$H$204,"ABERTA") -> 0 | L100: =IF(ISNUMBER(P100),"aceito",IF(H100<DATA_GESTAO,"devia estar concluído",IF(G100<=DATA_GESTAO,"em execução",IF(G100-DATA_GESTAO<=42,"começa em até 6 semanas","futuro"))))&IF(COUNTIFS('05C. RESTRIÇÕES'!$B$5:$B$204,"342",'05C. RESTRIÇÕES'!$C$5:$C$204,A100,'05C. RESTRIÇÕES'!$L$5:$L$204,"VENCIDA")>0," · restrição vencida","") -> futuro | M100: 997.72 | N100: nenhum | O100: =IF(COUNTIFS('05B. APONTAMENTO DIÁRIO'!$B$5:$B$1004,"342",'05B. APONTAMENTO DIÁRIO'!$C$5:$C$1004,$A100,'05B. APONTAMENTO DIÁRIO'!$A$5:$A$1004,"<="&DATA_GESTAO)=0,"sem apontamento",IF(COUNTIFS('05B. APONTAMENTO DIÁRIO'!$B$5:$B$1004,"342",'05B. APONTAMENTO DIÁRIO'!$C$5:$C$1004,$A100,'05B. APONTAMENTO DIÁRIO'!$A$5:$A$1004,"<="&DATA_GESTAO,'05B. APONTAMENTO DIÁRIO'!$G$5:$G$1004,"m²")=0,"unidade diferente",SUMIFS('05B. APONTAMENTO DIÁRIO'!$F$5:$F$1004,'05B. APONTAMENTO DIÁRIO'!$B$5:$B$1004,"342",'05B. APONTAMENTO DIÁRIO'!$C$5:$C$1004,$A100,'05B. APONTAMENTO DIÁRIO'!$A$5:$A$1004,"<="&DATA_GESTAO,'05B. APONTAMENTO DIÁRIO'!$G$5:$G$1004,"m²")/$M100)) -> sem apontamento | P100: PENDENTE | Q100: a definir com a fiscalização (quantidade da aba 37: 997,72 m²) | AG100: a definir com a fiscalização
A101: 3.8.1 | B101: 342 | C101: Rede de distribuição de energia | D101: 342-10 | E101: UN: só na conclusão | F101: 104799.22 | G101: 46433 | H101: 46449 | I101: 46466 | J101: =H101-G101+1 -> 17 | K101: =COUNTIFS('05C. RESTRIÇÕES'!$B$5:$B$204,"342",'05C. RESTRIÇÕES'!$C$5:$C$204,A101,'05C. RESTRIÇÕES'!$H$5:$H$204,"ABERTA") -> 3 | L101: =IF(ISNUMBER(P101),"aceito",IF(H101<DATA_GESTAO,"devia estar concluído",IF(G101<=DATA_GESTAO,"em execução",IF(G101-DATA_GESTAO<=42,"começa em até 6 semanas","futuro"))))&IF(COUNTIFS('05C. RESTRIÇÕES'!$B$5:$B$204,"342",'05C. RESTRIÇÕES'!$C$5:$C$204,A101,'05C. RESTRIÇÕES'!$L$5:$L$204,"VENCIDA")>0," · restrição vencida","") -> futuro | M101: 1 | N101: nenhum | O101: =IF(COUNTIFS('05B. APONTAMENTO DIÁRIO'!$B$5:$B$1004,"342",'05B. APONTAMENTO DIÁRIO'!$C$5:$C$1004,$A101,'05B. APONTAMENTO DIÁRIO'!$A$5:$A$1004,"<="&DATA_GESTAO)=0,"sem apontamento",IF(COUNTIFS('05B. APONTAMENTO DIÁRIO'!$B$5:$B$1004,"342",'05B. APONTAMENTO DIÁRIO'!$C$5:$C$1004,$A101,'05B. APONTAMENTO DIÁRIO'!$A$5:$A$1004,"<="&DATA_GESTAO,'05B. APONTAMENTO DIÁRIO'!$G$5:$G$1004,"vb")=0,"unidade diferente",SUMIFS('05B. APONTAMENTO DIÁRIO'!$F$5:$F$1004,'05B. APONTAMENTO DIÁRIO'!$B$5:$B$1004,"342",'05B. APONTAMENTO DIÁRIO'!$C$5:$C$1004,$A101,'05B. APONTAMENTO DIÁRIO'!$A$5:$A$1004,"<="&DATA_GESTAO,'05B. APONTAMENTO DIÁRIO'!$G$5:$G$1004,"vb")/$M101)) -> sem apontamento | P101: PENDENTE | Q101: rede montada, ensaios a frio com laudo e ART (aba 37 ID 31; Anexo VII p.12) | AG101: laudo dos ensaios e ART
A102: 4.1.1 | B102: 342 | C102: Projetos: parcela proporcional | D102: 342-11 | E102: %: proporcional | F102: 25160.99 | G102: 46268 | H102: 46329 | I102: 46346 | J102: =H102-G102+1 -> 62 | K102: =COUNTIFS('05C. RESTRIÇÕES'!$B$5:$B$204,"342",'05C. RESTRIÇÕES'!$C$5:$C$204,A102,'05C. RESTRIÇÕES'!$H$5:$H$204,"ABERTA") -> 2 | L102: =IF(ISNUMBER(P102),"aceito",IF(H102<DATA_GESTAO,"devia estar concluído",IF(G102<=DATA_GESTAO,"em execução",IF(G102-DATA_GESTAO<=42,"começa em até 6 semanas","futuro"))))&IF(COUNTIFS('05C. RESTRIÇÕES'!$B$5:$B$204,"342",'05C. RESTRIÇÕES'!$C$5:$C$204,A102,'05C. RESTRIÇÕES'!$L$5:$L$204,"VENCIDA")>0," · restrição vencida","") -> em execução · restrição vencida | M102: 1 | N102: nenhum | O102: proporcional ao BM | P102: a cada BM (06) | Q102: medição proporcional no BM | AG102: BM aprovado (06)
A103: 4.1.2 | B103: 342 | C103: Entrega definitiva e aprovação do as built | D103: 342-11 | E103: UN: só na conclusão | F103: 2795.67 | G103: 46626 | H103: 46626 | I103: 46650 | J103: =H103-G103+1 -> 1 | K103: =COUNTIFS('05C. RESTRIÇÕES'!$B$5:$B$204,"342",'05C. RESTRIÇÕES'!$C$5:$C$204,A103,'05C. RESTRIÇÕES'!$H$5:$H$204,"ABERTA") -> 0 | L103: =IF(ISNUMBER(P103),"aceito",IF(H103<DATA_GESTAO,"devia estar concluído",IF(G103<=DATA_GESTAO,"em execução",IF(G103-DATA_GESTAO<=42,"começa em até 6 semanas","futuro"))))&IF(COUNTIFS('05C. RESTRIÇÕES'!$B$5:$B$204,"342",'05C. RESTRIÇÕES'!$C$5:$C$204,A103,'05C. RESTRIÇÕES'!$L$5:$L$204,"VENCIDA")>0," · restrição vencida","") -> futuro | M103: SEM BASE | N103: SEM BASE | O103: SEM BASE | P103: PENDENTE | Q103: as built entregue e aprovado pela fiscalização | AG103: termo de aprovação do as built
C104: Total dos eventos | F104: =SUM(F74:F103) -> 3257970.7 | G104: =_xlfn.MINIFS(G74:G103,B74:B103,"342") -> 46268 | H104: =_xlfn.MAXIFS(H74:H103,B74:B103,"342") -> 46626
C105: Contrato menos eventos (arredondamento dos pesos, R$) | F105: ='03. CONTRATOS'!$B$8-F104 -> 29.26
A107: MARCOS DO FIM DA 342 (estudo REV13, aba 37; contrato, cláusula sexta)
...

Sheet HISTOGRAMA PLANEJADO
A2: HISTOGRAMA PLANEJADO: efetivo e custo de mão de obra + equipamentos, por mês e por semana
A3: Valores copiados do estudo (planejamento, não apontamento). As colunas amarelas são do realizado: ficam vazias até o apontamento começar, e vazio não é zero (o desvio só aparece quando há realizado).
A4: Fonte: 342 = estudo REV13 (pasta panorama do projeto, 15/10/2026), aba 40 (mensal: pico, média, dias úteis, engenheiro) e aba 39 (semanal), custo pela 04. PLANO DAS OBRAS; 343 = MOTOR TAF\ESTUDOS\TAF 343 CAESB SOBRADINHO - PLANEJAMENTO.xlsx (estudo de 27/09/2026 17:51).
A6: OBRA 342 SANEAGO UTR: HISTOGRAMA MENSAL | N6: TAF EMPRESA: GENTE DAS 3 OBRAS POR MÊS (soma dos picos)
A7: Mês | B7: Pico (pessoas) | C7: Média (pessoas) | D7: Dias úteis | E7: Engenheiros | F7: MO própria + serviços de campo previsto (R$, 04) | G7: Realizado: efetivo médio (digitar) | H7: Efetivo médio na 05. SEMANAS | I7: Realizado considerado | J7: Desvio (pessoas) | K7: Realizado: MO + equip. (R$, digitar) | L7: Desvio (R$) | N7: Mês | O7: 342 (pico) | P7: 343 (pico) | Q7: 281 (pico; Ricarlos informa) | R7: 342 + 343 | S7: TAF (3 obras) | T7: Efetivo disponível (digitar; Thadeu indica quem informa) | U7: A contratar | V7: Leitura
A8: 46266 | B8: ='04. PLANO DAS OBRAS'!C13 -> 1 | C8: ='04. PLANO DAS OBRAS'!C14 -> 0.9 | D8: 21 | E8: 0.9 | F8: ='04. PLANO DAS OBRAS'!C8+'04. PLANO DAS OBRAS'!C10 -> 0 | H8: =IFERROR(AVERAGEIFS('05. SEMANAS'!$F$5:$F$64,'05. SEMANAS'!$B$5:$B$64,"342",'05. SEMANAS'!$A$5:$A$64,">="&A8,'05. SEMANAS'!$A$5:$A$64,"<"&EDATE(A8,1)),"") | I8: =IF(G8<>"",G8,H8) | J8: =IF(I8="","",I8-C8) | L8: =IF(K8="","",K8-F8) | N8: =A8 -> 46266 | O8: =B8 -> 1 | P8: =IFERROR(INDEX($B$29:$B$44,MATCH(N8,$A$29:$A$44,0)),"SEM BASE") -> 4 | Q8: SEM BASE | R8: =IF(AND(ISNUMBER(O8),ISNUMBER(P8)),O8+P8,"SEM BASE") -> 5 | S8: =IF(AND(ISNUMBER(R8),ISNUMBER(Q8)),R8+Q8,"SEM BASE") -> SEM BASE | T8: PENDENTE | U8: =IF(NOT(ISNUMBER(T8)),"PENDENTE",IF(ISNUMBER(S8),MAX(0,ROUNDUP(S8-T8,0)),IF(ISNUMBER(R8),MAX(0,ROUNDUP(R8-T8,0)),"SEM BASE"))) -> PENDENTE | V8: =IF(NOT(ISNUMBER(T8)),"falta o efetivo disponível",IF(NOT(ISNUMBER(U8)),"SEM BASE",IF(U8>0,IF(ISNUMBER(S8),"contratar","contratar (mínimo, sem a 281)"),IF(ISNUMBER(S8),"tem gente","tem gente para 342 e 343; falta a 281")))) -> falta o efetivo disponível
A9: 46296 | B9: ='04. PLANO DAS OBRAS'!D13 -> 23 | C9: ='04. PLANO DAS OBRAS'!D14 -> 11.48 | D9: 21 | E9: 1 | F9: ='04. PLANO DAS OBRAS'!D8+'04. PLANO DAS OBRAS'!D10 -> 0 | H9: =IFERROR(AVERAGEIFS('05. SEMANAS'!$F$5:$F$64,'05. SEMANAS'!$B$5:$B$64,"342",'05. SEMANAS'!$A$5:$A$64,">="&A9,'05. SEMANAS'!$A$5:$A$64,"<"&EDATE(A9,1)),"") | I9: =IF(G9<>"",G9,H9) | J9: =IF(I9="","",I9-C9) | L9: =IF(K9="","",K9-F9) | N9: =A9 -> 46296 | O9: =B9 -> 23 | P9: =IFERROR(INDEX($B$29:$B$44,MATCH(N9,$A$29:$A$44,0)),"SEM BASE") -> 11.3108 | Q9: SEM BASE | R9: =IF(AND(ISNUMBER(O9),ISNUMBER(P9)),O9+P9,"SEM BASE") -> 34.3108 | S9: =IF(AND(ISNUMBER(R9),ISNUMBER(Q9)),R9+Q9,"SEM BASE") -> SEM BASE | T9: PENDENTE | U9: =IF(NOT(ISNUMBER(T9)),"PENDENTE",IF(ISNUMBER(S9),MAX(0,ROUNDUP(S9-T9,0)),IF(ISNUMBER(R9),MAX(0,ROUNDUP(R9-T9,0)),"SEM BASE"))) -> PENDENTE | V9: =IF(NOT(ISNUMBER(T9)),"falta o efetivo disponível",IF(NOT(ISNUMBER(U9)),"SEM BASE",IF(U9>0,IF(ISNUMBER(S9),"contratar","contratar (mínimo, sem a 281)"),IF(ISNUMBER(S9),"tem gente","tem gente para 342 e 343; falta a 281")))) -> falta o efetivo disponível
A10: 46327 | B10: ='04. PLANO DAS OBRAS'!E13 -> 23 | C10: ='04. PLANO DAS OBRAS'!E14 -> 17.22 | D10: 18 | E10: 1 | F10: ='04. PLANO DAS OBRAS'!E8+'04. PLANO DAS OBRAS'!E10 -> 112252.18 | H10: =IFERROR(AVERAGEIFS('05. SEMANAS'!$F$5:$F$64,'05. SEMANAS'!$B$5:$B$64,"342",'05. SEMANAS'!$A$5:$A$64,">="&A10,'05. SEMANAS'!$A$5:$A$64,"<"&EDATE(A10,1)),"") | I10: =IF(G10<>"",G10,H10) | J10: =IF(I10="","",I10-C10) | L10: =IF(K10="","",K10-F10) | N10: =A10 -> 46327 | O10: =B10 -> 23 | P10: =IFERROR(INDEX($B$29:$B$44,MATCH(N10,$A$29:$A$44,0)),"SEM BASE") -> 11.3108 | Q10: SEM BASE | R10: =IF(AND(ISNUMBER(O10),ISNUMBER(P10)),O10+P10,"SEM BASE") -> 34.3108 | S10: =IF(AND(ISNUMBER(R10),ISNUMBER(Q10)),R10+Q10,"SEM BASE") -> SEM BASE | T10: PENDENTE | U10: =IF(NOT(ISNUMBER(T10)),"PENDENTE",IF(ISNUMBER(S10),MAX(0,ROUNDUP(S10-T10,0)),IF(ISNUMBER(R10),MAX(0,ROUNDUP(R10-T10,0)),"SEM BASE"))) -> PENDENTE | V10: =IF(NOT(ISNUMBER(T10)),"falta o efetivo disponível",IF(NOT(ISNUMBER(U10)),"SEM BASE",IF(U10>0,IF(ISNUMBER(S10),"contratar","contratar (mínimo, sem a 281)"),IF(ISNUMBER(S10),"tem gente","tem gente para 342 e 343; falta a 281")))) -> falta o efetivo disponível
A11: 46357 | B11: ='04. PLANO DAS OBRAS'!F13 -> 43 | C11: ='04. PLANO DAS OBRAS'!F14 -> 39.68 | D11: 22 | E11: 1 | F11: ='04. PLANO DAS OBRAS'!F8+'04. PLANO DAS OBRAS'!F10 -> 83607.92 | H11: =IFERROR(AVERAGEIFS('05. SEMANAS'!$F$5:$F$64,'05. SEMANAS'!$B$5:$B$64,"342",'05. SEMANAS'!$A$5:$A$64,">="&A11,'05. SEMANAS'!$A$5:$A$64,"<"&EDATE(A11,1)),"") | I11: =IF(G11<>"",G11,H11) | J11: =IF(I11="","",I11-C11) | L11: =IF(K11="","",K11-F11) | N11: =A11 -> 46357 | O11: =B11 -> 43 | P11: =IFERROR(INDEX($B$29:$B$44,MATCH(N11,$A$29:$A$44,0)),"SEM BASE") -> 11.3108 | Q11: SEM BASE | R11: =IF(AND(ISNUMBER(O11),ISNUMBER(P11)),O11+P11,"SEM BASE") -> 54.3108 | S11: =IF(AND(ISNUMBER(R11),ISNUMBER(Q11)),R11+Q11,"SEM BASE") -> SEM BASE | T11: PENDENTE | U11: =IF(NOT(ISNUMBER(T11)),"PENDENTE",IF(ISNUMBER(S11),MAX(0,ROUNDUP(S11-T11,0)),IF(ISNUMBER(R11),MAX(0,ROUNDUP(R11-T11,0)),"SEM BASE"))) -> PENDENTE | V11: =IF(NOT(ISNUMBER(T11)),"falta o efetivo disponível",IF(NOT(ISNUMBER(U11)),"SEM BASE",IF(U11>0,IF(ISNUMBER(S11),"contratar","contratar (mínimo, sem a 281)"),IF(ISNUMBER(S11),"tem gente","tem gente para 342 e 343; falta a 281")))) -> falta o efetivo disponível
A12: 46388 | B12: ='04. PLANO DAS OBRAS'!G13 -> 27 | C12: ='04. PLANO DAS OBRAS'!G14 -> 21.4 | D12: 20 | E12: 1 | F12: ='04. PLANO DAS OBRAS'!G8+'04. PLANO DAS OBRAS'!G10 -> 395729.49 | H12: =IFERROR(AVERAGEIFS('05. SEMANAS'!$F$5:$F$64,'05. SEMANAS'!$B$5:$B$64,"342",'05. SEMANAS'!$A$5:$A$64,">="&A12,'05. SEMANAS'!$A$5:$A$64,"<"&EDATE(A12,1)),"") | I12: =IF(G12<>"",G12,H12) | J12: =IF(I12="","",I12-C12) | L12: =IF(K12="","",K12-F12) | N12: =A12 -> 46388 | O12: =B12 -> 27 | P12: =IFERROR(INDEX($B$29:$B$44,MATCH(N12,$A$29:$A$44,0)),"SEM BASE") -> 7.3108 | Q12: SEM BASE | R12: =IF(AND(ISNUMBER(O12),ISNUMBER(P12)),O12+P12,"SEM BASE") -> 34.3108 | S12: =IF(AND(ISNUMBER(R12),ISNUMBER(Q12)),R12+Q12,"SEM BASE") -> SEM BASE | T12: PENDENTE | U12: =IF(NOT(ISNUMBER(T12)),"PENDENTE",IF(ISNUMBER(S12),MAX(0,ROUNDUP(S12-T12,0)),IF(ISNUMBER(R12),MAX(0,ROUNDUP(R12-T12,0)),"SEM BASE"))) -> PENDENTE | V12: =IF(NOT(ISNUMBER(T12)),"falta o efetivo disponível",IF(NOT(ISNUMBER(U12)),"SEM BASE",IF(U12>0,IF(ISNUMBER(S12),"contratar","contratar (mínimo, sem a 281)"),IF(ISNUMBER(S12),"tem gente","tem gente para 342 e 343; falta a 281")))) -> falta o efetivo disponível
A13: 46419 | B13: ='04. PLANO DAS OBRAS'!H13 -> 27 | C13: ='04. PLANO DAS OBRAS'!H14 -> 19.89 | D13: 18 | E13: 1 | F13: ='04. PLANO DAS OBRAS'!H8+'04. PLANO DAS OBRAS'!H10 -> 176763.18 | H13: =IFERROR(AVERAGEIFS('05. SEMANAS'!$F$5:$F$64,'05. SEMANAS'!$B$5:$B$64,"342",'05. SEMANAS'!$A$5:$A$64,">="&A13,'05. SEMANAS'!$A$5:$A$64,"<"&EDATE(A13,1)),"") | I13: =IF(G13<>"",G13,H13) | J13: =IF(I13="","",I13-C13) | L13: =IF(K13="","",K13-F13) | N13: =A13 -> 46419 | O13: =B13 -> 27 | P13: =IFERROR(INDEX($B$29:$B$44,MATCH(N13,$A$29:$A$44,0)),"SEM BASE") -> 7.3108 | Q13: SEM BASE | R13: =IF(AND(ISNUMBER(O13),ISNUMBER(P13)),O13+P13,"SEM BASE") -> 34.3108 | S13: =IF(AND(ISNUMBER(R13),ISNUMBER(Q13)),R13+Q13,"SEM BASE") -> SEM BASE | T13: PENDENTE | U13: =IF(NOT(ISNUMBER(T13)),"PENDENTE",IF(ISNUMBER(S13),MAX(0,ROUNDUP(S13-T13,0)),IF(ISNUMBER(R13),MAX(0,ROUNDUP(R13-T13,0)),"SEM BASE"))) -> PENDENTE | V13: =IF(NOT(ISNUMBER(T13)),"falta o efetivo disponível",IF(NOT(ISNUMBER(U13)),"SEM BASE",IF(U13>0,IF(ISNUMBER(S13),"contratar","contratar (mínimo, sem a 281)"),IF(ISNUMBER(S13),"tem gente","tem gente para 342 e 343; falta a 281")))) -> falta o efetivo disponível
A14: 46447 | B14: ='04. PLANO DAS OBRAS'!I13 -> 43 | C14: ='04. PLANO DAS OBRAS'!I14 -> 20.89 | D14: 22 | E14: 1 | F14: ='04. PLANO DAS OBRAS'!I8+'04. PLANO DAS OBRAS'!I10 -> 147157.32 | H14: =IFERROR(AVERAGEIFS('05. SEMANAS'!$F$5:$F$64,'05. SEMANAS'!$B$5:$B$64,"342",'05. SEMANAS'!$A$5:$A$64,">="&A14,'05. SEMANAS'!$A$5:$A$64,"<"&EDATE(A14,1)),"") | I14: =IF(G14<>"",G14,H14) | J14: =IF(I14="","",I14-C14) | L14: =IF(K14="","",K14-F14) | N14: =A14 -> 46447 | O14: =B14 -> 43 | P14: =IFERROR(INDEX($B$29:$B$44,MATCH(N14,$A$29:$A$44,0)),"SEM BASE") -> 7.3108 | Q14: SEM BASE | R14: =IF(AND(ISNUMBER(O14),ISNUMBER(P14)),O14+P14,"SEM BASE") -> 50.3108 | S14: =IF(AND(ISNUMBER(R14),ISNUMBER(Q14)),R14+Q14,"SEM BASE") -> SEM BASE | T14: PENDENTE | U14: =IF(NOT(ISNUMBER(T14)),"PENDENTE",IF(ISNUMBER(S14),MAX(0,ROUNDUP(S14-T14,0)),IF(ISNUMBER(R14),MAX(0,ROUNDUP(R14-T14,0)),"SEM BASE"))) -> PENDENTE | V14: =IF(NOT(ISNUMBER(T14)),"falta o efetivo disponível",IF(NOT(ISNUMBER(U14)),"SEM BASE",IF(U14>0,IF(ISNUMBER(S14),"contratar","contratar (mínimo, sem a 281)"),IF(ISNUMBER(S14),"tem gente","tem gente para 342 e 343; falta a 281")))) -> falta o efetivo disponível
A15: 46478 | B15: ='04. PLANO DAS OBRAS'!J13 -> 34.5 | C15: ='04. PLANO DAS OBRAS'!J14 -> 23.12 | D15: 21 | E15: 1 | F15: ='04. PLANO DAS OBRAS'!J8+'04. PLANO DAS OBRAS'!J10 -> 100127.67 | H15: =IFERROR(AVERAGEIFS('05. SEMANAS'!$F$5:$F$64,'05. SEMANAS'!$B$5:$B$64,"342",'05. SEMANAS'!$A$5:$A$64,">="&A15,'05. SEMANAS'!$A$5:$A$64,"<"&EDATE(A15,1)),"") | I15: =IF(G15<>"",G15,H15) | J15: =IF(I15="","",I15-C15) | L15: =IF(K15="","",K15-F15) | N15: =A15 -> 46478 | O15: =B15 -> 34.5 | P15: =IFERROR(INDEX($B$29:$B$44,MATCH(N15,$A$29:$A$44,0)),"SEM BASE") -> 7.3108 | Q15: SEM BASE | R15: =IF(AND(ISNUMBER(O15),ISNUMBER(P15)),O15+P15,"SEM BASE") -> 41.8108 | S15: =IF(AND(ISNUMBER(R15),ISNUMBER(Q15)),R15+Q15,"SEM BASE") -> SEM BASE | T15: PENDENTE | U15: =IF(NOT(ISNUMBER(T15)),"PENDENTE",IF(ISNUMBER(S15),MAX(0,ROUNDUP(S15-T15,0)),IF(ISNUMBER(R15),MAX(0,ROUNDUP(R15-T15,0)),"SEM BASE"))) -> PENDENTE | V15: =IF(NOT(ISNUMBER(T15)),"falta o efetivo disponível",IF(NOT(ISNUMBER(U15)),"SEM BASE",IF(U15>0,IF(ISNUMBER(S15),"contratar","contratar (mínimo, sem a 281)"),IF(ISNUMBER(S15),"tem gente","tem gente para 342 e 343; falta a 281")))) -> falta o efetivo disponível
A16: 46508 | B16: ='04. PLANO DAS OBRAS'!K13 -> 29.5 | C16: ='04. PLANO DAS OBRAS'!K14 -> 21.39 | D16: 19 | E16: 1 | F16: ='04. PLANO DAS OBRAS'!K8+'04. PLANO DAS OBRAS'!K10 -> 141771.61 | H16: =IFERROR(AVERAGEIFS('05. SEMANAS'!$F$5:$F$64,'05. SEMANAS'!$B$5:$B$64,"342",'05. SEMANAS'!$A$5:$A$64,">="&A16,'05. SEMANAS'!$A$5:$A$64,"<"&EDATE(A16,1)),"") | I16: =IF(G16<>"",G16,H16) | J16: =IF(I16="","",I16-C16) | L16: =IF(K16="","",K16-F16) | N16: =A16 -> 46508 | O16: =B16 -> 29.5 | P16: =IFERROR(INDEX($B$29:$B$44,MATCH(N16,$A$29:$A$44,0)),"SEM BASE") -> 4 | Q16: SEM BASE | R16: =IF(AND(ISNUMBER(O16),ISNUMBER(P16)),O16+P16,"SEM BASE") -> 33.5 | S16: =IF(AND(ISNUMBER(R16),ISNUMBER(Q16)),R16+Q16,"SEM BASE") -> SEM BASE | T16: PENDENTE | U16: =IF(NOT(ISNUMBER(T16)),"PENDENTE",IF(ISNUMBER(S16),MAX(0,ROUNDUP(S16-T16,0)),IF(ISNUMBER(R16),MAX(0,ROUNDUP(R16-T16,0)),"SEM BASE"))) -> PENDENTE | V16: =IF(NOT(ISNUMBER(T16)),"falta o efetivo disponível",IF(NOT(ISNUMBER(U16)),"SEM BASE",IF(U16>0,IF(ISNUMBER(S16),"contratar","contratar (mínimo, sem a 281)"),IF(ISNUMBER(S16),"tem gente","tem gente para 342 e 343; falta a 281")))) -> falta o efetivo disponível
A17: 46539 | B17: ='04. PLANO DAS OBRAS'!L13 -> 31.5 | C17: ='04. PLANO DAS OBRAS'!L14 -> 21.3 | D17: 22 | E17: 1 | F17: ='04. PLANO DAS OBRAS'!L8+'04. PLANO DAS OBRAS'!L10 -> 97210.15 | H17: =IFERROR(AVERAGEIFS('05. SEMANAS'!$F$5:$F$64,'05. SEMANAS'!$B$5:$B$64,"342",'05. SEMANAS'!$A$5:$A$64,">="&A17,'05. SEMANAS'!$A$5:$A$64,"<"&EDATE(A17,1)),"") | I17: =IF(G17<>"",G17,H17) | J17: =IF(I17="","",I17-C17) | L17: =IF(K17="","",K17-F17) | N17: =A17 -> 46539 | O17: =B17 -> 31.5 | P17: =IFERROR(INDEX($B$29:$B$44,MATCH(N17,$A$29:$A$44,0)),"SEM BASE") -> 0 | Q17: SEM BASE | R17: =IF(AND(ISNUMBER(O17),ISNUMBER(P17)),O17+P17,"SEM BASE") -> 31.5 | S17: =IF(AND(ISNUMBER(R17),ISNUMBER(Q17)),R17+Q17,"SEM BASE") -> SEM BASE | T17: PENDENTE | U17: =IF(NOT(ISNUMBER(T17)),"PENDENTE",IF(ISNUMBER(S17),MAX(0,ROUNDUP(S17-T17,0)),IF(ISNUMBER(R17),MAX(0,ROUNDUP(R17-T17,0)),"SEM BASE"))) -> PENDENTE | V17: =IF(NOT(ISNUMBER(T17)),"falta o efetivo disponível",IF(NOT(ISNUMBER(U17)),"SEM BASE",IF(U17>0,IF(ISNUMBER(S17),"contratar","contratar (mínimo, sem a 281)"),IF(ISNUMBER(S17),"tem gente","tem gente para 342 e 343; falta a 281")))) -> falta o efetivo disponível
A18: 46569 | B18: ='04. PLANO DAS OBRAS'!M13 -> 28.5 | C18: ='04. PLANO DAS OBRAS'!M14 -> 17.95 | D18: 22 | E18: 1 | F18: ='04. PLANO DAS OBRAS'!M8+'04. PLANO DAS OBRAS'!M10 -> 163276.85 | H18: =IFERROR(AVERAGEIFS('05. SEMANAS'!$F$5:$F$64,'05. SEMANAS'!$B$5:$B$64,"342",'05. SEMANAS'!$A$5:$A$64,">="&A18,'05. SEMANAS'!$A$5:$A$64,"<"&EDATE(A18,1)),"") | I18: =IF(G18<>"",G18,H18) | J18: =IF(I18="","",I18-C18) | L18: =IF(K18="","",K18-F18) | N18: =A18 -> 46569 | O18: =B18 -> 28.5 | P18: =IFERROR(INDEX($B$29:$B$44,MATCH(N18,$A$29:$A$44,0)),"SEM BASE") -> 0 | Q18: SEM BASE | R18: =IF(AND(ISNUMBER(O18),ISNUMBER(P18)),O18+P18,"SEM BASE") -> 28.5 | S18: =IF(AND(ISNUMBER(R18),ISNUMBER(Q18)),R18+Q18,"SEM BASE") -> SEM BASE | T18: PENDENTE | U18: =IF(NOT(ISNUMBER(T18)),"PENDENTE",IF(ISNUMBER(S18),MAX(0,ROUNDUP(S18-T18,0)),IF(ISNUMBER(R18),MAX(0,ROUNDUP(R18-T18,0)),"SEM BASE"))) -> PENDENTE | V18: =IF(NOT(ISNUMBER(T18)),"falta o efetivo disponível",IF(NOT(ISNUMBER(U18)),"SEM BASE",IF(U18>0,IF(ISNUMBER(S18),"contratar","contratar (mínimo, sem a 281)"),IF(ISNUMBER(S18),"tem gente","tem gente para 342 e 343; falta a 281")))) -> falta o efetivo disponível
A19: 46600 | B19: ='04. PLANO DAS OBRAS'!N13 -> 15 | C19: ='04. PLANO DAS OBRAS'!N14 -> 3.45 | D19: 22 | E19: 0.91 | F19: ='04. PLANO DAS OBRAS'!N8+'04. PLANO DAS OBRAS'!N10 -> 89535.44 | H19: =IFERROR(AVERAGEIFS('05. SEMANAS'!$F$5:$F$64,'05. SEMANAS'!$B$5:$B$64,"342",'05. SEMANAS'!$A$5:$A$64,">="&A19,'05. SEMANAS'!$A$5:$A$64,"<"&EDATE(A19,1)),"") | I19: =IF(G19<>"",G19,H19) | J19: =IF(I19="","",I19-C19) | L19: =IF(K19="","",K19-F19) | N19: =A19 -> 46600 | O19: =B19 -> 15 | P19: =IFERROR(INDEX($B$29:$B$44,MATCH(N19,$A$29:$A$44,0)),"SEM BASE") -> 0 | Q19: SEM BASE | R19: =IF(AND(ISNUMBER(O19),ISNUMBER(P19)),O19+P19,"SEM BASE") -> 15 | S19: =IF(AND(ISNUMBER(R19),ISNUMBER(Q19)),R19+Q19,"SEM BASE") -> SEM BASE | T19: PENDENTE | U19: =IF(NOT(ISNUMBER(T19)),"PENDENTE",IF(ISNUMBER(S19),MAX(0,ROUNDUP(S19-T19,0)),IF(ISNUMBER(R19),MAX(0,ROUNDUP(R19-T19,0)),"SEM BASE"))) -> PENDENTE | V19: =IF(NOT(ISNUMBER(T19)),"falta o efetivo disponível",IF(NOT(ISNUMBER(U19)),"SEM BASE",IF(U19>0,IF(ISNUMBER(S19),"contratar","contratar (mínimo, sem a 281)"),IF(ISNUMBER(S19),"tem gente","tem gente para 342 e 343; falta a 281")))) -> falta o efetivo disponível
A20: 46631 | B20: ='04. PLANO DAS OBRAS'!O13 -> 0 | C20: ='04. PLANO DAS OBRAS'!O14 -> 0 | D20: 21 | E20: 0 | F20: ='04. PLANO DAS OBRAS'!O8+'04. PLANO DAS OBRAS'!O10 -> 10894.39 | H20: =IFERROR(AVERAGEIFS('05. SEMANAS'!$F$5:$F$64,'05. SEMANAS'!$B$5:$B$64,"342",'05. SEMANAS'!$A$5:$A$64,">="&A20,'05. SEMANAS'!$A$5:$A$64,"<"&EDATE(A20,1)),"") | I20: =IF(G20<>"",G20,H20) | J20: =IF(I20="","",I20-C20) | L20: =IF(K20="","",K20-F20) | N20: =A20 -> 46631 | O20: =B20 -> 0 | P20: =IFERROR(INDEX($B$29:$B$44,MATCH(N20,$A$29:$A$44,0)),"SEM BASE") -> 0 | Q20: SEM BASE | R20: =IF(AND(ISNUMBER(O20),ISNUMBER(P20)),O20+P20,"SEM BASE") -> 0 | S20: =IF(AND(ISNUMBER(R20),ISNUMBER(Q20)),R20+Q20,"SEM BASE") -> SEM BASE | T20: PENDENTE | U20: =IF(NOT(ISNUMBER(T20)),"PENDENTE",IF(ISNUMBER(S20),MAX(0,ROUNDUP(S20-T20,0)),IF(ISNUMBER(R20),MAX(0,ROUNDUP(R20-T20,0)),"SEM BASE"))) -> PENDENTE | V20: =IF(NOT(ISNUMBER(T20)),"falta o efetivo disponível",IF(NOT(ISNUMBER(U20)),"SEM BASE",IF(U20>0,IF(ISNUMBER(S20),"contratar","contratar (mínimo, sem a 281)"),IF(ISNUMBER(S20),"tem gente","tem gente para 342 e 343; falta a 281")))) -> falta o efetivo disponível
A21: 46661 | B21: ='04. PLANO DAS OBRAS'!P13 -> 0 | C21: ='04. PLANO DAS OBRAS'!P14 -> 0 | D21: 20 | E21: 0 | F21: ='04. PLANO DAS OBRAS'!P8+'04. PLANO DAS OBRAS'!P10 -> 0 | H21: =IFERROR(AVERAGEIFS('05. SEMANAS'!$F$5:$F$64,'05. SEMANAS'!$B$5:$B$64,"342",'05. SEMANAS'!$A$5:$A$64,">="&A21,'05. SEMANAS'!$A$5:$A$64,"<"&EDATE(A21,1)),"") | I21: =IF(G21<>"",G21,H21) | J21: =IF(I21="","",I21-C21) | L21: =IF(K21="","",K21-F21) | N21: =A21 -> 46661 | O21: =B21 -> 0 | P21: =IFERROR(INDEX($B$29:$B$44,MATCH(N21,$A$29:$A$44,0)),"SEM BASE") -> 0 | Q21: SEM BASE | R21: =IF(AND(ISNUMBER(O21),ISNUMBER(P21)),O21+P21,"SEM BASE") -> 0 | S21: =IF(AND(ISNUMBER(R21),ISNUMBER(Q21)),R21+Q21,"SEM BASE") -> SEM BASE | T21: PENDENTE | U21: =IF(NOT(ISNUMBER(T21)),"PENDENTE",IF(ISNUMBER(S21),MAX(0,ROUNDUP(S21-T21,0)),IF(ISNUMBER(R21),MAX(0,ROUNDUP(R21-T21,0)),"SEM BASE"))) -> PENDENTE | V21: =IF(NOT(ISNUMBER(T21)),"falta o efetivo disponível",IF(NOT(ISNUMBER(U21)),"SEM BASE",IF(U21>0,IF(ISNUMBER(S21),"contratar","contratar (mínimo, sem a 281)"),IF(ISNUMBER(S21),"tem gente","tem gente para 342 e 343; falta a 281")))) -> falta o efetivo disponível
A22: 46692 | B22: ='04. PLANO DAS OBRAS'!Q13 -> 0 | C22: ='04. PLANO DAS OBRAS'!Q14 -> 0 | D22: 19 | E22: 0 | F22: ='04. PLANO DAS OBRAS'!Q8+'04. PLANO DAS OBRAS'!Q10 -> 0 | H22: =IFERROR(AVERAGEIFS('05. SEMANAS'!$F$5:$F$64,'05. SEMANAS'!$B$5:$B$64,"342",'05. SEMANAS'!$A$5:$A$64,">="&A22,'05. SEMANAS'!$A$5:$A$64,"<"&EDATE(A22,1)),"") | I22: =IF(G22<>"",G22,H22) | J22: =IF(I22="","",I22-C22) | L22: =IF(K22="","",K22-F22) | N22: =A22 -> 46692 | O22: =B22 -> 0 | P22: =IFERROR(INDEX($B$29:$B$44,MATCH(N22,$A$29:$A$44,0)),"SEM BASE") -> 0 | Q22: SEM BASE | R22: =IF(AND(ISNUMBER(O22),ISNUMBER(P22)),O22+P22,"SEM BASE") -> 0 | S22: =IF(AND(ISNUMBER(R22),ISNUMBER(Q22)),R22+Q22,"SEM BASE") -> SEM BASE | T22: PENDENTE | U22: =IF(NOT(ISNUMBER(T22)),"PENDENTE",IF(ISNUMBER(S22),MAX(0,ROUNDUP(S22-T22,0)),IF(ISNUMBER(R22),MAX(0,ROUNDUP(R22-T22,0)),"SEM BASE"))) -> PENDENTE | V22: =IF(NOT(ISNUMBER(T22)),"falta o efetivo disponível",IF(NOT(ISNUMBER(U22)),"SEM BASE",IF(U22>0,IF(ISNUMBER(S22),"contratar","contratar (mínimo, sem a 281)"),IF(ISNUMBER(S22),"tem gente","tem gente para 342 e 343; falta a 281")))) -> falta o efetivo disponível
A23: 46722 | B23: ='04. PLANO DAS OBRAS'!R13 -> 0 | C23: ='04. PLANO DAS OBRAS'!R14 -> 0 | D23: 23 | E23: 0 | F23: ='04. PLANO DAS OBRAS'!R8+'04. PLANO DAS OBRAS'!R10 -> 0 | H23: =IFERROR(AVERAGEIFS('05. SEMANAS'!$F$5:$F$64,'05. SEMANAS'!$B$5:$B$64,"342",'05. SEMANAS'!$A$5:$A$64,">="&A23,'05. SEMANAS'!$A$5:$A$64,"<"&EDATE(A23,1)),"") | I23: =IF(G23<>"",G23,H23) | J23: =IF(I23="","",I23-C23) | L23: =IF(K23="","",K23-F23) | N23: =A23 -> 46722 | O23: =B23 -> 0 | P23: =IFERROR(INDEX($B$29:$B$44,MATCH(N23,$A$29:$A$44,0)),"SEM BASE") -> 0 | Q23: SEM BASE | R23: =IF(AND(ISNUMBER(O23),ISNUMBER(P23)),O23+P23,"SEM BASE") -> 0 | S23: =IF(AND(ISNUMBER(R23),ISNUMBER(Q23)),R23+Q23,"SEM BASE") -> SEM BASE | T23: PENDENTE | U23: =IF(NOT(ISNUMBER(T23)),"PENDENTE",IF(ISNUMBER(S23),MAX(0,ROUNDUP(S23-T23,0)),IF(ISNUMBER(R23),MAX(0,ROUNDUP(R23-T23,0)),"SEM BASE"))) -> PENDENTE | V23: =IF(NOT(ISNUMBER(T23)),"falta o efetivo disponível",IF(NOT(ISNUMBER(U23)),"SEM BASE",IF(U23>0,IF(ISNUMBER(S23),"contratar","contratar (mínimo, sem a 281)"),IF(ISNUMBER(S23),"tem gente","tem gente para 342 e 343; falta a 281")))) -> falta o efetivo disponível
A24: Pico / total | B24: =MAX(B8:B23) -> 43 | F24: =SUM(F8:F23) -> 1518326.2 | K24: =IF(COUNT(K8:K23)=0,"sem lançamento",SUM(K8:K23)) -> sem lançamento | N24: Pico | O24: =MAX(O8:O23) -> 43 | P24: =IF(COUNT(P8:P23)=0,"SEM BASE",MAX(P8:P23)) -> 11.3108 | Q24: =IF(COUNT(Q8:Q23)<16,"SEM BASE",MAX(Q8:Q23)) -> SEM BASE | R24: =IF(COUNT(R8:R23)=0,"SEM BASE",MAX(R8:R23)) -> 54.3108 | S24: =IF(COUNT(S8:S23)<16,"SEM BASE",MAX(S8:S23)) -> SEM BASE | T24: maior falta | U24: =IF(COUNT(U8:U23)=0,"PENDENTE",MAX(U8:U23)) -> PENDENTE
N25: Contratar a partir de | P25: =IF(COUNT(U8:U23)=0,"PENDENTE",IF(COUNTIF(U8:U23,">0")=0,"nenhum",_xlfn.MINIFS(N8:N23,U8:U23,">0"))) -> PENDENTE
A27: OBRA 343 CAESB SOBRADINHO: HISTOGRAMA MENSAL
A28: Mês | B28: Pico (pessoas) | C28: Média (pessoas) | D28: Dias úteis | E28: Engenheiros | F28: MO + equip. previsto (R$) | G28: Realizado: efetivo médio (digitar) | H28: Efetivo médio na 05. SEMANAS | I28: Realizado considerado | J28: Desvio (pessoas) | K28: Realizado: MO + equip. (R$, digitar) | L28: Desvio (R$)
A29: 46266 | B29: 4 | C29: 4 | D29: 21 | E29: 1 | F29: 55670.761 | H29: =IFERROR(AVERAGEIFS('05. SEMANAS'!$F$5:$F$64,'05. SEMANAS'!$B$5:$B$64,"343",'05. SEMANAS'!$A$5:$A$64,">="&A29,'05. SEMANAS'!$A$5:$A$64,"<"&EDATE(A29,1)),"") | I29: =IF(G29<>"",G29,H29) | J29: =IF(I29="","",I29-C29) | L29: =IF(K29="","",K29-F29)
A30: 46296 | B30: 11.3108 | C30: 11.3108 | D30: 21 | E30: 1 | F30: 212493.75 | H30: =IFERROR(AVERAGEIFS('05. SEMANAS'!$F$5:$F$64,'05. SEMANAS'!$B$5:$B$64,"343",'05. SEMANAS'!$A$5:$A$64,">="&A30,'05. SEMANAS'!$A$5:$A$64,"<"&EDATE(A30,1)),"") | I30: =IF(G30<>"",G30,H30) | J30: =IF(I30="","",I30-C30) | L30: =IF(K30="","",K30-F30)
A31: 46327 | B31: 11.3108 | C31: 11.3108 | D31: 18 | E31: 1 | F31: 182137.5 | H31: =IFERROR(AVERAGEIFS('05. SEMANAS'!$F$5:$F$64,'05. SEMANAS'!$B$5:$B$64,"343",'05. SEMANAS'!$A$5:$A$64,">="&A31,'05. SEMANAS'!$A$5:$A$64,"<"&EDATE(A31,1)),"") | I31: =IF(G31<>"",G31,H31) | J31: =IF(I31="","",I31-C31) | L31: =IF(K31="","",K31-F31)
A32: 46357 | B32: 11.3108 | C32: 7.6744364 | D32: 22 | E32: 1 | F32: 96993.948 | H32: =IFERROR(AVERAGEIFS('05. SEMANAS'!$F$5:$F$64,'05. SEMANAS'!$B$5:$B$64,"343",'05. SEMANAS'!$A$5:$A$64,">="&A32,'05. SEMANAS'!$A$5:$A$64,"<"&EDATE(A32,1)),"") | I32: =IF(G32<>"",G32,H32) | J32: =IF(I32="","",I32-C32) | L32: =IF(K32="","",K32-F32)
A33: 46388 | B33: 7.3108 | C33: 7.3108 | D33: 20 | E33: 1 | F33: 76756.449 | H33: =IFERROR(AVERAGEIFS('05. SEMANAS'!$F$5:$F$64,'05. SEMANAS'!$B$5:$B$64,"343",'05. SEMANAS'!$A$5:$A$64,">="&A33,'05. SEMANAS'!$A$5:$A$64,"<"&EDATE(A33,1)),"") | I33: =IF(G33<>"",G33,H33) | J33: =IF(I33="","",I33-C33) | L33: =IF(K33="","",K33-F33)
A34: 46419 | B34: 7.3108 | C34: 7.3108 | D34: 18 | E34: 1 | F34: 69080.804 | H34: =IFERROR(AVERAGEIFS('05. SEMANAS'!$F$5:$F$64,'05. SEMANAS'!$B$5:$B$64,"343",'05. SEMANAS'!$A$5:$A$64,">="&A34,'05. SEMANAS'!$A$5:$A$64,"<"&EDATE(A34,1)),"") | I34: =IF(G34<>"",G34,H34) | J34: =IF(I34="","",I34-C34) | L34: =IF(K34="","",K34-F34)
A35: 46447 | B35: 7.3108 | C35: 7.3108 | D35: 22 | E35: 1 | F35: 84432.094 | H35: =IFERROR(AVERAGEIFS('05. SEMANAS'!$F$5:$F$64,'05. SEMANAS'!$B$5:$B$64,"343",'05. SEMANAS'!$A$5:$A$64,">="&A35,'05. SEMANAS'!$A$5:$A$64,"<"&EDATE(A35,1)),"") | I35: =IF(G35<>"",G35,H35) | J35: =IF(I35="","",I35-C35) | L35: =IF(K35="","",K35-F35)
A36: 46478 | B36: 7.3108 | C36: 4.4729714 | D36: 21 | E36: 1 | F36: 59231.262 | H36: =IFERROR(AVERAGEIFS('05. SEMANAS'!$F$5:$F$64,'05. SEMANAS'!$B$5:$B$64,"343",'05. SEMANAS'!$A$5:$A$64,">="&A36,'05. SEMANAS'!$A$5:$A$64,"<"&EDATE(A36,1)),"") | I36: =IF(G36<>"",G36,H36) | J36: =IF(I36="","",I36-C36) | L36: =IF(K36="","",K36-F36)
